Workbook

Sheet README
A1: Cat home financial model (Checkpoint 4, Phase G)
A2: Investor-style e-commerce study | as of October 19, 2026 | US Shopify DTC
A4: PURPOSE
A5: Unit economics, 24-month cohort LTV, scenarios, sensitivities, launch cash and go/no-go gates for:
A6: BASE CASE: cat home brand - corded/USB stainless water fountain with a 90-day filter pack subscription (US-stocked filters), litter mat add-on.
A7: SHADOW CASE: espresso upgrade brand - De'Longhi Dedica / 51mm kit (portafilter, tamper, WDT, puck screen) with beans via Roastify / Dripshipper.
A9: IMPORTANT: inputs tagged ASSUMPTION are the analyst's planning values. They are NOT market facts and must be replaced with quotes, test results and real campaign data as they arrive. Only FILING / VENDOR / SECONDHAND rows trace to a cited source; ESTIMATE rows are arithmetic on cited inputs.
A11: SCENARIO SELECTOR
A12: Change Inputs!D3 (1 = Pessimistic, 2 = Base, 3 = Optimistic). Current selection: | B12: =Inputs!$D$3 -> 2 | C12: =Inputs!$E$3 -> Base
A13: Change Inputs!D4 (1 = Test stage: AliExpress + CPA m1-3; 2 = Private label + CPA m4-12) to choose which first order the cohort uses: | B13: =Inputs!$D$4 -> 2 | C13: =Inputs!$E$4 -> Private label (OEM + 3PL, CPA months 4-12)
A14: Change Inputs!D5 (1 = Lean, 2 = Moderate, 3 = Higher-capital) to choose the launch tier used by GoNoGo: | B14: =Inputs!$D$5 -> 1 | C14: =Inputs!$E$5 -> Lean
A15: The Scenarios sheet always shows all three scenarios side by side (independent engine columns), whatever the selector says.
A17: HOW TO USE
A18: 1. Edit only blue cells on light-yellow fill (Inputs sheet; shock sizes and two-way axes on Sensitivity). Everything else is a formula.
A19: 2. Read results: Cat_UnitEcon / Espresso_UnitEcon (per order), Cat_Cohort / Espresso_Cohort (24-month cohort, top block = selected scenario).
A20: 3. Compare: Scenarios (P/B/O both cases), Sensitivity (base-case shocks + CPA x attach tables), Launch_Budget (cash), GoNoGo (gates).
A21: 4. Engine columns/blocks to the right of / below the selected views feed Scenarios and Sensitivity. Do not edit them.
A23: COLOR LEGEND
A24: Input (hardcoded, editable) | B24: 123.45
A25: Selector / key control | B25: 2
A26: Formula (calculation) | B26: =B24*2 -> 246.9
A27: Formula that links to another sheet | B27: =Inputs!$D$3 -> 2
A28: Key output | B28: =B24 -> 123.45
A30: SHEETS
A31: Inputs - every driver with Pessimistic / Base / Optimistic, Selected (CHOOSE on D3), source tag and URL/note; USPS rate card; launch tiers; gate thresholds.
A32: Cat_UnitEcon - (a) fountain first order at test stage, (b) at private label, (c) fountain + mat bundle, (d) filter renewal, (e) one-time filter order; contribution before ads, after CPA, break-even CPA.
A33: Cat_Cohort - 100 customers, 3 segments (one-time, occasional repeat, subscribers), monthly contribution, cumulative after CAC, payback, 12/24-month contribution LTV.
A34: Espresso_UnitEcon / Espresso_Cohort - same structure for the shadow case (monthly bean subscription).
A35: Scenarios - P/B/O outputs for both cases. Sensitivity - CPA +30%, COGS +15%, shipping +20%, attach -50%, churn +50%, returns 2x; two-way tables.
A36: Launch_Budget - lean / moderate / higher-capital one-time costs, monthly fixed costs, test ads, cash before first PL sale, runway, break-even volume.
A37: GoNoGo - model-derived CPA ceilings, margin, payback, LTV:CAC, renewal economics, minimum attach and cash gates with GO / CONDITIONAL / NO-GO.
A38: Repositioned - base-cost tests of repositioned offers (R1 $79 easy-clean system; R2 = R1 + 6-month 12-filter subscription; R3 = R2 + affiliate/organic CPA cut; R4 = R2 + non-China OEM; R6 = all cat levers; R5 = espresso kit at $99), each with its own cohort, launch cash and gate results.
A40: CONVENTIONS
A41: LTV = contribution profit (net revenue less all variable costs), never revenue. First-order profitability is reported separately everywhere.
A42: Month 1 = acquisition month. Filter renewals bill every 3 months from month 4 (90-day pack). Bean renewals bill monthly from month 2.
... A60: Inputs research: research_notes/Cat home financial model/cost_inputs.md and acquisition_retention.md; reports/Espresso and cat validation.md (CP3); reports/Category brand subscription deep dive.md (CP2). Client defaults: CP3 Section 9.

Sheet Inputs
A1: Inputs: every driver, Pessimistic / Base / Optimistic, with Selected column
A2: Blue cells on light-yellow fill are inputs. Black cells are formulas. Rows tagged ASSUMPTION are the analyst's planning values, NOT market facts. As of Oct 19, 2026 (Checkpoint 4).
B3: Scenario selector: 1 = Pessimistic, 2 = Base, 3 = Optimistic | D3: 2 | E3: =CHOOSE($D$3,"Pessimistic","Base","Optimistic") -> Base
B4: First-order / cohort stage: 1 = Test stage (AliExpress + CPA months 1-3); 2 = Private label (CPA months 4-12) | D4: 2 | E4: =CHOOSE($D$4,"Test stage (AliExpress dropship, CPA months 1-3)","Private label (OEM + 3PL, CPA months 4-12)") -> Private label (OEM + 3PL, CPA months 4-12)
B5: Launch budget tier: 1 = Lean, 2 = Moderate, 3 = Higher-capital | D5: 1 | E5: =CHOOSE($D$5,"Lean","Moderate","Higher-capital") -> Lean
A7: ID | B7: Driver | C7: Unit | D7: Pessimistic | E7: Base | F7: Optimistic | G7: Selected | H7: Source tag | I7: Source URL / note
B8: Model controls
A9: cohort_size | B9: Cohort size (customers acquired) | C9: customers | D9: 100 | E9: 100 | F9: 100 | G9: =CHOOSE($D$3,D9,E9,F9) -> 100 | H9: ASSUMPTION | I9: Structural: 100-customer cohort per Checkpoint 4 spec.
B10: A. Retail prices (customer-facing, free shipping unless stated)
A11: p_fountain | B11: Cat fountain (corded/USB stainless) retail price | C11: $/unit | D11: 44.99 | E11: 49.99 | F11: 59.99 | G11: =CHOOSE($D$3,D11,E11,F11) -> 49.99 | H11: ASSUMPTION | I11: Feature tier $35-$65: Petlibro Dockstream $60.89-$62.99, Capsule $36.99 (Cats.com, Sep 18 2026, https://cats.com/best-cat-water-fountain). CP3 landed-cost table used $49.99. Amazon generics $18.99-$19.99 (CP3 Sec.2).
A12: p_filter_onetime | B12: Filter 90-day pack (6 filters), one-time price | C12: $/pack | D12: 14.99 | E12: 16.99 | F12: 17.49 | G12: =CHOOSE($D$3,D12,E12,F12) -> 16.99 | H12: ASSUMPTION | I12: CONFLICT: CP2 suggested ~$19.99/quarter; CP3 says price under Petlibro ~$2.62/filter subscribed = $15.72 per 6 (https://petlibro.com/products/dockstream-2-smart-fountain-replacement-filter). Conservative: subscription price kept under the CP3 anchor.
A13: sub_disc | B13: Subscription discount on filter pack | C13: % | D13: 0.15 | E13: 0.1 | F13: 0.1 | G13: =CHOOSE($D$3,D13,E13,F13) -> 0.1 | H13: ASSUMPTION | I13: Petlibro 30% first order then 10%; Chewy 35% first Autoship (CP2/CP3).
A14: p_filter_sub | B14: Filter pack subscription price (formula) | C14: $/pack | D14: =D12*(1-D13) -> 12.7415 | E14: =E12*(1-E13) -> 15.291 | F14: =F12*(1-F13) -> 15.741 | G14: =CHOOSE($D$3,D14,E14,F14) -> 15.291 | H14: ESTIMATE | I14: One-time price x (1 - discount). Base $15.29 = $2.55/filter, under the $2.62 Petlibro anchor.
A15: filters_per_pack | B15: Filters per 90-day pack | C15: filters | D15: 6 | E15: 6 | F15: 6 | G15: =CHOOSE($D$3,D15,E15,F15) -> 6 | H15: ASSUMPTION | I15: Client-approved default: 90-day 6-pack cadence (CP3 Sec.9 #5).
A16: ship_charge_filter | B16: Shipping charged on one-time (non-subscription) filter orders | C16: $/order | D16: 0 | E16: 0 | F16: 3.99 | G16: =CHOOSE($D$3,D16,E16,F16) -> 0 | H16: ASSUMPTION | I16: Base keeps free shipping to compete with Prime generic filters (32 for $16.99, CP3 Sec.5).
A17: p_mat | B17: Litter mat add-on price | C17: $/unit | D17: 16.99 | E17: 19.99 | F17: 22.99 | G17: =CHOOSE($D$3,D17,E17,F17) -> 19.99 | H17: ASSUMPTION | I17: Amazon Cat Litter Mats best sellers $8-$23 (CP3 Sec.2, https://www.amazon.com/Best-Sellers-Pet-Supplies-Cat-Litter-Mats/zgbs/pet-supplies/17295526011).
A18: p_kit | B18: Espresso Dedica 51mm upgrade kit price (portafilter + tamper + WDT + puck screen) | C18: $/kit | D18: 74.99 | E18: 84.99 | F18: 99.99 | G18: =CHOOSE($D$3,D18,E18,F18) -> 84.99 | H18: ASSUMPTION | I18: Espresso first-order AOV assumption $70/$85/$105 (acquisition_retention.md Q2). Dedica Essential stack $90-$120 (https://completehomebarista.com/guides/best-upgrades-delonghi-dedica-ec685). Amazon 7-pc Breville kit $42.98-$45.99 anchor.
A19: kit_pieces | B19: Pieces (picks) per espresso kit | C19: items | D19: 4 | E19: 4 | F19: 4 | G19: =CHOOSE($D$3,D19,E19,F19) -> 4 | H19: ASSUMPTION | I19: Kit composition used in the model.
A20: p_beans_onetime | B20: Beans shipment (2 x 12oz), one-time price incl. shipping | C20: $/shipment | D20: 37.99 | E20: 39.99 | F20: 43.99 | G20: =CHOOSE($D$3,D20,E20,F20) -> 39.99 | H20: ASSUMPTION | I20: CP2 bean subscription anchor $34-$40 incl. shipping (Trade, Bean Box, Atlas).
A21: bean_sub_disc | B21: Bean subscription discount | C21: % | D21: 0.1 | E21: 0.1 | F21: 0.1 | G21: =CHOOSE($D$3,D21,E21,F21) -> 0.1 | H21: ASSUMPTION | I21: Mirrors filter discount.
A22: p_beans_sub | B22: Beans shipment subscription price (formula) | C22: $/shipment | D22: =D20*(1-D21) -> 34.191 | E22: =E20*(1-E21) -> 35.991 | F22: =F20*(1-F21) -> 39.591 | G22: =CHOOSE($D$3,D22,E22,F22) -> 35.991 | H22: ESTIMATE | I22: One-time x (1 - discount).
A23: bags_per_ship | B23: 12oz bags per bean shipment | C23: bags | D23: 2 | E23: 2 | F23: 2 | G23: =CHOOSE($D$3,D23,E23,F23) -> 2 | H23: ASSUMPTION | I23: CP2 offer: 2 x 12oz every 2-4 weeks; modeled monthly.
B24: B. COGS - test stage (AliExpress via AutoDS dropship; supplier ships free)
A25: ali_fountain | B25: AliExpress corded stainless fountain unit price | C25: $/unit | D25: 34.08 | E25: 28.39 | F25: 21.79 | G25: =CHOOSE($D$3,D25,E25,F25) -> 28.39 | H25: VENDOR | I25: CP3 Sec.3.2: ROJECO 2L 'US Adapter New' $28.39 (https://www.aliexpress.us/item/3256808061782685.html); search band $21.79-$42.81; listed $26.91-$34.08. Welcome prices may vanish.
A26: test_duty | B26: Duty / price pass-through on China parcels (test stage) | C26: % of item | D26: 0.375 | E26: 0.3 | F26: 0 | G26: =CHOOSE($D$3,D26,E26,F26) -> 0.3 | H26: ESTIMATE | I26: Unresolved whether AliExpress collects duty (CP3 Case A 0% vs Case B). cost_inputs.md Q4 planning: 25-40%, ~30%. Pess = full 37.5% stack.
A27: autods_fee | B27: AutoDS wallet / card fee on supplier cost | C27: % of item | D27: 0.05 | E27: 0.05 | F27: 0 | G27: =CHOOSE($D$3,D27,E27,F27) -> 0.05 | H27: SECONDHAND | I27: CONFLICT: CP3 cites AutoDS help (5% card, https://help.autods.com/en/articles/12700443-automate-your-orders-with-fulfilled-by-autods-fba); cost_inputs.md says not verified (base 0%). Conservative base = 5%.
A28: test_lost | B28: Duty-refused / lost / re-ship parcels (test stage) | C28: % of orders | D28: 0.07 | E28: 0.05 | F28: 0.02 | G28: =CHOOSE($D$3,D28,E28,F28) -> 0.05 | H28: ASSUMPTION | I28: cost_inputs.md Q4: budget ~5% risk of duty-due refusals or re-ships; returns to China uneconomic.
A29: ali_pf | B29: AliExpress 51mm Dedica bottomless portafilter | C29: $/unit | D29: 25.66 | E29: 17.53 | F29: 17.01 | G29: =CHOOSE($D$3,D29,E29,F29) -> 17.53 | H29: VENDOR | I29: Listing 3256809164814557: $17.01-$25.66 (https://www.aliexpress.us/item/3256809164814557.html).
A30: ali_tamper | B30: AliExpress 51mm tamper | C30: $/unit | D30: 14.09 | E30: 13.28 | F30: 12.37 | G30: =CHOOSE($D$3,D30,E30,F30) -> 13.28 | H30: VENDOR | I30: PERFFEE 51mm $13.28-$14.09 (https://www.aliexpress.us/item/3256806759653263.html); same 51mm listing $12.37-$13.99.
A31: ali_wdt | B31: AliExpress WDT tool | C31: $/unit | D31: 13.09 | E31: 6.33 | F31: 1.14 | G31: =CHOOSE($D$3,D31,E31,F31) -> 6.33 | H31: VENDOR | I31: $13.09 clicked SKU; $6.33 low of search band; $1.14 Bundle Deals welcome price (CP3 Sec.3.1).
A32: ali_screen | B32: AliExpress 51mm puck screen | C32: $/unit | D32: 11.14 | E32: 4.98 | F32: 1.29 | G32: =CHOOSE($D$3,D32,E32,F32) -> 4.98 | H32: VENDOR | I32: 51mm magnet $11.14; 2-pc $9.95 (=$4.98/pc); 51mm 1-pc welcome $1.29 (https://www.aliexpress.us/item/3256809211885821.html).
A33: ali_kit | B33: AliExpress Dedica kit component cost (formula) | C33: $/kit | D33: =D29+D30+D31+D32 -> 63.98 | E33: =E29+E30+E31+E32 -> 42.12 | F33: =F29+F30+F31+F32 -> 31.81 | G33: =CHOOSE($D$3,D33,E33,F33) -> 42.12 | H33: ESTIMATE | I33: Sum of components; arrives as several parcels (CP3).
A34: test_duty_esp | B34: Duty / pass-through on espresso parcels (test stage) | C34: % of item | D34: 0.414 | E34: 0.3 | F34: 0 | G34: =CHOOSE($D$3,D34,E34,F34) -> 0.3 | H34: ESTIMATE | I34: Pess = List 3 25% + 12.5% forced-labor 301 + ~3.9% MFN; base 30% planning pass-through; opt Case A.
B35: C. COGS - private-label stage, cat (OEM, sea LCL, 3PL)
A36: oem_fountain | B36: OEM corded stainless fountain FOB (500 MOQ) | C36: $/unit | D36: 10.83 | E36: 9.77 | F36: 6.66 | G36: =CHOOSE($D$3,D36,E36,F36) -> 9.77 | H36: VENDOR | I36: Petwant 2L $6.66-$7.33, 2.7L $9.77-$10.52 at 500 MOQ (https://www.alibaba.com/product-detail/Petwant-OEM-ODM-2-7L-Stainless_1601927624978.html); CP2 wholesale $10.00-$10.83. Search-card data; fresh quotes needed. Non-China quotes requested in parallel (client default).
A37: adapter_premium | B37: UL 1310 / ETL-listed adapter premium | C37: $/unit | D37: 3 | E37: 2 | F37: 1.5 | G37: =CHOOSE($D$3,D37,E37,F37) -> 2 | H37: ASSUMPTION | I37: cost_inputs.md Q5: +$1.50-$3.00 vs unlisted; only retail listed-adapter prices found ($6.55-$10.98).
A38: fountain_freight | B38: Ocean LCL freight + destination charges per fountain | C38: $/unit | D38: 5 | E38: 3.5 | F38: 2.2 | G38: =CHOOSE($D$3,D38,E38,F38) -> 3.5 | H38: ESTIMATE | I38: CONFLICT: CP3 $1.00-$2.50 (unsourced) vs cost_inputs.md Q3 $2.20-$4.60, base $3.50, $5.00 at 2026 peak. Conservative base $3.50.
A39: fountain_duty | B39: Fountain duty stack (HTS 8413.70.2004: MFN 0% + 301 List 1 25% + 301 forced-labor 12.5%) | C39: % of FOB | D39: 0.375 | E39: 0.375 | F39: 0.375 | G39: =CHOOSE($D$3,D39,E39,F39) -> 0.375 | H39: FILING | I39: CBP rulings N303286/N303288 (https://www.tarifflens.ai/rulings/N303286); 12.5% from Jul 24 2026 (https://www.chrobinson.com/en-us/resources/blog/section-301-forced-labor-tariffs/). Section 232 risk unverified (broker).
A40: moq_fountain | B40: Units per import entry (fountain MOQ) | C40: units | D40: 500 | E40: 500 | F40: 1000 | G40: =CHOOSE($D$3,D40,E40,F40) -> 500 | H40: ASSUMPTION | I40: Client default: commit 500-1,000 MOQ only after creative win + passed samples (CP3 Sec.9 #3).
A41: broker_fee | B41: Customs broker entry fee | C41: $/entry | D41: 250 | E41: 150 | F41: 100 | G41: =CHOOSE($D$3,D41,E41,F41) -> 150 | H41: VENDOR | I41: $100-$250 (Strix), $150-$350 (GingerControl) (https://strixsmart.com/resources/blog/customs-broker-cost).
A42: isf_fee | B42: ISF filing | C42: $/entry | D42: 75 | E42: 50 | F42: 30 | G42: =CHOOSE($D$3,D42,E42,F42) -> 50 | H42: VENDOR | I42: $30-$75 per filing (Strix; Suaid).
A43: bond_fee | B43: Customs bond (single-entry) | C43: $/entry | D43: 75 | E43: 75 | F43: 40 | G43: =CHOOSE($D$3,D43,E43,F43) -> 75 | H43: VENDOR | I43: Clearit: $5 per $1,000, $40 min + $35 prep (https://clearitusa.com/customs-clearance-pricing-rates/).
A44: mpf_rate | B44: Merchandise Processing Fee rate (FY2026) | C44: % of value | D44: 0.003464 | E44: 0.003464 | F44: 0.003464 | G44: =CHOOSE($D$3,D44,E44,F44) -> 0.003464 | H44: FILING | I44: CBP Dec. 25-10 via GHY (https://www.ghy.com/trade-compliance/cbp-customs-user-fees-fy-2026/). FY2027 values not found (gap).
A45: mpf_min | B45: MPF minimum per formal entry | C45: $/entry | D45: 33.58 | E45: 33.58 | F45: 33.58 | G45: =CHOOSE($D$3,D45,E45,F45) -> 33.58 | H45: FILING | I45: FY2026.
A46: mpf_max | B46: MPF maximum per formal entry | C46: $/entry | D46: 651.5 | E46: 651.5 | F46: 651.5 | G46: =CHOOSE($D$3,D46,E46,F46) -> 651.5 | H46: FILING | I46: FY2026.
A47: hmf_rate | B47: Harbor Maintenance Fee (ocean) | C47: % of value | D47: 0.00125 | E47: 0.00125 | F47: 0.00125 | G47: =CHOOSE($D$3,D47,E47,F47) -> 0.00125 | H47: FILING | I47: 0.125% of value, ocean only.
... A59: filter_pack_pkg | B59: Filter pack pouch / sleeve | C59: $/pack | D59: 0.3 | E59: 0.2 | F59: 0.15 | G59: =CHOOSE($D$3,D59,E59,F59) -> 0.2 | H59: ASSUMPTION | I59: No packaging quote found.
B60: D. COGS - private-label stage, espresso Dedica kit (SHADOW CASE)
A61: oem_pf | B61: OEM 51mm bottomless portafilter FOB | C61: $/unit | D61: 33.5 | E61: 12 | F61: 8.47 | G61: =CHOOSE($D$3,D61,E61,F61) -> 12 | H61: VENDOR | I61: CONFLICT: only 51mm-specific OEM is Everich $32-$35/set at 100 MOQ (https://www.alibaba.com/product-detail/51mm-53mm-54mm-55mm-Coffee-Espresso_1600223449255.html) vs 54mm Nuoda ~$10-$12 (logo 50) and Shenzhen Magic $8.47. Base uses $12 (54mm proxy); pess carries Everich.
A62: oem_tamper | B62: OEM 51mm tamper FOB | C62: $/unit | D62: 5 | E62: 4 | F62: 3 | G62: =CHOOSE($D$3,D62,E62,F62) -> 4 | H62: ASSUMPTION | I62: No tamper OEM price visible (CP3 Sec.3.3).
A63: oem_wdt | B63: OEM WDT tool FOB | C63: $/unit | D63: 2.5 | E63: 1.8 | F63: 1.2 | G63: =CHOOSE($D$3,D63,E63,F63) -> 1.8 | H63: ASSUMPTION | I63: Custom WDT MOQ 5, price not visible.
A64: oem_screen | B64: OEM 51mm puck screen FOB | C64: $/unit | D64: 2 | E64: 1.5 | F64: 1 | G64: =CHOOSE($D$3,D64,E64,F64) -> 1.5 | H64: ASSUMPTION | I64: Custom-logo screen MOQ 200, $2 sample; unit price not visible.
A65: oem_kit | B65: OEM Dedica kit FOB (formula) | C65: $/kit | D65: =D61+D62+D63+D64 -> 43 | E65: =E61+E62+E63+E64 -> 19.3 | F65: =F61+F62+F63+F64 -> 13.67 | G65: =CHOOSE($D$3,D65,E65,F65) -> 19.3 | H65: ESTIMATE | I65: Sum of components.
A66: esp_duty | B66: Espresso tool duty stack | C66: % of FOB | D66: 0.414 | E66: 0.414 | F66: 0.279 | G66: =CHOOSE($D$3,D66,E66,F66) -> 0.414 | H66: ESTIMATE | I66: CONFLICT: CP3 24%-36.5% + MFN (list status unverified) vs cost_inputs.md Q4 List 3 25% + 12.5% + MFN 3.7-3.9% (CBP N335954). Conservative base 41.4%.
A67: esp_freight | B67: Freight per kit | C67: $/kit | D67: 2.5 | E67: 1.5 | F67: 1 | G67: =CHOOSE($D$3,D67,E67,F67) -> 1.5 | H67: ASSUMPTION | I67: CP3 placeholder $1.50 freight.
A68: esp_moq | B68: Kits per import entry | C68: units | D68: 100 | E68: 200 | F68: 300 | G68: =CHOOSE($D$3,D68,E68,F68) -> 200 | H68: ASSUMPTION | I68: Espresso OEM MOQs 20-600 (CP3 Sec.3.3).
A69: esp_packaging | B69: Kit retail box + insert | C69: $/kit | D69: 1.5 | E69: 1 | F69: 0.7 | G69: =CHOOSE($D$3,D69,E69,F69) -> 1 | H69: ASSUMPTION | I69: No quote.
A70: esp_cert_units | B70: Kits over which Prop 65 + food-contact tests are amortized | C70: units | D70: 300 | E70: 500 | F70: 1000 | G70: =CHOOSE($D$3,D70,E70,F70) -> 500 | H70: ASSUMPTION | I70: Prop 65 lead-in-brass exposure (CP3 Sec.3.6); uses Prop 65 and food-contact costs above.
B71: E. Beans - US roaster dropship (SHADOW CASE; Roastify / Dripshipper published rates)
A72: bean_bag | B72: Roaster wholesale cost per 12oz bag | C72: $/bag | D72: 13.2 | E72: 12 | F72: 9.39 | G72: =CHOOSE($D$3,D72,E72,F72) -> 12 | H72: VENDOR | I72: CONFLICT: Roastify member bag $12.00 + ship (https://roastify.app/pricing) vs Dripshipper '$9.39+' free shipping (https://www.dripshipper.io/bulk-espresso-beans) vs merchant anecdote ~$14 landed. Base = Roastify (conservative); pess +10% drift (ASSUMPTION).
A73: roaster_ship_first | B73: Roaster dropship shipping, first item | C73: $/shipment | D73: 4.5 | E73: 4.5 | F73: 0 | G73: =CHOOSE($D$3,D73,E73,F73) -> 4.5 | H73: VENDOR | I73: Roastify $4.50 first item; Dripshipper free shipping (opt).
A74: roaster_ship_add | B74: Roaster dropship shipping, each additional item | C74: $/item | D74: 1.25 | E74: 1.25 | F74: 0 | G74: =CHOOSE($D$3,D74,E74,F74) -> 1.25 | H74: VENDOR | I74: Roastify $1.25.
B75: F. USPS Ground Advantage COMMERCIAL rate card - here columns D / E / F = Zone 2 / Zone 5 / Zone 8 (not scenarios) | I75: USPS Notice 123, edition effective Oct 4, 2026 (https://pe.usps.com/text/dmm300/Notice123.htm); includes temporary 8% surcharge to Jan 17, 2027.
A76: rc_05 | B76: Up to 8 oz (filter pack mailer) | C76: $/parcel | D76: 7.34 | E76: 8.24 | F76: 8.95 | G76: n/a | H76: VENDOR | I76: Official USPS price list (tool-extracted; verify cells).
A77: rc_1 | B77: 1 lb | C77: $/parcel | D77: 8.08 | E77: 9.29 | F77: 11.22 | G77: n/a | H77: VENDOR | I77: Official USPS price list.
A78: rc_2 | B78: 2 lb (boxed fountain, 10x10x8 = 800 cu in, actual weight billed) | C78: $/parcel | D78: 8.48 | E78: 10.5 | F78: 13.42 | G78: n/a | H78: VENDOR | I78: Below 1,728 cu in so USPS bills actual weight.
A79: rc_3 | B79: 3 lb (fountain + mat; espresso kit) | C79: $/parcel | D79: 9.06 | E79: 12.12 | F79: 16.3 | G79: n/a | H79: VENDOR | I79: Official USPS price list.
B80: G. Shipping per order (scenario): Pess = avg of Zone 5 & 8; Base = Zone 5; Opt = Zone 5 after 8% surcharge expiry
A81: usps_surcharge | B81: USPS temporary surcharge in current rates | C81: % | D81: 0.08 | E81: 0.08 | F81: 0.08 | G81: =CHOOSE($D$3,D81,E81,F81) -> 0.08 | H81: SECONDHAND | I81: 8% Apr 26 2026 - Jan 17 2027 (https://www.ship.com/post/usps-rate-changes-july-2026). Base/pess keep it (a Jan 2027 GRI may offset expiry).
A82: below_comm | B82: Below-commercial (ounce-tier) discount on <=8 oz parcels | C82: % | D82: 0 | E82: 0 | F82: 0.15 | G82: =CHOOSE($D$3,D82,E82,F82) -> 0 | H82: ASSUMPTION | I82: Pirate Ship/Shopify keep ounce tiers below Notice 123 commercial (https://support.pirateship.com/en/articles/15453569-july-2026-usps-rate-and-rule-changes); cells not retrievable, so base uses commercial as ceiling.
A83: post_fountain | B83: Postage: fountain order (2 lb) | C83: $/order | D83: =AVERAGE(E78,F78) -> 11.96 | E83: =E78 -> 10.5 | F83: =E78/(1+F81) -> 9.7222222 | G83: =CHOOSE($D$3,D83,E83,F83) -> 10.5 | H83: ESTIMATE | I83: From rate card (formula).
A84: post_bundle | B84: Postage: fountain + litter mat bundle (3 lb) | C84: $/order | D84: =AVERAGE(E79,F79) -> 14.21 | E84: =E79 -> 12.12 | F84: =E79/(1+F81) -> 11.222222 | G84: =CHOOSE($D$3,D84,E84,F84) -> 12.12 | H84: ESTIMATE | I84: From rate card (formula).
A85: post_filter | B85: Postage: filter 6-pack mailer (<=8 oz) | C85: $/order | D85: =AVERAGE(E76,F76)*(1-D82) -> 8.595 | E85: =E76*(1-E82) -> 8.24 | F85: =E76/(1+F81)*(1-F82) -> 6.4851852 | G85: =CHOOSE($D$3,D85,E85,F85) -> 8.24 | H85: ESTIMATE | I85: From rate card x (1 - below-commercial discount).
A86: post_kit | B86: Postage: espresso kit (3 lb) | C86: $/order | D86: =AVERAGE(E79,F79) -> 14.21 | E86: =E79 -> 12.12 | F86: =E79/(1+F81) -> 11.222222 | G86: =CHOOSE($D$3,D86,E86,F86) -> 12.12 | H86: ESTIMATE | I86: Portafilter + tamper + tools ~1.2 kg packed (ASSUMPTION on weight).
B87: H. 3PL fulfillment (private-label stage)
A88: pick_first | B88: Pick/pack, first item | C88: $/order | D88: 3.25 | E88: 3 | F88: 2 | G88: =CHOOSE($D$3,D88,E88,F88) -> 3 | H88: SECONDHAND | I88: Fulfill.com 2026: $2-$3 typical, survey avg $3.20, card median ~$2.00 (https://fulfill.com/3pl-pricing). CP3 used $3.25 (Fulfyld).
A89: pick_add | B89: Pick, each additional item | C89: $/item | D89: 0.75 | E89: 0.5 | F89: 0.4 | G89: =CHOOSE($D$3,D89,E89,F89) -> 0.5 | H89: SECONDHAND | I89: Fulfill.com $0.30-$0.75, avg $0.48.
A90: carton | B90: Shipping carton for fountain / kit | C90: $/order | D90: 1.5 | E90: 1.25 | F90: 1 | G90: =CHOOSE($D$3,D90,E90,F90) -> 1.25 | H90: ASSUMPTION | I90: cost_inputs.md Q2: $1.00-$1.50 if 3PL supplies 10x10x8.
A91: mailer | B91: Poly mailer for filter pack | C91: $/order | D91: 0.75 | E91: 0.5 | F91: 0.35 | G91: =CHOOSE($D$3,D91,E91,F91) -> 0.5 | H91: ASSUMPTION | I91: cost_inputs.md Q2: $0.35-$0.75.
A92: tpl_uplift | B92: 3PL hidden-fee uplift on pick/pack | C92: % | D92: 0.35 | E92: 0.2 | F92: 0.1 | G92: =CHOOSE($D$3,D92,E92,F92) -> 0.2 | H92: SECONDHAND | I92: Eightx: invoices run 20-50% above quoted (https://eightx.co/blog/3pl-all-in-cost-per-order).
A93: return_proc | B93: 3PL returns processing | C93: $/return | D93: 7 | E93: 4.06 | F93: 1 | G93: =CHOOSE($D$3,D93,E93,F93) -> 4.06 | H93: SECONDHAND | I93: Fulfill.com $1-$7, avg $4.06.
A94: storage_pallet | B94: Storage per pallet | C94: $/pallet/month | D94: 40 | E94: 25 | F94: 18 | G94: =CHOOSE($D$3,D94,E94,F94) -> 25 | H94: SECONDHAND | I94: Fulfill.com $15-$40 (most $18-$25); Simpl $40.
A95: pallets | B95: Pallets stored (fountains + filters) | C95: pallets | D95: 4 | E95: 3 | F95: 2 | G95: =CHOOSE($D$3,D95,E95,F95) -> 3 | H95: ESTIMATE | I95: cost_inputs.md Q2: 500-1,000 fountains ~2-4 pallets; filters 1-2.
A96: tpl_min | B96: 3PL monthly minimum | C96: $/month | D96: 750 | E96: 500 | F96: 0 | G96: =CHOOSE($D$3,D96,E96,F96) -> 500 | H96: SECONDHAND | I96: Survey avg $517; Simpl $750; no-minimum pet 3PLs exist (Fulfill.com; CP3 Sec.4).
A97: receiving | B97: Receiving per pallet | C97: $/pallet | D97: 15 | E97: 10.52 | F97: 5 | G97: =CHOOSE($D$3,D97,E97,F97) -> 10.52 | H97: SECONDHAND | I97: Fulfill.com $5-$15, avg $10.52.
A98: tpl_setup | B98: 3PL setup + integration (one-time) | C98: $ one-time | D98: 1000 | E98: 608 | F98: 0 | G98: =CHOOSE($D$3,D98,E98,F98) -> 608 | H98: SECONDHAND | I98: Setup avg $333 + integration $275 (Fulfill.com).
B99: I. Payments, returns, defects and chargebacks
A100: pay_pct | B100: Shopify Payments rate (Basic) | C100: % of order | D100: 0.029 | E100: 0.029 | F100: 0.029 | G100: =CHOOSE($D$3,D100,E100,F100) -> 0.029 | H100: VENDOR | I100: 2.9% + 30c online (https://www.nerdwallet.com/article/small-business/shopify-pricing).
A101: pay_fixed | B101: Shopify Payments fixed fee | C101: $/order | D101: 0.3 | E101: 0.3 | F101: 0.3 | G101: =CHOOSE($D$3,D101,E101,F101) -> 0.3 | H101: VENDOR | I101: As above.
A102: refund_fountain | B102: Fountain refund / return rate | C102: % of fountain revenue | D102: 0.08 | E102: 0.05 | F102: 0.03 | G102: =CHOOSE($D$3,D102,E102,F102) -> 0.05 | H102: ASSUMPTION | I102: No US category data; pet supplies 1.2% (Galaxus), pet 8% / appliances 8% (Statista via TrackingMore). Returned units non-resaleable.
A103: replace_fountain | B103: Fountain warranty replacement rate (pump failure) | C103: % of units | D103: 0.05 | E103: 0.03 | F103: 0.015 | G103: =CHOOSE($D$3,D103,E103,F103) -> 0.03 | H103: ASSUMPTION | I103: Pump failure is the dominant complaint (https://kimola.com/reports/comprehensive-cat-water-fountain-feedback-analysis-amazon-en-us-143234). Full-unit re-ship (conservative).
A104: refund_filter | B104: Filter / mat refund rate | C104: % of revenue | D104: 0.02 | E104: 0.01 | F104: 0.005 | G104: =CHOOSE($D$3,D104,E104,F104) -> 0.01 | H104: ASSUMPTION | I104: Consumables low-return (acquisition_retention.md Q5).
A105: refund_kit | B105: Espresso kit refund rate (fit issues EC680/685/885) | C105: % of kit revenue | D105: 0.12 | E105: 0.07 | F105: 0.04 | G105: =CHOOSE($D$3,D105,E105,F105) -> 0.07 | H105: ASSUMPTION | I105: acquisition_retention.md Q5.
A106: replace_kit | B106: Espresso kit replacement / exchange rate | C106: % of kits | D106: 0.03 | E106: 0.02 | F106: 0.01 | G106: =CHOOSE($D$3,D106,E106,F106) -> 0.02 | H106: ASSUMPTION | I106: Wrong-ear / wrong-size exchanges.
A107: refund_beans | B107: Bean refund rate | C107: % of revenue | D107: 0.02 | E107: 0.01 | F107: 0.005 | G107: =CHOOSE($D$3,D107,E107,F107) -> 0.01 | H107: ASSUMPTION | I107: Consumable.
A108: cb_rate | B108: Chargeback rate | C108: % of orders | D108: 0.006 | E108: 0.003 | F108: 0.0015 | G108: =CHOOSE($D$3,D108,E108,F108) -> 0.003 | H108: ASSUMPTION | I108: All-industry ~0.26% (Sift, secondhand); 'typical' ~0.60% (https://www.chargeback.io/es/blog/average-e-commerce-chargeback-rate).
A109: cb_fee | B109: Chargeback fee (plus order value lost) | C109: $/dispute | D109: 15 | E109: 15 | F109: 15 | G109: =CHOOSE($D$3,D109,E109,F109) -> 15 | H109: VENDOR | I109: $15 per US Shopify dispute (chargeback.io, vendor claim).
B110: J. Acquisition and marketing
A111: cpa_m13 | B111: Cat paid CPA, months 1-3 (new pixel) | C111: $/new customer | D111: 90 | E111: 60 | F111: 40 | G111: =CHOOSE($D$3,D111,E111,F111) -> 60 | H111: ASSUMPTION | I111: acquisition_retention.md Q1 (capped). Triple Whale Meta Pets median CPA $38.51 for established brands (SECONDHAND, https://www.digitalapplied.com/blog/facebook-ads-benchmarks-2026-cpc-cpm-ctr-industry).
A112: cpa_m412 | B112: Cat paid CPA, months 4-12 (after learning) | C112: $/new customer | D112: 65 | E112: 45 | F112: 32 | G112: =CHOOSE($D$3,D112,E112,F112) -> 45 | H112: ASSUMPTION | I112: As above.
...

Sheet Cat_UnitEcon
A1: Cat_UnitEcon: per-order contribution, cat home (BASE CASE)
A2: Group 1 (columns B-F) follows the scenario selector. Groups to the right are the engine for Scenarios and Sensitivity: identical formulas pointing at a fixed Inputs column, some with a shock multiplier.
A3: Costs shown as negatives. Contribution = net revenue less all variable costs (product, fulfillment, postage, payments, warranty, returns, chargebacks, affiliates). Fixed costs (apps, 3PL storage, UGC) are in Launch_Budget.
A5: Scenario group | B5: ="SELECTED scenario: "&Inputs!$E$3 -> SELECTED scenario: Base | H5: PESSIMISTIC (engine) | N5: BASE (engine) | T5: OPTIMISTIC (engine) | Z5: BASE + CPA shock (sensitivity) | AF5: BASE + supplier/COGS shock (sensitivity) | AL5: BASE + shipping shock (sensitivity) | AR5: BASE + subscription-attach shock (sensitivity) | AX5: BASE + churn shock (sensitivity) | BD5: BASE + returns shock (sensitivity)
A6: Inputs column used | B6: G = Selected | H6: D = Pessimistic | N6: E = Base | T6: F = Optimistic | Z6: E = Base | AF6: E = Base | AL6: E = Base | AR6: E = Base | AX6: E = Base | BD6: E = Base
A7: Multiplier - paid CPA | B7: 1 | H7: 1 | N7: 1 | T7: 1 | Z7: =1+Sensitivity!$C$5 -> 1.3 | AF7: 1 | AL7: 1 | AR7: 1 | AX7: 1 | BD7: 1
A8: Multiplier - supplier unit cost (COGS) | B8: 1 | H8: 1 | N8: 1 | T8: 1 | Z8: 1 | AF8: =1+Sensitivity!$C$6 -> 1.15 | AL8: 1 | AR8: 1 | AX8: 1 | BD8: 1
A9: Multiplier - postage | B9: 1 | H9: 1 | N9: 1 | T9: 1 | Z9: 1 | AF9: 1 | AL9: =1+Sensitivity!$C$7 -> 1.2 | AR9: 1 | AX9: 1 | BD9: 1
A10: Multiplier - subscription attach (used in cohort) | B10: 1 | H10: 1 | N10: 1 | T10: 1 | Z10: 1 | AF10: 1 | AL10: 1 | AR10: =1+Sensitivity!$C$8 -> 0.5 | AX10: 1 | BD10: 1
A11: Multiplier - churn (used in cohort) | B11: 1 | H11: 1 | N11: 1 | T11: 1 | Z11: 1 | AF11: 1 | AL11: 1 | AR11: 1 | AX11: =1+Sensitivity!$C$9 -> 1.5 | BD11: 1
A12: Multiplier - refunds, replacements, returns | B12: 1 | H12: 1 | N12: 1 | T12: 1 | Z12: 1 | AF12: 1 | AL12: 1 | AR12: 1 | AX12: 1 | BD12: =Sensitivity!$C$10 -> 2
A14: Landed cost build (per unit, value in first column of each group)
A15: Test-stage fountain landed (AliExpress x (1 + duty + AutoDS fee)) | B15: =Inputs!$G$25*$B$8*(1+Inputs!$G$26+Inputs!$G$27) -> 38.3265 | H15: =Inputs!$D$25*$H$8*(1+Inputs!$D$26+Inputs!$D$27) -> 48.564 | N15: =Inputs!$E$25*$N$8*(1+Inputs!$E$26+Inputs!$E$27) -> 38.3265 | T15: =Inputs!$F$25*$T$8*(1+Inputs!$F$26+Inputs!$F$27) -> 21.79 | Z15: =Inputs!$E$25*$Z$8*(1+Inputs!$E$26+Inputs!$E$27) -> 38.3265 | AF15: =Inputs!$E$25*$AF$8*(1+Inputs!$E$26+Inputs!$E$27) -> 44.075475 | AL15: =Inputs!$E$25*$AL$8*(1+Inputs!$E$26+Inputs!$E$27) -> 38.3265 | AR15: =Inputs!$E$25*$AR$8*(1+Inputs!$E$26+Inputs!$E$27) -> 38.3265 | AX15: =Inputs!$E$25*$AX$8*(1+Inputs!$E$26+Inputs!$E$27) -> 38.3265 | BD15: =Inputs!$E$25*$BD$8*(1+Inputs!$E$26+Inputs!$E$27) -> 38.3265
A16: PL fountain FOB incl. listed adapter | B16: =(Inputs!$G$36+Inputs!$G$37)*$B$8 -> 11.77 | H16: =(Inputs!$D$36+Inputs!$D$37)*$H$8 -> 13.83 | N16: =(Inputs!$E$36+Inputs!$E$37)*$N$8 -> 11.77 | T16: =(Inputs!$F$36+Inputs!$F$37)*$T$8 -> 8.16 | Z16: =(Inputs!$E$36+Inputs!$E$37)*$Z$8 -> 11.77 | AF16: =(Inputs!$E$36+Inputs!$E$37)*$AF$8 -> 13.5355 | AL16: =(Inputs!$E$36+Inputs!$E$37)*$AL$8 -> 11.77 | AR16: =(Inputs!$E$36+Inputs!$E$37)*$AR$8 -> 11.77 | AX16: =(Inputs!$E$36+Inputs!$E$37)*$AX$8 -> 11.77 | BD16: =(Inputs!$E$36+Inputs!$E$37)*$BD$8 -> 11.77
A17: PL duty (Section 301 stack) | B17: =$B$16*Inputs!$G$39 -> 4.41375 | H17: =$H$16*Inputs!$D$39 -> 5.18625 | N17: =$N$16*Inputs!$E$39 -> 4.41375 | T17: =$T$16*Inputs!$F$39 -> 3.06 | Z17: =$Z$16*Inputs!$E$39 -> 4.41375 | AF17: =$AF$16*Inputs!$E$39 -> 5.0758125 | AL17: =$AL$16*Inputs!$E$39 -> 4.41375 | AR17: =$AR$16*Inputs!$E$39 -> 4.41375 | AX17: =$AX$16*Inputs!$E$39 -> 4.41375 | BD17: =$BD$16*Inputs!$E$39 -> 4.41375
A18: PL ocean freight per unit | B18: =Inputs!$G$38 -> 3.5 | H18: =Inputs!$D$38 -> 5 | N18: =Inputs!$E$38 -> 3.5 | T18: =Inputs!$F$38 -> 2.2 | Z18: =Inputs!$E$38 -> 3.5 | AF18: =Inputs!$E$38 -> 3.5 | AL18: =Inputs!$E$38 -> 3.5 | AR18: =Inputs!$E$38 -> 3.5 | AX18: =Inputs!$E$38 -> 3.5 | BD18: =Inputs!$E$38 -> 3.5
A19: PL customs entry fees per unit (broker, ISF, bond, MPF, HMF) | B19: =(Inputs!$G$41+Inputs!$G$42+Inputs!$G$43+MAX(Inputs!$G$45,MIN(Inputs!$G$46,Inputs!$G$44*Inputs!$G$40*$B$16))+Inputs!$G$47*Inputs!$G$40*$B$16)/Inputs!$G$40 -> 0.6318725 | H19: =(Inputs!$D$41+Inputs!$D$42+Inputs!$D$43+MAX(Inputs!$D$45,MIN(Inputs!$D$46,Inputs!$D$44*Inputs!$D$40*$H$16))+Inputs!$D$47*Inputs!$D$40*$H$16)/Inputs!$D$40 -> 0.8844475 | N19: =(Inputs!$E$41+Inputs!$E$42+Inputs!$E$43+MAX(Inputs!$E$45,MIN(Inputs!$E$46,Inputs!$E$44*Inputs!$E$40*$N$16))+Inputs!$E$47*Inputs!$E$40*$N$16)/Inputs!$E$40 -> 0.6318725 | T19: =(Inputs!$F$41+Inputs!$F$42+Inputs!$F$43+MAX(Inputs!$F$45,MIN(Inputs!$F$46,Inputs!$F$44*Inputs!$F$40*$T$16))+Inputs!$F$47*Inputs!$F$40*$T$16)/Inputs!$F$40 -> 0.21378 | Z19: =(Inputs!$E$41+Inputs!$E$42+Inputs!$E$43+MAX(Inputs!$E$45,MIN(Inputs!$E$46,Inputs!$E$44*Inputs!$E$40*$Z$16))+Inputs!$E$47*Inputs!$E$40*$Z$16)/Inputs!$E$40 -> 0.6318725 | AF19: =(Inputs!$E$41+Inputs!$E$42+Inputs!$E$43+MAX(Inputs!$E$45,MIN(Inputs!$E$46,Inputs!$E$44*Inputs!$E$40*$AF$16))+Inputs!$E$47*Inputs!$E$40*$AF$16)/Inputs!$E$40 -> 0.63407937 | AL19: =(Inputs!$E$41+Inputs!$E$42+Inputs!$E$43+MAX(Inputs!$E$45,MIN(Inputs!$E$46,Inputs!$E$44*Inputs!$E$40*$AL$16))+Inputs!$E$47*Inputs!$E$40*$AL$16)/Inputs!$E$40 -> 0.6318725 | AR19: =(Inputs!$E$41+Inputs!$E$42+Inputs!$E$43+MAX(Inputs!$E$45,MIN(Inputs!$E$46,Inputs!$E$44*Inputs!$E$40*$AR$16))+Inputs!$E$47*Inputs!$E$40*$AR$16)/Inputs!$E$40 -> 0.6318725 | AX19: =(Inputs!$E$41+Inputs!$E$42+Inputs!$E$43+MAX(Inputs!$E$45,MIN(Inputs!$E$46,Inputs!$E$44*Inputs!$E$40*$AX$16))+Inputs!$E$47*Inputs!$E$40*$AX$16)/Inputs!$E$40 -> 0.6318725 | BD19: =(Inputs!$E$41+Inputs!$E$42+Inputs!$E$43+MAX(Inputs!$E$45,MIN(Inputs!$E$46,Inputs!$E$44*Inputs!$E$40*$BD$16))+Inputs!$E$47*Inputs!$E$40*$BD$16)/Inputs!$E$40 -> 0.6318725
A20: PL retail packaging | B20: =Inputs!$G$48 -> 1 | H20: =Inputs!$D$48 -> 1.5 | N20: =Inputs!$E$48 -> 1 | T20: =Inputs!$F$48 -> 0.7 | Z20: =Inputs!$E$48 -> 1 | AF20: =Inputs!$E$48 -> 1 | AL20: =Inputs!$E$48 -> 1 | AR20: =Inputs!$E$48 -> 1 | AX20: =Inputs!$E$48 -> 1 | BD20: =Inputs!$E$48 -> 1
A21: PL certification amortization (FCC + Prop 65 + food-contact) | B21: =(Inputs!$G$49+Inputs!$G$50+Inputs!$G$51)/Inputs!$G$52 -> 4.65 | H21: =(Inputs!$D$49+Inputs!$D$50+Inputs!$D$51)/Inputs!$D$52 -> 14.8 | N21: =(Inputs!$E$49+Inputs!$E$50+Inputs!$E$51)/Inputs!$E$52 -> 4.65 | T21: =(Inputs!$F$49+Inputs!$F$50+Inputs!$F$51)/Inputs!$F$52 -> 1.275 | Z21: =(Inputs!$E$49+Inputs!$E$50+Inputs!$E$51)/Inputs!$E$52 -> 4.65 | AF21: =(Inputs!$E$49+Inputs!$E$50+Inputs!$E$51)/Inputs!$E$52 -> 4.65 | AL21: =(Inputs!$E$49+Inputs!$E$50+Inputs!$E$51)/Inputs!$E$52 -> 4.65 | AR21: =(Inputs!$E$49+Inputs!$E$50+Inputs!$E$51)/Inputs!$E$52 -> 4.65 | AX21: =(Inputs!$E$49+Inputs!$E$50+Inputs!$E$51)/Inputs!$E$52 -> 4.65 | BD21: =(Inputs!$E$49+Inputs!$E$50+Inputs!$E$51)/Inputs!$E$52 -> 4.65
A22: PL fountain landed cost | B22: =SUM(B16:B21) -> 25.965622 | H22: =SUM(H16:H21) -> 41.200698 | N22: =SUM(N16:N21) -> 25.965622 | T22: =SUM(T16:T21) -> 15.60878 | Z22: =SUM(Z16:Z21) -> 25.965622 | AF22: =SUM(AF16:AF21) -> 28.395392 | AL22: =SUM(AL16:AL21) -> 25.965622 | AR22: =SUM(AR16:AR21) -> 25.965622 | AX22: =SUM(AX16:AX21) -> 25.965622 | BD22: =SUM(BD16:BD21) -> 25.965622
A23: PL litter mat landed cost | B23: =Inputs!$G$53*$B$8*(1+Inputs!$G$54)+Inputs!$G$55 -> 5.075 | H23: =Inputs!$D$53*$H$8*(1+Inputs!$D$54)+Inputs!$D$55 -> 6.7 | N23: =Inputs!$E$53*$N$8*(1+Inputs!$E$54)+Inputs!$E$55 -> 5.075 | T23: =Inputs!$F$53*$T$8*(1+Inputs!$F$54)+Inputs!$F$55 -> 3 | Z23: =Inputs!$E$53*$Z$8*(1+Inputs!$E$54)+Inputs!$E$55 -> 5.075 | AF23: =Inputs!$E$53*$AF$8*(1+Inputs!$E$54)+Inputs!$E$55 -> 5.71625 | AL23: =Inputs!$E$53*$AL$8*(1+Inputs!$E$54)+Inputs!$E$55 -> 5.075 | AR23: =Inputs!$E$53*$AR$8*(1+Inputs!$E$54)+Inputs!$E$55 -> 5.075 | AX23: =Inputs!$E$53*$AX$8*(1+Inputs!$E$54)+Inputs!$E$55 -> 5.075 | BD23: =Inputs!$E$53*$BD$8*(1+Inputs!$E$54)+Inputs!$E$55 -> 5.075
A24: PL filter 6-pack landed cost (US stock) | B24: =Inputs!$G$15*Inputs!$G$56*$B$8*(1+Inputs!$G$57)+Inputs!$G$58+Inputs!$G$59 -> 5.2425 | H24: =Inputs!$D$15*Inputs!$D$56*$H$8*(1+Inputs!$D$57)+Inputs!$D$58+Inputs!$D$59 -> 6.5675 | N24: =Inputs!$E$15*Inputs!$E$56*$N$8*(1+Inputs!$E$57)+Inputs!$E$58+Inputs!$E$59 -> 5.2425 | T24: =Inputs!$F$15*Inputs!$F$56*$T$8*(1+Inputs!$F$57)+Inputs!$F$58+Inputs!$F$59 -> 4.3625 | Z24: =Inputs!$E$15*Inputs!$E$56*$Z$8*(1+Inputs!$E$57)+Inputs!$E$58+Inputs!$E$59 -> 5.2425 | AF24: =Inputs!$E$15*Inputs!$E$56*$AF$8*(1+Inputs!$E$57)+Inputs!$E$58+Inputs!$E$59 -> 5.848875 | AL24: =Inputs!$E$15*Inputs!$E$56*$AL$8*(1+Inputs!$E$57)+Inputs!$E$58+Inputs!$E$59 -> 5.2425 | AR24: =Inputs!$E$15*Inputs!$E$56*$AR$8*(1+Inputs!$E$57)+Inputs!$E$58+Inputs!$E$59 -> 5.2425 | AX24: =Inputs!$E$15*Inputs!$E$56*$AX$8*(1+Inputs!$E$57)+Inputs!$E$58+Inputs!$E$59 -> 5.2425 | BD24: =Inputs!$E$15*Inputs!$E$56*$BD$8*(1+Inputs!$E$57)+Inputs!$E$58+Inputs!$E$59 -> 5.2425
A26: Order type | B26: (a) Fountain first order - TEST stage (AliExpress) | C26: (b) Fountain first order - PRIVATE LABEL | D26: (c) Fountain + litter mat bundle - PRIVATE LABEL | E26: (d) Filter 90-day pack - SUBSCRIPTION renewal | F26: (e) Filter pack - one-time repeat order | H26: (a) Fountain first order - TEST stage (AliExpress) | I26: (b) Fountain first order - PRIVATE LABEL | J26: (c) Fountain + litter mat bundle - PRIVATE LABEL | K26: (d) Filter 90-day pack - SUBSCRIPTION renewal | L26: (e) Filter pack - one-time repeat order | N26: (a) Fountain first order - TEST stage (AliExpress) | O26: (b) Fountain first order - PRIVATE LABEL | P26: (c) Fountain + litter mat bundle - PRIVATE LABEL | Q26: (d) Filter 90-day pack - SUBSCRIPTION renewal | R26: (e) Filter pack - one-time repeat order | T26: (a) Fountain first order - TEST stage (AliExpress) | U26: (b) Fountain first order - PRIVATE LABEL | V26: (c) Fountain + litter mat bundle - PRIVATE LABEL | W26: (d) Filter 90-day pack - SUBSCRIPTION renewal | X26: (e) Filter pack - one-time repeat order | Z26: (a) Fountain first order - TEST stage (AliExpress) | AA26: (b) Fountain first order - PRIVATE LABEL | AB26: (c) Fountain + litter mat bundle - PRIVATE LABEL | AC26: (d) Filter 90-day pack - SUBSCRIPTION renewal | AD26: (e) Filter pack - one-time repeat order | AF26: (a) Fountain first order - TEST stage (AliExpress) | AG26: (b) Fountain first order - PRIVATE LABEL | AH26: (c) Fountain + litter mat bundle - PRIVATE LABEL | AI26: (d) Filter 90-day pack - SUBSCRIPTION renewal | AJ26: (e) Filter pack - one-time repeat order | AL26: (a) Fountain first order - TEST stage (AliExpress) | AM26: (b) Fountain first order - PRIVATE LABEL | AN26: (c) Fountain + litter mat bundle - PRIVATE LABEL | AO26: (d) Filter 90-day pack - SUBSCRIPTION renewal | AP26: (e) Filter pack - one-time repeat order | AR26: (a) Fountain first order - TEST stage (AliExpress) | AS26: (b) Fountain first order - PRIVATE LABEL | AT26: (c) Fountain + litter mat bundle - PRIVATE LABEL | AU26: (d) Filter 90-day pack - SUBSCRIPTION renewal | AV26: (e) Filter pack - one-time repeat order | AX26: (a) Fountain first order - TEST stage (AliExpress) | AY26: (b) Fountain first order - PRIVATE LABEL | AZ26: (c) Fountain + litter mat bundle - PRIVATE LABEL | BA26: (d) Filter 90-day pack - SUBSCRIPTION renewal | BB26: (e) Filter pack - one-time repeat order | BD26: (a) Fountain first order - TEST stage (AliExpress) | BE26: (b) Fountain first order - PRIVATE LABEL | BF26: (c) Fountain + litter mat bundle - PRIVATE LABEL | BG26: (d) Filter 90-day pack - SUBSCRIPTION renewal | BH26: (e) Filter pack - one-time repeat order
A27: Stage | B27: Test | C27: Private label | D27: Private label | E27: PL renewal | F27: PL one-time | H27: Test | I27: Private label | J27: Private label | K27: PL renewal | L27: PL one-time | N27: Test | O27: Private label | P27: Private label | Q27: PL renewal | R27: PL one-time | T27: Test | U27: Private label | V27: Private label | W27: PL renewal | X27: PL one-time | Z27: Test | AA27: Private label | AB27: Private label | AC27: PL renewal | AD27: PL one-time | AF27: Test | AG27: Private label | AH27: Private label | AI27: PL renewal | AJ27: PL one-time | AL27: Test | AM27: Private label | AN27: Private label | AO27: PL renewal | AP27: PL one-time | AR27: Test | AS27: Private label | AT27: Private label | AU27: PL renewal | AV27: PL one-time | AX27: Test | AY27: Private label | AZ27: Private label | BA27: PL renewal | BB27: PL one-time | BD27: Test | BE27: Private label | BF27: Private label | BG27: PL renewal | BH27: PL one-time
A28: Fountain units | B28: 1 | C28: 1 | D28: 1 | E28: 0 | F28: 0 | H28: 1 | I28: 1 | J28: 1 | K28: 0 | L28: 0 | N28: 1 | O28: 1 | P28: 1 | Q28: 0 | R28: 0 | T28: 1 | U28: 1 | V28: 1 | W28: 0 | X28: 0 | Z28: 1 | AA28: 1 | AB28: 1 | AC28: 0 | AD28: 0 | AF28: 1 | AG28: 1 | AH28: 1 | AI28: 0 | AJ28: 0 | AL28: 1 | AM28: 1 | AN28: 1 | AO28: 0 | AP28: 0 | AR28: 1 | AS28: 1 | AT28: 1 | AU28: 0 | AV28: 0 | AX28: 1 | AY28: 1 | AZ28: 1 | BA28: 0 | BB28: 0 | BD28: 1 | BE28: 1 | BF28: 1 | BG28: 0 | BH28: 0
A29: Litter mat units | B29: 0 | C29: 0 | D29: 1 | E29: 0 | F29: 0 | H29: 0 | I29: 0 | J29: 1 | K29: 0 | L29: 0 | N29: 0 | O29: 0 | P29: 1 | Q29: 0 | R29: 0 | T29: 0 | U29: 0 | V29: 1 | W29: 0 | X29: 0 | Z29: 0 | AA29: 0 | AB29: 1 | AC29: 0 | AD29: 0 | AF29: 0 | AG29: 0 | AH29: 1 | AI29: 0 | AJ29: 0 | AL29: 0 | AM29: 0 | AN29: 1 | AO29: 0 | AP29: 0 | AR29: 0 | AS29: 0 | AT29: 1 | AU29: 0 | AV29: 0 | AX29: 0 | AY29: 0 | AZ29: 1 | BA29: 0 | BB29: 0 | BD29: 0 | BE29: 0 | BF29: 1 | BG29: 0 | BH29: 0
A30: Filter packs | B30: 0 | C30: 0 | D30: 0 | E30: 1 | F30: 1 | H30: 0 | I30: 0 | J30: 0 | K30: 1 | L30: 1 | N30: 0 | O30: 0 | P30: 0 | Q30: 1 | R30: 1 | T30: 0 | U30: 0 | V30: 0 | W30: 1 | X30: 1 | Z30: 0 | AA30: 0 | AB30: 0 | AC30: 1 | AD30: 1 | AF30: 0 | AG30: 0 | AH30: 0 | AI30: 1 | AJ30: 1 | AL30: 0 | AM30: 0 | AN30: 0 | AO30: 1 | AP30: 1 | AR30: 0 | AS30: 0 | AT30: 0 | AU30: 1 | AV30: 1 | AX30: 0 | AY30: 0 | AZ30: 0 | BA30: 1 | BB30: 1 | BD30: 0 | BE30: 0 | BF30: 0 | BG30: 1 | BH30: 1
A31: Revenue - fountain | B31: =B28*Inputs!$G$11 -> 49.99 | C31: =C28*Inputs!$G$11 -> 49.99 | D31: =D28*Inputs!$G$11 -> 49.99 | E31: =E28*Inputs!$G$11 -> 0 | F31: =F28*Inputs!$G$11 -> 0 | H31: =H28*Inputs!$D$11 -> 44.99 | I31: =I28*Inputs!$D$11 -> 44.99 | J31: =J28*Inputs!$D$11 -> 44.99 | K31: =K28*Inputs!$D$11 -> 0 | L31: =L28*Inputs!$D$11 -> 0 | N31: =N28*Inputs!$E$11 -> 49.99 | O31: =O28*Inputs!$E$11 -> 49.99 | P31: =P28*Inputs!$E$11 -> 49.99 | Q31: =Q28*Inputs!$E$11 -> 0 | R31: =R28*Inputs!$E$11 -> 0 | T31: =T28*Inputs!$F$11 -> 59.99 | U31: =U28*Inputs!$F$11 -> 59.99 | V31: =V28*Inputs!$F$11 -> 59.99 | W31: =W28*Inputs!$F$11 -> 0 | X31: =X28*Inputs!$F$11 -> 0 | Z31: =Z28*Inputs!$E$11 -> 49.99 | AA31: =AA28*Inputs!$E$11 -> 49.99 | AB31: =AB28*Inputs!$E$11 -> 49.99 | AC31: =AC28*Inputs!$E$11 -> 0 | AD31: =AD28*Inputs!$E$11 -> 0 | AF31: =AF28*Inputs!$E$11 -> 49.99 | AG31: =AG28*Inputs!$E$11 -> 49.99 | AH31: =AH28*Inputs!$E$11 -> 49.99 | AI31: =AI28*Inputs!$E$11 -> 0 | AJ31: =AJ28*Inputs!$E$11 -> 0 | AL31: =AL28*Inputs!$E$11 -> 49.99 | AM31: =AM28*Inputs!$E$11 -> 49.99 | AN31: =AN28*Inputs!$E$11 -> 49.99 | AO31: =AO28*Inputs!$E$11 -> 0 | AP31: =AP28*Inputs!$E$11 -> 0 | AR31: =AR28*Inputs!$E$11 -> 49.99 | AS31: =AS28*Inputs!$E$11 -> 49.99 | AT31: =AT28*Inputs!$E$11 -> 49.99 | AU31: =AU28*Inputs!$E$11 -> 0 | AV31: =AV28*Inputs!$E$11 -> 0 | AX31: =AX28*Inputs!$E$11 -> 49.99 | AY31: =AY28*Inputs!$E$11 -> 49.99 | AZ31: =AZ28*Inputs!$E$11 -> 49.99 | BA31: =BA28*Inputs!$E$11 -> 0 | BB31: =BB28*Inputs!$E$11 -> 0 | BD31: =BD28*Inputs!$E$11 -> 49.99 | BE31: =BE28*Inputs!$E$11 -> 49.99 | BF31: =BF28*Inputs!$E$11 -> 49.99 | BG31: =BG28*Inputs!$E$11 -> 0 | BH31: =BH28*Inputs!$E$11 -> 0
A32: Revenue - litter mat | B32: =B29*Inputs!$G$17 -> 0 | C32: =C29*Inputs!$G$17 -> 0 | D32: =D29*Inputs!$G$17 -> 19.99 | E32: =E29*Inputs!$G$17 -> 0 | F32: =F29*Inputs!$G$17 -> 0 | H32: =H29*Inputs!$D$17 -> 0 | I32: =I29*Inputs!$D$17 -> 0 | J32: =J29*Inputs!$D$17 -> 16.99 | K32: =K29*Inputs!$D$17 -> 0 | L32: =L29*Inputs!$D$17 -> 0 | N32: =N29*Inputs!$E$17 -> 0 | O32: =O29*Inputs!$E$17 -> 0 | P32: =P29*Inputs!$E$17 -> 19.99 | Q32: =Q29*Inputs!$E$17 -> 0 | R32: =R29*Inputs!$E$17 -> 0 | T32: =T29*Inputs!$F$17 -> 0 | U32: =U29*Inputs!$F$17 -> 0 | V32: =V29*Inputs!$F$17 -> 22.99 | W32: =W29*Inputs!$F$17 -> 0 | X32: =X29*Inputs!$F$17 -> 0 | Z32: =Z29*Inputs!$E$17 -> 0 | AA32: =AA29*Inputs!$E$17 -> 0 | AB32: =AB29*Inputs!$E$17 -> 19.99 | AC32: =AC29*Inputs!$E$17 -> 0 | AD32: =AD29*Inputs!$E$17 -> 0 | AF32: =AF29*Inputs!$E$17 -> 0 | AG32: =AG29*Inputs!$E$17 -> 0 | AH32: =AH29*Inputs!$E$17 -> 19.99 | AI32: =AI29*Inputs!$E$17 -> 0 | AJ32: =AJ29*Inputs!$E$17 -> 0 | AL32: =AL29*Inputs!$E$17 -> 0 | AM32: =AM29*Inputs!$E$17 -> 0 | AN32: =AN29*Inputs!$E$17 -> 19.99 | AO32: =AO29*Inputs!$E$17 -> 0 | AP32: =AP29*Inputs!$E$17 -> 0 | AR32: =AR29*Inputs!$E$17 -> 0 | AS32: =AS29*Inputs!$E$17 -> 0 | AT32: =AT29*Inputs!$E$17 -> 19.99 | AU32: =AU29*Inputs!$E$17 -> 0 | AV32: =AV29*Inputs!$E$17 -> 0 | AX32: =AX29*Inputs!$E$17 -> 0 | AY32: =AY29*Inputs!$E$17 -> 0 | AZ32: =AZ29*Inputs!$E$17 -> 19.99 | BA32: =BA29*Inputs!$E$17 -> 0 | BB32: =BB29*Inputs!$E$17 -> 0 | BD32: =BD29*Inputs!$E$17 -> 0 | BE32: =BE29*Inputs!$E$17 -> 0 | BF32: =BF29*Inputs!$E$17 -> 19.99 | BG32: =BG29*Inputs!$E$17 -> 0 | BH32: =BH29*Inputs!$E$17 -> 0
A33: Revenue - filter pack | B33: =B30*Inputs!$G$14 -> 0 | C33: =C30*Inputs!$G$14 -> 0 | D33: =D30*Inputs!$G$14 -> 0 | E33: =E30*Inputs!$G$14 -> 15.291 | F33: =F30*Inputs!$G$12 -> 16.99 | H33: =H30*Inputs!$D$14 -> 0 | I33: =I30*Inputs!$D$14 -> 0 | J33: =J30*Inputs!$D$14 -> 0 | K33: =K30*Inputs!$D$14 -> 12.7415 | L33: =L30*Inputs!$D$12 -> 14.99 | N33: =N30*Inputs!$E$14 -> 0 | O33: =O30*Inputs!$E$14 -> 0 | P33: =P30*Inputs!$E$14 -> 0 | Q33: =Q30*Inputs!$E$14 -> 15.291 | R33: =R30*Inputs!$E$12 -> 16.99 | T33: =T30*Inputs!$F$14 -> 0 | U33: =U30*Inputs!$F$14 -> 0 | V33: =V30*Inputs!$F$14 -> 0 | W33: =W30*Inputs!$F$14 -> 15.741 | X33: =X30*Inputs!$F$12 -> 17.49 | Z33: =Z30*Inputs!$E$14 -> 0 | AA33: =AA30*Inputs!$E$14 -> 0 | AB33: =AB30*Inputs!$E$14 -> 0 | AC33: =AC30*Inputs!$E$14 -> 15.291 | AD33: =AD30*Inputs!$E$12 -> 16.99 | AF33: =AF30*Inputs!$E$14 -> 0 | AG33: =AG30*Inputs!$E$14 -> 0 | AH33: =AH30*Inputs!$E$14 -> 0 | AI33: =AI30*Inputs!$E$14 -> 15.291 | AJ33: =AJ30*Inputs!$E$12 -> 16.99 | AL33: =AL30*Inputs!$E$14 -> 0 | AM33: =AM30*Inputs!$E$14 -> 0 | AN33: =AN30*Inputs!$E$14 -> 0 | AO33: =AO30*Inputs!$E$14 -> 15.291 | AP33: =AP30*Inputs!$E$12 -> 16.99 | AR33: =AR30*Inputs!$E$14 -> 0 | AS33: =AS30*Inputs!$E$14 -> 0 | AT33: =AT30*Inputs!$E$14 -> 0 | AU33: =AU30*Inputs!$E$14 -> 15.291 | AV33: =AV30*Inputs!$E$12 -> 16.99 | AX33: =AX30*Inputs!$E$14 -> 0 | AY33: =AY30*Inputs!$E$14 -> 0 | AZ33: =AZ30*Inputs!$E$14 -> 0 | BA33: =BA30*Inputs!$E$14 -> 15.291 | BB33: =BB30*Inputs!$E$12 -> 16.99 | BD33: =BD30*Inputs!$E$14 -> 0 | BE33: =BE30*Inputs!$E$14 -> 0 | BF33: =BF30*Inputs!$E$14 -> 0 | BG33: =BG30*Inputs!$E$14 -> 15.291 | BH33: =BH30*Inputs!$E$12 -> 16.99
A34: Shipping charged to customer | B34: 0 | C34: 0 | D34: 0 | E34: 0 | F34: =Inputs!$G$16 -> 0 | H34: 0 | I34: 0 | J34: 0 | K34: 0 | L34: =Inputs!$D$16 -> 0 | N34: 0 | O34: 0 | P34: 0 | Q34: 0 | R34: =Inputs!$E$16 -> 0 | T34: 0 | U34: 0 | V34: 0 | W34: 0 | X34: =Inputs!$F$16 -> 3.99 | Z34: 0 | AA34: 0 | AB34: 0 | AC34: 0 | AD34: =Inputs!$E$16 -> 0 | AF34: 0 | AG34: 0 | AH34: 0 | AI34: 0 | AJ34: =Inputs!$E$16 -> 0 | AL34: 0 | AM34: 0 | AN34: 0 | AO34: 0 | AP34: =Inputs!$E$16 -> 0 | AR34: 0 | AS34: 0 | AT34: 0 | AU34: 0 | AV34: =Inputs!$E$16 -> 0 | AX34: 0 | AY34: 0 | AZ34: 0 | BA34: 0 | BB34: =Inputs!$E$16 -> 0 | BD34: 0 | BE34: 0 | BF34: 0 | BG34: 0 | BH34: =Inputs!$E$16 -> 0
A35: Gross revenue | B35: =SUM(B31:B34) -> 49.99 | C35: =SUM(C31:C34) -> 49.99 | D35: =SUM(D31:D34) -> 69.98 | E35: =SUM(E31:E34) -> 15.291 | F35: =SUM(F31:F34) -> 16.99 | H35: =SUM(H31:H34) -> 44.99 | I35: =SUM(I31:I34) -> 44.99 | J35: =SUM(J31:J34) -> 61.98 | K35: =SUM(K31:K34) -> 12.7415 | L35: =SUM(L31:L34) -> 14.99 | N35: =SUM(N31:N34) -> 49.99 | O35: =SUM(O31:O34) -> 49.99 | P35: =SUM(P31:P34) -> 69.98 | Q35: =SUM(Q31:Q34) -> 15.291 | R35: =SUM(R31:R34) -> 16.99 | T35: =SUM(T31:T34) -> 59.99 | U35: =SUM(U31:U34) -> 59.99 | V35: =SUM(V31:V34) -> 82.98 | W35: =SUM(W31:W34) -> 15.741 | X35: =SUM(X31:X34) -> 21.48 | Z35: =SUM(Z31:Z34) -> 49.99 | AA35: =SUM(AA31:AA34) -> 49.99 | AB35: =SUM(AB31:AB34) -> 69.98 | AC35: =SUM(AC31:AC34) -> 15.291 | AD35: =SUM(AD31:AD34) -> 16.99 | AF35: =SUM(AF31:AF34) -> 49.99 | AG35: =SUM(AG31:AG34) -> 49.99 | AH35: =SUM(AH31:AH34) -> 69.98 | AI35: =SUM(AI31:AI34) -> 15.291 | AJ35: =SUM(AJ31:AJ34) -> 16.99 | AL35: =SUM(AL31:AL34) -> 49.99 | AM35: =SUM(AM31:AM34) -> 49.99 | AN35: =SUM(AN31:AN34) -> 69.98 | AO35: =SUM(AO31:AO34) -> 15.291 | AP35: =SUM(AP31:AP34) -> 16.99 | AR35: =SUM(AR31:AR34) -> 49.99 | AS35: =SUM(AS31:AS34) -> 49.99 | AT35: =SUM(AT31:AT34) -> 69.98 | AU35: =SUM(AU31:AU34) -> 15.291 | AV35: =SUM(AV31:AV34) -> 16.99 | AX35: =SUM(AX31:AX34) -> 49.99 | AY35: =SUM(AY31:AY34) -> 49.99 | AZ35: =SUM(AZ31:AZ34) -> 69.98 | BA35: =SUM(BA31:BA34) -> 15.291 | BB35: =SUM(BB31:BB34) -> 16.99 | BD35: =SUM(BD31:BD34) -> 49.99 | BE35: =SUM(BE31:BE34) -> 49.99 | BF35: =SUM(BF31:BF34) -> 69.98 | BG35: =SUM(BG31:BG34) -> 15.291 | BH35: =SUM(BH31:BH34) -> 16.99
A36: Refunds / returns (revenue reversed) | B36: =-(B31*Inputs!$G$102+(B32+B33)*Inputs!$G$104)*$B$12 -> -2.4995 | C36: =-(C31*Inputs!$G$102+(C32+C33)*Inputs!$G$104)*$B$12 -> -2.4995 | D36: =-(D31*Inputs!$G$102+(D32+D33)*Inputs!$G$104)*$B$12 -> -2.6994 | E36: =-(E31*Inputs!$G$102+(E32+E33)*Inputs!$G$104)*$B$12 -> -0.15291 | F36: =-(F31*Inputs!$G$102+(F32+F33)*Inputs!$G$104)*$B$12 -> -0.1699 | H36: =-(H31*Inputs!$D$102+(H32+H33)*Inputs!$D$104)*$H$12 -> -3.5992 | I36: =-(I31*Inputs!$D$102+(I32+I33)*Inputs!$D$104)*$H$12 -> -3.5992 | J36: =-(J31*Inputs!$D$102+(J32+J33)*Inputs!$D$104)*$H$12 -> -3.939 | K36: =-(K31*Inputs!$D$102+(K32+K33)*Inputs!$D$104)*$H$12 -> -0.25483 | L36: =-(L31*Inputs!$D$102+(L32+L33)*Inputs!$D$104)*$H$12 -> -0.2998 | N36: =-(N31*Inputs!$E$102+(N32+N33)*Inputs!$E$104)*$N$12 -> -2.4995 | O36: =-(O31*Inputs!$E$102+(O32+O33)*Inputs!$E$104)*$N$12 -> -2.4995 | P36: =-(P31*Inputs!$E$102+(P32+P33)*Inputs!$E$104)*$N$12 -> -2.6994 | Q36: =-(Q31*Inputs!$E$102+(Q32+Q33)*Inputs!$E$104)*$N$12 -> -0.15291 | R36: =-(R31*Inputs!$E$102+(R32+R33)*Inputs!$E$104)*$N$12 -> -0.1699 | T36: =-(T31*Inputs!$F$102+(T32+T33)*Inputs!$F$104)*$T$12 -> -1.7997 | U36: =-(U31*Inputs!$F$102+(U32+U33)*Inputs!$F$104)*$T$12 -> -1.7997 | V36: =-(V31*Inputs!$F$102+(V32+V33)*Inputs!$F$104)*$T$12 -> -1.91465 | W36: =-(W31*Inputs!$F$102+(W32+W33)*Inputs!$F$104)*$T$12 -> -0.078705 | X36: =-(X31*Inputs!$F$102+(X32+X33)*Inputs!$F$104)*$T$12 -> -0.08745 | Z36: =-(Z31*Inputs!$E$102+(Z32+Z33)*Inputs!$E$104)*$Z$12 -> -2.4995 | AA36: =-(AA31*Inputs!$E$102+(AA32+AA33)*Inputs!$E$104)*$Z$12 -> -2.4995 | AB36: =-(AB31*Inputs!$E$102+(AB32+AB33)*Inputs!$E$104)*$Z$12 -> -2.6994 | AC36: =-(AC31*Inputs!$E$102+(AC32+AC33)*Inputs!$E$104)*$Z$12 -> -0.15291 | AD36: =-(AD31*Inputs!$E$102+(AD32+AD33)*Inputs!$E$104)*$Z$12 -> -0.1699 | AF36: =-(AF31*Inputs!$E$102+(AF32+AF33)*Inputs!$E$104)*$AF$12 -> -2.4995 | AG36: =-(AG31*Inputs!$E$102+(AG32+AG33)*Inputs!$E$104)*$AF$12 -> -2.4995 | AH36: =-(AH31*Inputs!$E$102+(AH32+AH33)*Inputs!$E$104)*$AF$12 -> -2.6994 | AI36: =-(AI31*Inputs!$E$102+(AI32+AI33)*Inputs!$E$104)*$AF$12 -> -0.15291 | AJ36: =-(AJ31*Inputs!$E$102+(AJ32+AJ33)*Inputs!$E$104)*$AF$12 -> -0.1699 | AL36: =-(AL31*Inputs!$E$102+(AL32+AL33)*Inputs!$E$104)*$AL$12 -> -2.4995 | AM36: =-(AM31*Inputs!$E$102+(AM32+AM33)*Inputs!$E$104)*$AL$12 -> -2.4995 | AN36: =-(AN31*Inputs!$E$102+(AN32+AN33)*Inputs!$E$104)*$AL$12 -> -2.6994 | AO36: =-(AO31*Inputs!$E$102+(AO32+AO33)*Inputs!$E$104)*$AL$12 -> -0.15291 | AP36: =-(AP31*Inputs!$E$102+(AP32+AP33)*Inputs!$E$104)*$AL$12 -> -0.1699 | AR36: =-(AR31*Inputs!$E$102+(AR32+AR33)*Inputs!$E$104)*$AR$12 -> -2.4995 | AS36: =-(AS31*Inputs!$E$102+(AS32+AS33)*Inputs!$E$104)*$AR$12 -> -2.4995 | AT36: =-(AT31*Inputs!$E$102+(AT32+AT33)*Inputs!$E$104)*$AR$12 -> -2.6994 | AU36: =-(AU31*Inputs!$E$102+(AU32+AU33)*Inputs!$E$104)*$AR$12 -> -0.15291 | AV36: =-(AV31*Inputs!$E$102+(AV32+AV33)*Inputs!$E$104)*$AR$12 -> -0.1699 | AX36: =-(AX31*Inputs!$E$102+(AX32+AX33)*Inputs!$E$104)*$AX$12 -> -2.4995 | AY36: =-(AY31*Inputs!$E$102+(AY32+AY33)*Inputs!$E$104)*$AX$12 -> -2.4995 | AZ36: =-(AZ31*Inputs!$E$102+(AZ32+AZ33)*Inputs!$E$104)*$AX$12 -> -2.6994 | BA36: =-(BA31*Inputs!$E$102+(BA32+BA33)*Inputs!$E$104)*$AX$12 -> -0.15291 | BB36: =-(BB31*Inputs!$E$102+(BB32+BB33)*Inputs!$E$104)*$AX$12 -> -0.1699 | BD36: =-(BD31*Inputs!$E$102+(BD32+BD33)*Inputs!$E$104)*$BD$12 -> -4.999 | BE36: =-(BE31*Inputs!$E$102+(BE32+BE33)*Inputs!$E$104)*$BD$12 -> -4.999 | BF36: =-(BF31*Inputs!$E$102+(BF32+BF33)*Inputs!$E$104)*$BD$12 -> -5.3988 | BG36: =-(BG31*Inputs!$E$102+(BG32+BG33)*Inputs!$E$104)*$BD$12 -> -0.30582 | BH36: =-(BH31*Inputs!$E$102+(BH32+BH33)*Inputs!$E$104)*$BD$12 -> -0.3398
A37: Net revenue | B37: =B35+B36 -> 47.4905 | C37: =C35+C36 -> 47.4905 | D37: =D35+D36 -> 67.2806 | E37: =E35+E36 -> 15.13809 | F37: =F35+F36 -> 16.8201 | H37: =H35+H36 -> 41.3908 | I37: =I35+I36 -> 41.3908 | J37: =J35+J36 -> 58.041 | K37: =K35+K36 -> 12.48667 | L37: =L35+L36 -> 14.6902 | N37: =N35+N36 -> 47.4905 | O37: =O35+O36 -> 47.4905 | P37: =P35+P36 -> 67.2806 | Q37: =Q35+Q36 -> 15.13809 | R37: =R35+R36 -> 16.8201 | T37: =T35+T36 -> 58.1903 | U37: =U35+U36 -> 58.1903 | V37: =V35+V36 -> 81.06535 | W37: =W35+W36 -> 15.662295 | X37: =X35+X36 -> 21.39255 | Z37: =Z35+Z36 -> 47.4905 | AA37: =AA35+AA36 -> 47.4905 | AB37: =AB35+AB36 -> 67.2806 | AC37: =AC35+AC36 -> 15.13809 | AD37: =AD35+AD36 -> 16.8201 | AF37: =AF35+AF36 -> 47.4905 | AG37: =AG35+AG36 -> 47.4905 | AH37: =AH35+AH36 -> 67.2806 | AI37: =AI35+AI36 -> 15.13809 | AJ37: =AJ35+AJ36 -> 16.8201 | AL37: =AL35+AL36 -> 47.4905 | AM37: =AM35+AM36 -> 47.4905 | AN37: =AN35+AN36 -> 67.2806 | AO37: =AO35+AO36 -> 15.13809 | AP37: =AP35+AP36 -> 16.8201 | AR37: =AR35+AR36 -> 47.4905 | AS37: =AS35+AS36 -> 47.4905 | AT37: =AT35+AT36 -> 67.2806 | AU37: =AU35+AU36 -> 15.13809 | AV37: =AV35+AV36 -> 16.8201 | AX37: =AX35+AX36 -> 47.4905 | AY37: =AY35+AY36 -> 47.4905 | AZ37: =AZ35+AZ36 -> 67.2806 | BA37: =BA35+BA36 -> 15.13809 | BB37: =BB35+BB36 -> 16.8201 | BD37: =BD35+BD36 -> 44.991 | BE37: =BE35+BE36 -> 44.991 | BF37: =BF35+BF36 -> 64.5812 | BG37: =BG35+BG36 -> 14.98518 | BH37: =BH35+BH36 -> 16.6502
A38: Product cost - fountain | B38: =-B28*$B$15 -> -38.3265 | C38: =-C28*$B$22 -> -25.965622 | D38: =-D28*$B$22 -> -25.965622 | E38: =-E28*$B$22 -> 0 | F38: =-F28*$B$22 -> 0 | H38: =-H28*$H$15 -> -48.564 | I38: =-I28*$H$22 -> -41.200698 | J38: =-J28*$H$22 -> -41.200698 | K38: =-K28*$H$22 -> 0 | L38: =-L28*$H$22 -> 0 | N38: =-N28*$N$15 -> -38.3265 | O38: =-O28*$N$22 -> -25.965622 | P38: =-P28*$N$22 -> -25.965622 | Q38: =-Q28*$N$22 -> 0 | R38: =-R28*$N$22 -> 0 | T38: =-T28*$T$15 -> -21.79 | U38: =-U28*$T$22 -> -15.60878 | V38: =-V28*$T$22 -> -15.60878 | W38: =-W28*$T$22 -> 0 | X38: =-X28*$T$22 -> 0 | Z38: =-Z28*$Z$15 -> -38.3265 | AA38: =-AA28*$Z$22 -> -25.965622 | AB38: =-AB28*$Z$22 -> -25.965622 | AC38: =-AC28*$Z$22 -> 0 | AD38: =-AD28*$Z$22 -> 0 | AF38: =-AF28*$AF$15 -> -44.075475 | AG38: =-AG28*$AF$22 -> -28.395392 | AH38: =-AH28*$AF$22 -> -28.395392 | AI38: =-AI28*$AF$22 -> 0 | AJ38: =-AJ28*$AF$22 -> 0 | AL38: =-AL28*$AL$15 -> -38.3265 | AM38: =-AM28*$AL$22 -> -25.965622 | AN38: =-AN28*$AL$22 -> -25.965622 | AO38: =-AO28*$AL$22 -> 0 | AP38: =-AP28*$AL$22 -> 0 | AR38: =-AR28*$AR$15 -> -38.3265 | AS38: =-AS28*$AR$22 -> -25.965622 | AT38: =-AT28*$AR$22 -> -25.965622 | AU38: =-AU28*$AR$22 -> 0 | AV38: =-AV28*$AR$22 -> 0 | AX38: =-AX28*$AX$15 -> -38.3265 | AY38: =-AY28*$AX$22 -> -25.965622 | AZ38: =-AZ28*$AX$22 -> -25.965622 | BA38: =-BA28*$AX$22 -> 0 | BB38: =-BB28*$AX$22 -> 0 | BD38: =-BD28*$BD$15 -> -38.3265 | BE38: =-BE28*$BD$22 -> -25.965622 | BF38: =-BF28*$BD$22 -> -25.965622 | BG38: =-BG28*$BD$22 -> 0 | BH38: =-BH28*$BD$22 -> 0
A39: Product cost - litter mat | B39: =-B29*$B$23 -> 0 | C39: =-C29*$B$23 -> 0 | D39: =-D29*$B$23 -> -5.075 | E39: =-E29*$B$23 -> 0 | F39: =-F29*$B$23 -> 0 | H39: =-H29*$H$23 -> 0 | I39: =-I29*$H$23 -> 0 | J39: =-J29*$H$23 -> -6.7 | K39: =-K29*$H$23 -> 0 | L39: =-L29*$H$23 -> 0 | N39: =-N29*$N$23 -> 0 | O39: =-O29*$N$23 -> 0 | P39: =-P29*$N$23 -> -5.075 | Q39: =-Q29*$N$23 -> 0 | R39: =-R29*$N$23 -> 0 | T39: =-T29*$T$23 -> 0 | U39: =-U29*$T$23 -> 0 | V39: =-V29*$T$23 -> -3 | W39: =-W29*$T$23 -> 0 | X39: =-X29*$T$23 -> 0 | Z39: =-Z29*$Z$23 -> 0 | AA39: =-AA29*$Z$23 -> 0 | AB39: =-AB29*$Z$23 -> -5.075 | AC39: =-AC29*$Z$23 -> 0 | AD39: =-AD29*$Z$23 -> 0 | AF39: =-AF29*$AF$23 -> 0 | AG39: =-AG29*$AF$23 -> 0 | AH39: =-AH29*$AF$23 -> -5.71625 | AI39: =-AI29*$AF$23 -> 0 | AJ39: =-AJ29*$AF$23 -> 0 | AL39: =-AL29*$AL$23 -> 0 | AM39: =-AM29*$AL$23 -> 0 | AN39: =-AN29*$AL$23 -> -5.075 | AO39: =-AO29*$AL$23 -> 0 | AP39: =-AP29*$AL$23 -> 0 | AR39: =-AR29*$AR$23 -> 0 | AS39: =-AS29*$AR$23 -> 0 | AT39: =-AT29*$AR$23 -> -5.075 | AU39: =-AU29*$AR$23 -> 0 | AV39: =-AV29*$AR$23 -> 0 | AX39: =-AX29*$AX$23 -> 0 | AY39: =-AY29*$AX$23 -> 0 | AZ39: =-AZ29*$AX$23 -> -5.075 | BA39: =-BA29*$AX$23 -> 0 | BB39: =-BB29*$AX$23 -> 0 | BD39: =-BD29*$BD$23 -> 0 | BE39: =-BE29*$BD$23 -> 0 | BF39: =-BF29*$BD$23 -> -5.075 | BG39: =-BG29*$BD$23 -> 0 | BH39: =-BH29*$BD$23 -> 0
A40: Product cost - filters | B40: =-B30*$B$24 -> 0 | C40: =-C30*$B$24 -> 0 | D40: =-D30*$B$24 -> 0 | E40: =-E30*$B$24 -> -5.2425 | F40: =-F30*$B$24 -> -5.2425 | H40: =-H30*$H$24 -> 0 | I40: =-I30*$H$24 -> 0 | J40: =-J30*$H$24 -> 0 | K40: =-K30*$H$24 -> -6.5675 | L40: =-L30*$H$24 -> -6.5675 | N40: =-N30*$N$24 -> 0 | O40: =-O30*$N$24 -> 0 | P40: =-P30*$N$24 -> 0 | Q40: =-Q30*$N$24 -> -5.2425 | R40: =-R30*$N$24 -> -5.2425 | T40: =-T30*$T$24 -> 0 | U40: =-U30*$T$24 -> 0 | V40: =-V30*$T$24 -> 0 | W40: =-W30*$T$24 -> -4.3625 | X40: =-X30*$T$24 -> -4.3625 | Z40: =-Z30*$Z$24 -> 0 | AA40: =-AA30*$Z$24 -> 0 | AB40: =-AB30*$Z$24 -> 0 | AC40: =-AC30*$Z$24 -> -5.2425 | AD40: =-AD30*$Z$24 -> -5.2425 | AF40: =-AF30*$AF$24 -> 0 | AG40: =-AG30*$AF$24 -> 0 | AH40: =-AH30*$AF$24 -> 0 | AI40: =-AI30*$AF$24 -> -5.848875 | AJ40: =-AJ30*$AF$24 -> -5.848875 | AL40: =-AL30*$AL$24 -> 0 | AM40: =-AM30*$AL$24 -> 0 | AN40: =-AN30*$AL$24 -> 0 | AO40: =-AO30*$AL$24 -> -5.2425 | AP40: =-AP30*$AL$24 -> -5.2425 | AR40: =-AR30*$AR$24 -> 0 | AS40: =-AS30*$AR$24 -> 0 | AT40: =-AT30*$AR$24 -> 0 | AU40: =-AU30*$AR$24 -> -5.2425 | AV40: =-AV30*$AR$24 -> -5.2425 | AX40: =-AX30*$AX$24 -> 0 | AY40: =-AY30*$AX$24 -> 0 | AZ40: =-AZ30*$AX$24 -> 0 | BA40: =-BA30*$AX$24 -> -5.2425 | BB40: =-BB30*$AX$24 -> -5.2425 | BD40: =-BD30*$BD$24 -> 0 | BE40: =-BE30*$BD$24 -> 0 | BF40: =-BF30*$BD$24 -> 0 | BG40: =-BG30*$BD$24 -> -5.2425 | BH40: =-BH30*$BD$24 -> -5.2425
A41: 3PL pick/pack + packaging (incl. hidden-fee uplift) | B41: 0 | C41: =-(Inputs!$G$88+Inputs!$G$90)*(1+Inputs!$G$92) -> -5.1 | D41: =-(Inputs!$G$88+Inputs!$G$89+Inputs!$G$90)*(1+Inputs!$G$92) -> -5.7 | E41: =-(Inputs!$G$88+Inputs!$G$91)*(1+Inputs!$G$92) -> -4.2 | F41: =-(Inputs!$G$88+Inputs!$G$91)*(1+Inputs!$G$92) -> -4.2 | H41: 0 | I41: =-(Inputs!$D$88+Inputs!$D$90)*(1+Inputs!$D$92) -> -6.4125 | J41: =-(Inputs!$D$88+Inputs!$D$89+Inputs!$D$90)*(1+Inputs!$D$92) -> -7.425 | K41: =-(Inputs!$D$88+Inputs!$D$91)*(1+Inputs!$D$92) -> -5.4 | L41: =-(Inputs!$D$88+Inputs!$D$91)*(1+Inputs!$D$92) -> -5.4 | N41: 0 | O41: =-(Inputs!$E$88+Inputs!$E$90)*(1+Inputs!$E$92) -> -5.1 | P41: =-(Inputs!$E$88+Inputs!$E$89+Inputs!$E$90)*(1+Inputs!$E$92) -> -5.7 | Q41: =-(Inputs!$E$88+Inputs!$E$91)*(1+Inputs!$E$92) -> -4.2 | R41: =-(Inputs!$E$88+Inputs!$E$91)*(1+Inputs!$E$92) -> -4.2 | T41: 0 | U41: =-(Inputs!$F$88+Inputs!$F$90)*(1+Inputs!$F$92) -> -3.3 | V41: =-(Inputs!$F$88+Inputs!$F$89+Inputs!$F$90)*(1+Inputs!$F$92) -> -3.74 | W41: =-(Inputs!$F$88+Inputs!$F$91)*(1+Inputs!$F$92) -> -2.585 | X41: =-(Inputs!$F$88+Inputs!$F$91)*(1+Inputs!$F$92) -> -2.585 | Z41: 0 | AA41: =-(Inputs!$E$88+Inputs!$E$90)*(1+Inputs!$E$92) -> -5.1 | AB41: =-(Inputs!$E$88+Inputs!$E$89+Inputs!$E$90)*(1+Inputs!$E$92) -> -5.7 | AC41: =-(Inputs!$E$88+Inputs!$E$91)*(1+Inputs!$E$92) -> -4.2 | AD41: =-(Inputs!$E$88+Inputs!$E$91)*(1+Inputs!$E$92) -> -4.2 | AF41: 0 | AG41: =-(Inputs!$E$88+Inputs!$E$90)*(1+Inputs!$E$92) -> -5.1 | AH41: =-(Inputs!$E$88+Inputs!$E$89+Inputs!$E$90)*(1+Inputs!$E$92) -> -5.7 | AI41: =-(Inputs!$E$88+Inputs!$E$91)*(1+Inputs!$E$92) -> -4.2 | AJ41: =-(Inputs!$E$88+Inputs!$E$91)*(1+Inputs!$E$92) -> -4.2 | AL41: 0 | AM41: =-(Inputs!$E$88+Inputs!$E$90)*(1+Inputs!$E$92) -> -5.1 | AN41: =-(Inputs!$E$88+Inputs!$E$89+Inputs!$E$90)*(1+Inputs!$E$92) -> -5.7 | AO41: =-(Inputs!$E$88+Inputs!$E$91)*(1+Inputs!$E$92) -> -4.2 | AP41: =-(Inputs!$E$88+Inputs!$E$91)*(1+Inputs!$E$92) -> -4.2 | AR41: 0 | AS41: =-(Inputs!$E$88+Inputs!$E$90)*(1+Inputs!$E$92) -> -5.1 | AT41: =-(Inputs!$E$88+Inputs!$E$89+Inputs!$E$90)*(1+Inputs!$E$92) -> -5.7 | AU41: =-(Inputs!$E$88+Inputs!$E$91)*(1+Inputs!$E$92) -> -4.2 | AV41: =-(Inputs!$E$88+Inputs!$E$91)*(1+Inputs!$E$92) -> -4.2 | AX41: 0 | AY41: =-(Inputs!$E$88+Inputs!$E$90)*(1+Inputs!$E$92) -> -5.1 | AZ41: =-(Inputs!$E$88+Inputs!$E$89+Inputs!$E$90)*(1+Inputs!$E$92) -> -5.7 | BA41: =-(Inputs!$E$88+Inputs!$E$91)*(1+Inputs!$E$92) -> -4.2 | BB41: =-(Inputs!$E$88+Inputs!$E$91)*(1+Inputs!$E$92) -> -4.2 | BD41: 0 | BE41: =-(Inputs!$E$88+Inputs!$E$90)*(1+Inputs!$E$92) -> -5.1 | BF41: =-(Inputs!$E$88+Inputs!$E$89+Inputs!$E$90)*(1+Inputs!$E$92) -> -5.7 | BG41: =-(Inputs!$E$88+Inputs!$E$91)*(1+Inputs!$E$92) -> -4.2 | BH41: =-(Inputs!$E$88+Inputs!$E$91)*(1+Inputs!$E$92) -> -4.2
A42: Postage (USPS Ground Advantage) | B42: 0 | C42: =-Inputs!$G$83*$B$9 -> -10.5 | D42: =-Inputs!$G$84*$B$9 -> -12.12 | E42: =-Inputs!$G$85*$B$9 -> -8.24 | F42: =-Inputs!$G$85*$B$9 -> -8.24 | H42: 0 | I42: =-Inputs!$D$83*$H$9 -> -11.96 | J42: =-Inputs!$D$84*$H$9 -> -14.21 | K42: =-Inputs!$D$85*$H$9 -> -8.595 | L42: =-Inputs!$D$85*$H$9 -> -8.595 | N42: 0 | O42: =-Inputs!$E$83*$N$9 -> -10.5 | P42: =-Inputs!$E$84*$N$9 -> -12.12 | Q42: =-Inputs!$E$85*$N$9 -> -8.24 | R42: =-Inputs!$E$85*$N$9 -> -8.24 | T42: 0 | U42: =-Inputs!$F$83*$T$9 -> -9.7222222 | V42: =-Inputs!$F$84*$T$9 -> -11.222222 | W42: =-Inputs!$F$85*$T$9 -> -6.4851852 | X42: =-Inputs!$F$85*$T$9 -> -6.4851852 | Z42: 0 | AA42: =-Inputs!$E$83*$Z$9 -> -10.5 | AB42: =-Inputs!$E$84*$Z$9 -> -12.12 | AC42: =-Inputs!$E$85*$Z$9 -> -8.24 | AD42: =-Inputs!$E$85*$Z$9 -> -8.24 | AF42: 0 | AG42: =-Inputs!$E$83*$AF$9 -> -10.5 | AH42: =-Inputs!$E$84*$AF$9 -> -12.12 | AI42: =-Inputs!$E$85*$AF$9 -> -8.24 | AJ42: =-Inputs!$E$85*$AF$9 -> -8.24 | AL42: 0 | AM42: =-Inputs!$E$83*$AL$9 -> -12.6 | AN42: =-Inputs!$E$84*$AL$9 -> -14.544 | AO42: =-Inputs!$E$85*$AL$9 -> -9.888 | AP42: =-Inputs!$E$85*$AL$9 -> -9.888 | AR42: 0 | AS42: =-Inputs!$E$83*$AR$9 -> -10.5 | AT42: =-Inputs!$E$84*$AR$9 -> -12.12 | AU42: =-Inputs!$E$85*$AR$9 -> -8.24 | AV42: =-Inputs!$E$85*$AR$9 -> -8.24 | AX42: 0 | AY42: =-Inputs!$E$83*$AX$9 -> -10.5 | AZ42: =-Inputs!$E$84*$AX$9 -> -12.12 | BA42: =-Inputs!$E$85*$AX$9 -> -8.24 | BB42: =-Inputs!$E$85*$AX$9 -> -8.24 | BD42: 0 | BE42: =-Inputs!$E$83*$BD$9 -> -10.5 | BF42: =-Inputs!$E$84*$BD$9 -> -12.12 | BG42: =-Inputs!$E$85*$BD$9 -> -8.24 | BH42: =-Inputs!$E$85*$BD$9 -> -8.24
A43: Payment processing | B43: =-(Inputs!$G$100*B35+Inputs!$G$101) -> -1.74971 | C43: =-(Inputs!$G$100*C35+Inputs!$G$101) -> -1.74971 | D43: =-(Inputs!$G$100*D35+Inputs!$G$101) -> -2.32942 | E43: =-(Inputs!$G$100*E35+Inputs!$G$101) -> -0.743439 | F43: =-(Inputs!$G$100*F35+Inputs!$G$101) -> -0.79271 | H43: =-(Inputs!$D$100*H35+Inputs!$D$101) -> -1.60471 | I43: =-(Inputs!$D$100*I35+Inputs!$D$101) -> -1.60471 | J43: =-(Inputs!$D$100*J35+Inputs!$D$101) -> -2.09742 | K43: =-(Inputs!$D$100*K35+Inputs!$D$101) -> -0.6695035 | L43: =-(Inputs!$D$100*L35+Inputs!$D$101) -> -0.73471 | N43: =-(Inputs!$E$100*N35+Inputs!$E$101) -> -1.74971 | O43: =-(Inputs!$E$100*O35+Inputs!$E$101) -> -1.74971 | P43: =-(Inputs!$E$100*P35+Inputs!$E$101) -> -2.32942 | Q43: =-(Inputs!$E$100*Q35+Inputs!$E$101) -> -0.743439 | R43: =-(Inputs!$E$100*R35+Inputs!$E$101) -> -0.79271 | T43: =-(Inputs!$F$100*T35+Inputs!$F$101) -> -2.03971 | U43: =-(Inputs!$F$100*U35+Inputs!$F$101) -> -2.03971 | V43: =-(Inputs!$F$100*V35+Inputs!$F$101) -> -2.70642 | W43: =-(Inputs!$F$100*W35+Inputs!$F$101) -> -0.756489 | X43: =-(Inputs!$F$100*X35+Inputs!$F$101) -> -0.92292 | Z43: =-(Inputs!$E$100*Z35+Inputs!$E$101) -> -1.74971 | AA43: =-(Inputs!$E$100*AA35+Inputs!$E$101) -> -1.74971 | AB43: =-(Inputs!$E$100*AB35+Inputs!$E$101) -> -2.32942 | AC43: =-(Inputs!$E$100*AC35+Inputs!$E$101) -> -0.743439 | AD43: =-(Inputs!$E$100*AD35+Inputs!$E$101) -> -0.79271 | AF43: =-(Inputs!$E$100*AF35+Inputs!$E$101) -> -1.74971 | AG43: =-(Inputs!$E$100*AG35+Inputs!$E$101) -> -1.74971 | AH43: =-(Inputs!$E$100*AH35+Inputs!$E$101) -> -2.32942 | AI43: =-(Inputs!$E$100*AI35+Inputs!$E$101) -> -0.743439 | AJ43: =-(Inputs!$E$100*AJ35+Inputs!$E$101) -> -0.79271 | AL43: =-(Inputs!$E$100*AL35+Inputs!$E$101) -> -1.74971 | AM43: =-(Inputs!$E$100*AM35+Inputs!$E$101) -> -1.74971 | AN43: =-(Inputs!$E$100*AN35+Inputs!$E$101) -> -2.32942 | AO43: =-(Inputs!$E$100*AO35+Inputs!$E$101) -> -0.743439 | AP43: =-(Inputs!$E$100*AP35+Inputs!$E$101) -> -0.79271 | AR43: =-(Inputs!$E$100*AR35+Inputs!$E$101) -> -1.74971 | AS43: =-(Inputs!$E$100*AS35+Inputs!$E$101) -> -1.74971 | AT43: =-(Inputs!$E$100*AT35+Inputs!$E$101) -> -2.32942 | AU43: =-(Inputs!$E$100*AU35+Inputs!$E$101) -> -0.743439 | AV43: =-(Inputs!$E$100*AV35+Inputs!$E$101) -> -0.79271 | AX43: =-(Inputs!$E$100*AX35+Inputs!$E$101) -> -1.74971 | AY43: =-(Inputs!$E$100*AY35+Inputs!$E$101) -> -1.74971 | AZ43: =-(Inputs!$E$100*AZ35+Inputs!$E$101) -> -2.32942 | BA43: =-(Inputs!$E$100*BA35+Inputs!$E$101) -> -0.743439 | BB43: =-(Inputs!$E$100*BB35+Inputs!$E$101) -> -0.79271 | BD43: =-(Inputs!$E$100*BD35+Inputs!$E$101) -> -1.74971 | BE43: =-(Inputs!$E$100*BE35+Inputs!$E$101) -> -1.74971 | BF43: =-(Inputs!$E$100*BF35+Inputs!$E$101) -> -2.32942 | BG43: =-(Inputs!$E$100*BG35+Inputs!$E$101) -> -0.743439 | BH43: =-(Inputs!$E$100*BH35+Inputs!$E$101) -> -0.79271
A44: Warranty replacements (expected) | B44: =-Inputs!$G$103*$B$12*$B$15 -> -1.149795 | C44: =-Inputs!$G$103*$B$12*($B$22+(Inputs!$G$88+Inputs!$G$90)*(1+Inputs!$G$92)+Inputs!$G$83*$B$9) -> -1.2469687 | D44: =-Inputs!$G$103*$B$12*($B$22+(Inputs!$G$88+Inputs!$G$90)*(1+Inputs!$G$92)+Inputs!$G$83*$B$9) -> -1.2469687 | E44: 0 | F44: 0 | H44: =-Inputs!$D$103*$H$12*$H$15 -> -2.4282 | I44: =-Inputs!$D$103*$H$12*($H$22+(Inputs!$D$88+Inputs!$D$90)*(1+Inputs!$D$92)+Inputs!$D$83*$H$9) -> -2.9786599 | J44: =-Inputs!$D$103*$H$12*($H$22+(Inputs!$D$88+Inputs!$D$90)*(1+Inputs!$D$92)+Inputs!$D$83*$H$9) -> -2.9786599 | K44: 0 | L44: 0 | N44: =-Inputs!$E$103*$N$12*$N$15 -> -1.149795 | O44: =-Inputs!$E$103*$N$12*($N$22+(Inputs!$E$88+Inputs!$E$90)*(1+Inputs!$E$92)+Inputs!$E$83*$N$9) -> -1.2469687 | P44: =-Inputs!$E$103*$N$12*($N$22+(Inputs!$E$88+Inputs!$E$90)*(1+Inputs!$E$92)+Inputs!$E$83*$N$9) -> -1.2469687 | Q44: 0 | R44: 0 | T44: =-Inputs!$F$103*$T$12*$T$15 -> -0.32685 | U44: =-Inputs!$F$103*$T$12*($T$22+(Inputs!$F$88+Inputs!$F$90)*(1+Inputs!$F$92)+Inputs!$F$83*$T$9) -> -0.42946503 | V44: =-Inputs!$F$103*$T$12*($T$22+(Inputs!$F$88+Inputs!$F$90)*(1+Inputs!$F$92)+Inputs!$F$83*$T$9) -> -0.42946503 | W44: 0 | X44: 0 | Z44: =-Inputs!$E$103*$Z$12*$Z$15 -> -1.149795 | AA44: =-Inputs!$E$103*$Z$12*($Z$22+(Inputs!$E$88+Inputs!$E$90)*(1+Inputs!$E$92)+Inputs!$E$83*$Z$9) -> -1.2469687 | AB44: =-Inputs!$E$103*$Z$12*($Z$22+(Inputs!$E$88+Inputs!$E$90)*(1+Inputs!$E$92)+Inputs!$E$83*$Z$9) -> -1.2469687 | AC44: 0 | AD44: 0 | AF44: =-Inputs!$E$103*$AF$12*$AF$15 -> -1.3222643 | AG44: =-Inputs!$E$103*$AF$12*($AF$22+(Inputs!$E$88+Inputs!$E$90)*(1+Inputs!$E$92)+Inputs!$E$83*$AF$9) -> -1.3198618 | AH44: =-Inputs!$E$103*$AF$12*($AF$22+(Inputs!$E$88+Inputs!$E$90)*(1+Inputs!$E$92)+Inputs!$E$83*$AF$9) -> -1.3198618 | AI44: 0 | AJ44: 0 | AL44: =-Inputs!$E$103*$AL$12*$AL$15 -> -1.149795 | AM44: =-Inputs!$E$103*$AL$12*($AL$22+(Inputs!$E$88+Inputs!$E$90)*(1+Inputs!$E$92)+Inputs!$E$83*$AL$9) -> -1.3099687 | AN44: =-Inputs!$E$103*$AL$12*($AL$22+(Inputs!$E$88+Inputs!$E$90)*(1+Inputs!$E$92)+Inputs!$E$83*$AL$9) -> -1.3099687 | AO44: 0 | AP44: 0 | AR44: =-Inputs!$E$103*$AR$12*$AR$15 -> -1.149795 | AS44: =-Inputs!$E$103*$AR$12*($AR$22+(Inputs!$E$88+Inputs!$E$90)*(1+Inputs!$E$92)+Inputs!$E$83*$AR$9) -> -1.2469687 | AT44: =-Inputs!$E$103*$AR$12*($AR$22+(Inputs!$E$88+Inputs!$E$90)*(1+Inputs!$E$92)+Inputs!$E$83*$AR$9) -> -1.2469687 | AU44: 0 | AV44: 0 | AX44: =-Inputs!$E$103*$AX$12*$AX$15 -> -1.149795 | AY44: =-Inputs!$E$103*$AX$12*($AX$22+(Inputs!$E$88+Inputs!$E$90)*(1+Inputs!$E$92)+Inputs!$E$83*$AX$9) -> -1.2469687 | AZ44: =-Inputs!$E$103*$AX$12*($AX$22+(Inputs!$E$88+Inputs!$E$90)*(1+Inputs!$E$92)+Inputs!$E$83*$AX$9) -> -1.2469687 | BA44: 0 | BB44: 0 | BD44: =-Inputs!$E$103*$BD$12*$BD$15 -> -2.29959 | BE44: =-Inputs!$E$103*$BD$12*($BD$22+(Inputs!$E$88+Inputs!$E$90)*(1+Inputs!$E$92)+Inputs!$E$83*$BD$9) -> -2.4939373 | BF44: =-Inputs!$E$103*$BD$12*($BD$22+(Inputs!$E$88+Inputs!$E$90)*(1+Inputs!$E$92)+Inputs!$E$83*$BD$9) -> -2.4939373 | BG44: 0 | BH44: 0
A45: Lost / duty-refused parcels (test stage) | B45: =-Inputs!$G$28*$B$15 -> -1.916325 | C45: 0 | D45: 0 | E45: 0 | F45: 0 | H45: =-Inputs!$D$28*$H$15 -> -3.39948 | I45: 0 | J45: 0 | K45: 0 | L45: 0 | N45: =-Inputs!$E$28*$N$15 -> -1.916325 | O45: 0 | P45: 0 | Q45: 0 | R45: 0 | T45: =-Inputs!$F$28*$T$15 -> -0.4358 | U45: 0 | V45: 0 | W45: 0 | X45: 0 | Z45: =-Inputs!$E$28*$Z$15 -> -1.916325 | AA45: 0 | AB45: 0 | AC45: 0 | AD45: 0 | AF45: =-Inputs!$E$28*$AF$15 -> -2.2037738 | AG45: 0 | AH45: 0 | AI45: 0 | AJ45: 0 | AL45: =-Inputs!$E$28*$AL$15 -> -1.916325 | AM45: 0 | AN45: 0 | AO45: 0 | AP45: 0 | AR45: =-Inputs!$E$28*$AR$15 -> -1.916325 | AS45: 0 | AT45: 0 | AU45: 0 | AV45: 0 | AX45: =-Inputs!$E$28*$AX$15 -> -1.916325 | AY45: 0 | AZ45: 0 | BA45: 0 | BB45: 0 | BD45: =-Inputs!$E$28*$BD$15 -> -1.916325 | BE45: 0 | BF45: 0 | BG45: 0 | BH45: 0
A46: Returns processing (3PL) | B46: 0 | C46: =-Inputs!$G$102*$B$12*Inputs!$G$93 -> -0.203 | D46: =-Inputs!$G$102*$B$12*Inputs!$G$93 -> -0.203 | E46: =-Inputs!$G$104*$B$12*Inputs!$G$93 -> -0.0406 | F46: =-Inputs!$G$104*$B$12*Inputs!$G$93 -> -0.0406 | H46: 0 | I46: =-Inputs!$D$102*$H$12*Inputs!$D$93 -> -0.56 | J46: =-Inputs!$D$102*$H$12*Inputs!$D$93 -> -0.56 | K46: =-Inputs!$D$104*$H$12*Inputs!$D$93 -> -0.14 | L46: =-Inputs!$D$104*$H$12*Inputs!$D$93 -> -0.14 | N46: 0 | O46: =-Inputs!$E$102*$N$12*Inputs!$E$93 -> -0.203 | P46: =-Inputs!$E$102*$N$12*Inputs!$E$93 -> -0.203 | Q46: =-Inputs!$E$104*$N$12*Inputs!$E$93 -> -0.0406 | R46: =-Inputs!$E$104*$N$12*Inputs!$E$93 -> -0.0406 | T46: 0 | U46: =-Inputs!$F$102*$T$12*Inputs!$F$93 -> -0.03 | V46: =-Inputs!$F$102*$T$12*Inputs!$F$93 -> -0.03 | W46: =-Inputs!$F$104*$T$12*Inputs!$F$93 -> -0.005 | X46: =-Inputs!$F$104*$T$12*Inputs!$F$93 -> -0.005 | Z46: 0 | AA46: =-Inputs!$E$102*$Z$12*Inputs!$E$93 -> -0.203 | AB46: =-Inputs!$E$102*$Z$12*Inputs!$E$93 -> -0.203 | AC46: =-Inputs!$E$104*$Z$12*Inputs!$E$93 -> -0.0406 | AD46: =-Inputs!$E$104*$Z$12*Inputs!$E$93 -> -0.0406 | AF46: 0 | AG46: =-Inputs!$E$102*$AF$12*Inputs!$E$93 -> -0.203 | AH46: =-Inputs!$E$102*$AF$12*Inputs!$E$93 -> -0.203 | AI46: =-Inputs!$E$104*$AF$12*Inputs!$E$93 -> -0.0406 | AJ46: =-Inputs!$E$104*$AF$12*Inputs!$E$93 -> -0.0406 | AL46: 0 | AM46: =-Inputs!$E$102*$AL$12*Inputs!$E$93 -> -0.203 | AN46: =-Inputs!$E$102*$AL$12*Inputs!$E$93 -> -0.203 | AO46: =-Inputs!$E$104*$AL$12*Inputs!$E$93 -> -0.0406 | AP46: =-Inputs!$E$104*$AL$12*Inputs!$E$93 -> -0.0406 | AR46: 0 | AS46: =-Inputs!$E$102*$AR$12*Inputs!$E$93 -> -0.203 | AT46: =-Inputs!$E$102*$AR$12*Inputs!$E$93 -> -0.203 | AU46: =-Inputs!$E$104*$AR$12*Inputs!$E$93 -> -0.0406 | AV46: =-Inputs!$E$104*$AR$12*Inputs!$E$93 -> -0.0406 | AX46: 0 | AY46: =-Inputs!$E$102*$AX$12*Inputs!$E$93 -> -0.203 | AZ46: =-Inputs!$E$102*$AX$12*Inputs!$E$93 -> -0.203 | BA46: =-Inputs!$E$104*$AX$12*Inputs!$E$93 -> -0.0406 | BB46: =-Inputs!$E$104*$AX$12*Inputs!$E$93 -> -0.0406 | BD46: 0 | BE46: =-Inputs!$E$102*$BD$12*Inputs!$E$93 -> -0.406 | BF46: =-Inputs!$E$102*$BD$12*Inputs!$E$93 -> -0.406 | BG46: =-Inputs!$E$104*$BD$12*Inputs!$E$93 -> -0.0812 | BH46: =-Inputs!$E$104*$BD$12*Inputs!$E$93 -> -0.0812
A47: Chargebacks (expected) | B47: =-Inputs!$G$108*(B35+Inputs!$G$109) -> -0.19497 | C47: =-Inputs!$G$108*(C35+Inputs!$G$109) -> -0.19497 | D47: =-Inputs!$G$108*(D35+Inputs!$G$109) -> -0.25494 | E47: =-Inputs!$G$108*(E35+Inputs!$G$109) -> -0.090873 | F47: =-Inputs!$G$108*(F35+Inputs!$G$109) -> -0.09597 | H47: =-Inputs!$D$108*(H35+Inputs!$D$109) -> -0.35994 | I47: =-Inputs!$D$108*(I35+Inputs!$D$109) -> -0.35994 | J47: =-Inputs!$D$108*(J35+Inputs!$D$109) -> -0.46188 | K47: =-Inputs!$D$108*(K35+Inputs!$D$109) -> -0.166449 | L47: =-Inputs!$D$108*(L35+Inputs!$D$109) -> -0.17994 | N47: =-Inputs!$E$108*(N35+Inputs!$E$109) -> -0.19497 | O47: =-Inputs!$E$108*(O35+Inputs!$E$109) -> -0.19497 | P47: =-Inputs!$E$108*(P35+Inputs!$E$109) -> -0.25494 | Q47: =-Inputs!$E$108*(Q35+Inputs!$E$109) -> -0.090873 | R47: =-Inputs!$E$108*(R35+Inputs!$E$109) -> -0.09597 | T47: =-Inputs!$F$108*(T35+Inputs!$F$109) -> -0.112485 | U47: =-Inputs!$F$108*(U35+Inputs!$F$109) -> -0.112485 | V47: =-Inputs!$F$108*(V35+Inputs!$F$109) -> -0.14697 | W47: =-Inputs!$F$108*(W35+Inputs!$F$109) -> -0.0461115 | X47: =-Inputs!$F$108*(X35+Inputs!$F$109) -> -0.05472 | Z47: =-Inputs!$E$108*(Z35+Inputs!$E$109) -> -0.19497 | AA47: =-Inputs!$E$108*(AA35+Inputs!$E$109) -> -0.19497 | AB47: =-Inputs!$E$108*(AB35+Inputs!$E$109) -> -0.25494 | AC47: =-Inputs!$E$108*(AC35+Inputs!$E$109) -> -0.090873 | AD47: =-Inputs!$E$108*(AD35+Inputs!$E$109) -> -0.09597 | AF47: =-Inputs!$E$108*(AF35+Inputs!$E$109) -> -0.19497 | AG47: =-Inputs!$E$108*(AG35+Inputs!$E$109) -> -0.19497 | AH47: =-Inputs!$E$108*(AH35+Inputs!$E$109) -> -0.25494 | AI47: =-Inputs!$E$108*(AI35+Inputs!$E$109) -> -0.090873 | AJ47: =-Inputs!$E$108*(AJ35+Inputs!$E$109) -> -0.09597 | AL47: =-Inputs!$E$108*(AL35+Inputs!$E$109) -> -0.19497 | AM47: =-Inputs!$E$108*(AM35+Inputs!$E$109) -> -0.19497 | AN47: =-Inputs!$E$108*(AN35+Inputs!$E$109) -> -0.25494 | AO47: =-Inputs!$E$108*(AO35+Inputs!$E$109) -> -0.090873 | AP47: =-Inputs!$E$108*(AP35+Inputs!$E$109) -> -0.09597 | AR47: =-Inputs!$E$108*(AR35+Inputs!$E$109) -> -0.19497 | AS47: =-Inputs!$E$108*(AS35+Inputs!$E$109) -> -0.19497 | AT47: =-Inputs!$E$108*(AT35+Inputs!$E$109) -> -0.25494 | AU47: =-Inputs!$E$108*(AU35+Inputs!$E$109) -> -0.090873 | AV47: =-Inputs!$E$108*(AV35+Inputs!$E$109) -> -0.09597 | AX47: =-Inputs!$E$108*(AX35+Inputs!$E$109) -> -0.19497 | AY47: =-Inputs!$E$108*(AY35+Inputs!$E$109) -> -0.19497 | AZ47: =-Inputs!$E$108*(AZ35+Inputs!$E$109) -> -0.25494 | BA47: =-Inputs!$E$108*(BA35+Inputs!$E$109) -> -0.090873 | BB47: =-Inputs!$E$108*(BB35+Inputs!$E$109) -> -0.09597 | BD47: =-Inputs!$E$108*(BD35+Inputs!$E$109) -> -0.19497 | BE47: =-Inputs!$E$108*(BE35+Inputs!$E$109) -> -0.19497 | BF47: =-Inputs!$E$108*(BF35+Inputs!$E$109) -> -0.25494 | BG47: =-Inputs!$E$108*(BG35+Inputs!$E$109) -> -0.090873 | BH47: =-Inputs!$E$108*(BH35+Inputs!$E$109) -> -0.09597
A48: Affiliate commissions (expected) | B48: =-Inputs!$G$122*Inputs!$G$123*B35 -> -0.44991 | C48: =-Inputs!$G$122*Inputs!$G$123*C35 -> -0.44991 | D48: =-Inputs!$G$122*Inputs!$G$123*D35 -> -0.62982 | E48: 0 | F48: 0 | H48: =-Inputs!$D$122*Inputs!$D$123*H35 -> -0.26994 | I48: =-Inputs!$D$122*Inputs!$D$123*I35 -> -0.26994 | J48: =-Inputs!$D$122*Inputs!$D$123*J35 -> -0.37188 | K48: 0 | L48: 0 | N48: =-Inputs!$E$122*Inputs!$E$123*N35 -> -0.44991 | O48: =-Inputs!$E$122*Inputs!$E$123*O35 -> -0.44991 | P48: =-Inputs!$E$122*Inputs!$E$123*P35 -> -0.62982 | Q48: 0 | R48: 0 | T48: =-Inputs!$F$122*Inputs!$F$123*T35 -> -0.5999 | U48: =-Inputs!$F$122*Inputs!$F$123*U35 -> -0.5999 | V48: =-Inputs!$F$122*Inputs!$F$123*V35 -> -0.8298 | W48: 0 | X48: 0 | Z48: =-Inputs!$E$122*Inputs!$E$123*Z35 -> -0.44991 | AA48: =-Inputs!$E$122*Inputs!$E$123*AA35 -> -0.44991 | AB48: =-Inputs!$E$122*Inputs!$E$123*AB35 -> -0.62982 | AC48: 0 | AD48: 0 | AF48: =-Inputs!$E$122*Inputs!$E$123*AF35 -> -0.44991 | AG48: =-Inputs!$E$122*Inputs!$E$123*AG35 -> -0.44991 | AH48: =-Inputs!$E$122*Inputs!$E$123*AH35 -> -0.62982 | AI48: 0 | AJ48: 0 | AL48: =-Inputs!$E$122*Inputs!$E$123*AL35 -> -0.44991 | AM48: =-Inputs!$E$122*Inputs!$E$123*AM35 -> -0.44991 | AN48: =-Inputs!$E$122*Inputs!$E$123*AN35 -> -0.62982 | AO48: 0 | AP48: 0 | AR48: =-Inputs!$E$122*Inputs!$E$123*AR35 -> -0.44991 | AS48: =-Inputs!$E$122*Inputs!$E$123*AS35 -> -0.44991 | AT48: =-Inputs!$E$122*Inputs!$E$123*AT35 -> -0.62982 | AU48: 0 | AV48: 0 | AX48: =-Inputs!$E$122*Inputs!$E$123*AX35 -> -0.44991 | AY48: =-Inputs!$E$122*Inputs!$E$123*AY35 -> -0.44991 | AZ48: =-Inputs!$E$122*Inputs!$E$123*AZ35 -> -0.62982 | BA48: 0 | BB48: 0 | BD48: =-Inputs!$E$122*Inputs!$E$123*BD35 -> -0.44991 | BE48: =-Inputs!$E$122*Inputs!$E$123*BE35 -> -0.44991 | BF48: =-Inputs!$E$122*Inputs!$E$123*BF35 -> -0.62982 | BG48: 0 | BH48: 0
A49: Total variable costs | B49: =SUM(B38:B48) -> -43.78721 | C49: =SUM(C38:C48) -> -45.410181 | D49: =SUM(D38:D48) -> -53.524771 | E49: =SUM(E38:E48) -> -18.557412 | F49: =SUM(F38:F48) -> -18.61178 | H49: =SUM(H38:H48) -> -56.62627 | I49: =SUM(I38:I48) -> -65.346447 | J49: =SUM(J38:J48) -> -76.005537 | K49: =SUM(K38:K48) -> -21.538452 | L49: =SUM(L38:L48) -> -21.61715 | N49: =SUM(N38:N48) -> -43.78721 | O49: =SUM(O38:O48) -> -45.410181 | P49: =SUM(P38:P48) -> -53.524771 | Q49: =SUM(Q38:Q48) -> -18.557412 | R49: =SUM(R38:R48) -> -18.61178 | T49: =SUM(T38:T48) -> -25.304745 | U49: =SUM(U38:U48) -> -31.842562 | V49: =SUM(V38:V48) -> -37.713657 | W49: =SUM(W38:W48) -> -14.240286 | X49: =SUM(X38:X48) -> -14.415325 | Z49: =SUM(Z38:Z48) -> -43.78721 | AA49: =SUM(AA38:AA48) -> -45.410181 | AB49: =SUM(AB38:AB48) -> -53.524771 | AC49: =SUM(AC38:AC48) -> -18.557412 | AD49: =SUM(AD38:AD48) -> -18.61178 | AF49: =SUM(AF38:AF48) -> -49.996103 | AG49: =SUM(AG38:AG48) -> -47.912844 | AH49: =SUM(AH38:AH48) -> -56.668684 | AI49: =SUM(AI38:AI48) -> -19.163787 | AJ49: =SUM(AJ38:AJ48) -> -19.218155 | AL49: =SUM(AL38:AL48) -> -43.78721 | AM49: =SUM(AM38:AM48) -> -47.573181 | AN49: =SUM(AN38:AN48) -> -56.011771 | AO49: =SUM(AO38:AO48) -> -20.205412 | AP49: =SUM(AP38:AP48) -> -20.25978 | AR49: =SUM(AR38:AR48) -> -43.78721 | AS49: =SUM(AS38:AS48) -> -45.410181 | AT49: =SUM(AT38:AT48) -> -53.524771 | AU49: =SUM(AU38:AU48) -> -18.557412 | AV49: =SUM(AV38:AV48) -> -18.61178 | AX49: =SUM(AX38:AX48) -> -43.78721 | AY49: =SUM(AY38:AY48) -> -45.410181 | AZ49: =SUM(AZ38:AZ48) -> -53.524771 | BA49: =SUM(BA38:BA48) -> -18.557412 | BB49: =SUM(BB38:BB48) -> -18.61178 | BD49: =SUM(BD38:BD48) -> -44.937005 | BE49: =SUM(BE38:BE48) -> -46.86015 | BF49: =SUM(BF38:BF48) -> -54.97474 | BG49: =SUM(BG38:BG48) -> -18.598012 | BH49: =SUM(BH38:BH48) -> -18.65238
A50: CONTRIBUTION BEFORE ADS | B50: =B37+B49 -> 3.70329 | C50: =C37+C49 -> 2.0803188 | D50: =D37+D49 -> 13.755829 | E50: =E37+E49 -> -3.419322 | F50: =F37+F49 -> -1.79168 | H50: =H37+H49 -> -15.23547 | I50: =I37+I49 -> -23.955647 | J50: =J37+J49 -> -17.964537 | K50: =K37+K49 -> -9.0517825 | L50: =L37+L49 -> -6.92695 | N50: =N37+N49 -> 3.70329 | O50: =O37+O49 -> 2.0803188 | P50: =P37+P49 -> 13.755829 | Q50: =Q37+Q49 -> -3.419322 | R50: =R37+R49 -> -1.79168 | T50: =T37+T49 -> 32.885555 | U50: =U37+U49 -> 26.347738 | V50: =V37+V49 -> 43.351693 | W50: =W37+W49 -> 1.4220093 | X50: =X37+X49 -> 6.9772248 | Z50: =Z37+Z49 -> 3.70329 | AA50: =AA37+AA49 -> 2.0803188 | AB50: =AB37+AB49 -> 13.755829 | AC50: =AC37+AC49 -> -3.419322 | AD50: =AD37+AD49 -> -1.79168 | AF50: =AF37+AF49 -> -2.505603 | AG50: =AG37+AG49 -> -0.42234363 | AH50: =AH37+AH49 -> 10.611916 | AI50: =AI37+AI49 -> -4.025697 | AJ50: =AJ37+AJ49 -> -2.398055 | AL50: =AL37+AL49 -> 3.70329 | AM50: =AM37+AM49 -> -0.082681175 | AN50: =AN37+AN49 -> 11.268829 | AO50: =AO37+AO49 -> -5.067322 | AP50: =AP37+AP49 -> -3.43968 | AR50: =AR37+AR49 -> 3.70329 | AS50: =AS37+AS49 -> 2.0803188 | AT50: =AT37+AT49 -> 13.755829 | AU50: =AU37+AU49 -> -3.419322 | AV50: =AV37+AV49 -> -1.79168 | AX50: =AX37+AX49 -> 3.70329 | AY50: =AY37+AY49 -> 2.0803188 | AZ50: =AZ37+AZ49 -> 13.755829 | BA50: =BA37+BA49 -> -3.419322 | BB50: =BB37+BB49 -> -1.79168 | BD50: =BD37+BD49 -> 0.053995 | BE50: =BE37+BE49 -> -1.8691498 | BF50: =BF37+BF49 -> 9.6064602 | BG50: =BG37+BG49 -> -3.612832 | BH50: =BH37+BH49 -> -2.00218
A51: Contribution margin (% of net revenue) | B51: =IFERROR(B50/B37,0) -> 0.077979596 | C51: =IFERROR(C50/C37,0) -> 0.043804947 | D51: =IFERROR(D50/D37,0) -> 0.20445461 | E51: =IFERROR(E50/E37,0) -> -0.22587539 | F51: =IFERROR(F50/F37,0) -> -0.10652018 | H51: =IFERROR(H50/H37,0) -> -0.36808832 | I51: =IFERROR(I50/I37,0) -> -0.57876744 | J51: =IFERROR(J50/J37,0) -> -0.30951461 | K51: =IFERROR(K50/K37,0) -> -0.72491565 | L51: =IFERROR(L50/L37,0) -> -0.47153545 | N51: =IFERROR(N50/N37,0) -> 0.077979596 | O51: =IFERROR(O50/O37,0) -> 0.043804947 | P51: =IFERROR(P50/P37,0) -> 0.20445461 | Q51: =IFERROR(Q50/Q37,0) -> -0.22587539 | R51: =IFERROR(R50/R37,0) -> -0.10652018 | T51: =IFERROR(T50/T37,0) -> 0.56513809 | U51: =IFERROR(U50/U37,0) -> 0.45278573 | V51: =IFERROR(V50/V37,0) -> 0.53477463 | W51: =IFERROR(W50/W37,0) -> 0.090791887 | X51: =IFERROR(X50/X37,0) -> 0.32615209 | Z51: =IFERROR(Z50/Z37,0) -> 0.077979596 | AA51: =IFERROR(AA50/AA37,0) -> 0.043804947 | AB51: =IFERROR(AB50/AB37,0) -> 0.20445461 | AC51: =IFERROR(AC50/AC37,0) -> -0.22587539 | AD51: =IFERROR(AD50/AD37,0) -> -0.10652018 | AF51: =IFERROR(AF50/AF37,0) -> -0.052760089 | AG51: =IFERROR(AG50/AG37,0) -> -0.0088932235 | AH51: =IFERROR(AH50/AH37,0) -> 0.15772624 | AI51: =IFERROR(AI50/AI37,0) -> -0.26593163 | AJ51: =IFERROR(AJ50/AJ37,0) -> -0.14257079 | AL51: =IFERROR(AL50/AL37,0) -> 0.077979596 | AM51: =IFERROR(AM50/AM37,0) -> -0.0017410045 | AN51: =IFERROR(AN50/AN37,0) -> 0.16749002 | AO51: =IFERROR(AO50/AO37,0) -> -0.33473985 | AP51: =IFERROR(AP50/AP37,0) -> -0.20449819 | AR51: =IFERROR(AR50/AR37,0) -> 0.077979596 | AS51: =IFERROR(AS50/AS37,0) -> 0.043804947 | AT51: =IFERROR(AT50/AT37,0) -> 0.20445461 | AU51: =IFERROR(AU50/AU37,0) -> -0.22587539 | AV51: =IFERROR(AV50/AV37,0) -> -0.10652018 | AX51: =IFERROR(AX50/AX37,0) -> 0.077979596 | AY51: =IFERROR(AY50/AY37,0) -> 0.043804947 | AZ51: =IFERROR(AZ50/AZ37,0) -> 0.20445461 | BA51: =IFERROR(BA50/BA37,0) -> -0.22587539 | BB51: =IFERROR(BB50/BB37,0) -> -0.10652018 | BD51: =IFERROR(BD50/BD37,0) -> 0.0012001289 | BE51: =IFERROR(BE50/BE37,0) -> -0.041544972 | BF51: =IFERROR(BF50/BF37,0) -> 0.1487501 | BG51: =IFERROR(BG50/BG37,0) -> -0.24109367 | BH51: =IFERROR(BH50/BH37,0) -> -0.12024961
A52: Paid CPA (first orders only) | B52: =-Inputs!$G$111*$B$7 -> -60 | C52: =-Inputs!$G$112*$B$7 -> -45 | D52: =-Inputs!$G$112*$B$7 -> -45 | E52: 0 | F52: 0 | H52: =-Inputs!$D$111*$H$7 -> -90 | I52: =-Inputs!$D$112*$H$7 -> -65 | J52: =-Inputs!$D$112*$H$7 -> -65 | K52: 0 | L52: 0 | N52: =-Inputs!$E$111*$N$7 -> -60 | O52: =-Inputs!$E$112*$N$7 -> -45 | P52: =-Inputs!$E$112*$N$7 -> -45 | Q52: 0 | R52: 0 | T52: =-Inputs!$F$111*$T$7 -> -40 | U52: =-Inputs!$F$112*$T$7 -> -32 | V52: =-Inputs!$F$112*$T$7 -> -32 | W52: 0 | X52: 0 | Z52: =-Inputs!$E$111*$Z$7 -> -78 | AA52: =-Inputs!$E$112*$Z$7 -> -58.5 | AB52: =-Inputs!$E$112*$Z$7 -> -58.5 | AC52: 0 | AD52: 0 | AF52: =-Inputs!$E$111*$AF$7 -> -60 | AG52: =-Inputs!$E$112*$AF$7 -> -45 | AH52: =-Inputs!$E$112*$AF$7 -> -45 | AI52: 0 | AJ52: 0 | AL52: =-Inputs!$E$111*$AL$7 -> -60 | AM52: =-Inputs!$E$112*$AL$7 -> -45 | AN52: =-Inputs!$E$112*$AL$7 -> -45 | AO52: 0 | AP52: 0 | AR52: =-Inputs!$E$111*$AR$7 -> -60 | AS52: =-Inputs!$E$112*$AR$7 -> -45 | AT52: =-Inputs!$E$112*$AR$7 -> -45 | AU52: 0 | AV52: 0 | AX52: =-Inputs!$E$111*$AX$7 -> -60 | AY52: =-Inputs!$E$112*$AX$7 -> -45 | AZ52: =-Inputs!$E$112*$AX$7 -> -45 | BA52: 0 | BB52: 0 | BD52: =-Inputs!$E$111*$BD$7 -> -60 | BE52: =-Inputs!$E$112*$BD$7 -> -45 | BF52: =-Inputs!$E$112*$BD$7 -> -45 | BG52: 0 | BH52: 0
A53: CONTRIBUTION AFTER CPA | B53: =B50+B52 -> -56.29671 | C53: =C50+C52 -> -42.919681 | D53: =D50+D52 -> -31.244171 | E53: =E50+E52 -> -3.419322 | F53: =F50+F52 -> -1.79168 | H53: =H50+H52 -> -105.23547 | I53: =I50+I52 -> -88.955647 | J53: =J50+J52 -> -82.964537 | K53: =K50+K52 -> -9.0517825 | L53: =L50+L52 -> -6.92695 | N53: =N50+N52 -> -56.29671 | O53: =O50+O52 -> -42.919681 | P53: =P50+P52 -> -31.244171 | Q53: =Q50+Q52 -> -3.419322 | R53: =R50+R52 -> -1.79168 | T53: =T50+T52 -> -7.114445 | U53: =U50+U52 -> -5.6522623 | V53: =V50+V52 -> 11.351693 | W53: =W50+W52 -> 1.4220093 | X53: =X50+X52 -> 6.9772248 | Z53: =Z50+Z52 -> -74.29671 | AA53: =AA50+AA52 -> -56.419681 | AB53: =AB50+AB52 -> -44.744171 | AC53: =AC50+AC52 -> -3.419322 | AD53: =AD50+AD52 -> -1.79168 | AF53: =AF50+AF52 -> -62.505603 | AG53: =AG50+AG52 -> -45.422344 | AH53: =AH50+AH52 -> -34.388084 | AI53: =AI50+AI52 -> -4.025697 | AJ53: =AJ50+AJ52 -> -2.398055 | AL53: =AL50+AL52 -> -56.29671 | AM53: =AM50+AM52 -> -45.082681 | AN53: =AN50+AN52 -> -33.731171 | AO53: =AO50+AO52 -> -5.067322 | AP53: =AP50+AP52 -> -3.43968 | AR53: =AR50+AR52 -> -56.29671 | AS53: =AS50+AS52 -> -42.919681 | AT53: =AT50+AT52 -> -31.244171 | AU53: =AU50+AU52 -> -3.419322 | AV53: =AV50+AV52 -> -1.79168 | AX53: =AX50+AX52 -> -56.29671 | AY53: =AY50+AY52 -> -42.919681 | AZ53: =AZ50+AZ52 -> -31.244171 | BA53: =BA50+BA52 -> -3.419322 | BB53: =BB50+BB52 -> -1.79168 | BD53: =BD50+BD52 -> -59.946005 | BE53: =BE50+BE52 -> -46.86915 | BF53: =BF50+BF52 -> -35.39354 | BG53: =BG50+BG52 -> -3.612832 | BH53: =BH50+BH52 -> -2.00218
A54: Break-even CPA (= contribution before ads) | B54: =B50 -> 3.70329 | C54: =C50 -> 2.0803188 | D54: =D50 -> 13.755829 | E54: n/a | F54: n/a | H54: =H50 -> -15.23547 | I54: =I50 -> -23.955647 | J54: =J50 -> -17.964537 | K54: n/a | L54: n/a | N54: =N50 -> 3.70329 | O54: =O50 -> 2.0803188 | P54: =P50 -> 13.755829 | Q54: n/a | R54: n/a | T54: =T50 -> 32.885555 | U54: =U50 -> 26.347738 | V54: =V50 -> 43.351693 | W54: n/a | X54: n/a | Z54: =Z50 -> 3.70329 | AA54: =AA50 -> 2.0803188 | AB54: =AB50 -> 13.755829 | AC54: n/a | AD54: n/a | AF54: =AF50 -> -2.505603 | AG54: =AG50 -> -0.42234363 | AH54: =AH50 -> 10.611916 | AI54: n/a | AJ54: n/a | AL54: =AL50 -> 3.70329 | AM54: =AM50 -> -0.082681175 | AN54: =AN50 -> 11.268829 | AO54: n/a | AP54: n/a | AR54: =AR50 -> 3.70329 | AS54: =AS50 -> 2.0803188 | AT54: =AT50 -> 13.755829 | AU54: n/a | AV54: n/a | AX54: =AX50 -> 3.70329 | AY54: =AY50 -> 2.0803188 | AZ54: =AZ50 -> 13.755829 | BA54: n/a | BB54: n/a | BD54: =BD50 -> 0.053995 | BE54: =BE50 -> -1.8691498 | BF54: =BF50 -> 9.6064602 | BG54: n/a | BH54: n/a
A56: Cohort first-order mix (per new customer; value in first column of each group)
A57: First-order contribution before ads (mix) | B57: =IF(Inputs!$D$4=1,B50,(1-Inputs!$G$132)*C50+Inputs!$G$132*D50) -> 4.9991963 | H57: =IF(Inputs!$D$4=1,H50,(1-Inputs!$D$132)*I50+Inputs!$D$132*J50) -> -23.056981 | N57: =IF(Inputs!$D$4=1,N50,(1-Inputs!$E$132)*O50+Inputs!$E$132*P50) -> 4.9991963 | T57: =IF(Inputs!$D$4=1,T50,(1-Inputs!$F$132)*U50+Inputs!$F$132*V50) -> 32.299122 | Z57: =IF(Inputs!$D$4=1,Z50,(1-Inputs!$E$132)*AA50+Inputs!$E$132*AB50) -> 4.9991963 | AF57: =IF(Inputs!$D$4=1,AF50,(1-Inputs!$E$132)*AG50+Inputs!$E$132*AH50) -> 2.3362214 | AL57: =IF(Inputs!$D$4=1,AL50,(1-Inputs!$E$132)*AM50+Inputs!$E$132*AN50) -> 2.7551963 | AR57: =IF(Inputs!$D$4=1,AR50,(1-Inputs!$E$132)*AS50+Inputs!$E$132*AT50) -> 4.9991963 | AX57: =IF(Inputs!$D$4=1,AX50,(1-Inputs!$E$132)*AY50+Inputs!$E$132*AZ50) -> 4.9991963 | BD57: =IF(Inputs!$D$4=1,BD50,(1-Inputs!$E$132)*BE50+Inputs!$E$132*BF50) -> 0.99975265
A58: First-order net revenue (mix) | B58: =IF(Inputs!$D$4=1,B37,(1-Inputs!$G$132)*C37+Inputs!$G$132*D37) -> 52.438025 | H58: =IF(Inputs!$D$4=1,H37,(1-Inputs!$D$132)*I37+Inputs!$D$132*J37) -> 43.88833 | N58: =IF(Inputs!$D$4=1,N37,(1-Inputs!$E$132)*O37+Inputs!$E$132*P37) -> 52.438025 | T58: =IF(Inputs!$D$4=1,T37,(1-Inputs!$F$132)*U37+Inputs!$F$132*V37) -> 66.196568 | Z58: =IF(Inputs!$D$4=1,Z37,(1-Inputs!$E$132)*AA37+Inputs!$E$132*AB37) -> 52.438025 | AF58: =IF(Inputs!$D$4=1,AF37,(1-Inputs!$E$132)*AG37+Inputs!$E$132*AH37) -> 52.438025 | AL58: =IF(Inputs!$D$4=1,AL37,(1-Inputs!$E$132)*AM37+Inputs!$E$132*AN37) -> 52.438025 | AR58: =IF(Inputs!$D$4=1,AR37,(1-Inputs!$E$132)*AS37+Inputs!$E$132*AT37) -> 52.438025 | AX58: =IF(Inputs!$D$4=1,AX37,(1-Inputs!$E$132)*AY37+Inputs!$E$132*AZ37) -> 52.438025 | BD58: =IF(Inputs!$D$4=1,BD37,(1-Inputs!$E$132)*BE37+Inputs!$E$132*BF37) -> 49.88855
A59: First-order gross revenue (mix) | B59: =IF(Inputs!$D$4=1,B35,(1-Inputs!$G$132)*C35+Inputs!$G$132*D35) -> 54.9875 | H59: =IF(Inputs!$D$4=1,H35,(1-Inputs!$D$132)*I35+Inputs!$D$132*J35) -> 47.5385 | N59: =IF(Inputs!$D$4=1,N35,(1-Inputs!$E$132)*O35+Inputs!$E$132*P35) -> 54.9875 | T59: =IF(Inputs!$D$4=1,T35,(1-Inputs!$F$132)*U35+Inputs!$F$132*V35) -> 68.0365 | Z59: =IF(Inputs!$D$4=1,Z35,(1-Inputs!$E$132)*AA35+Inputs!$E$132*AB35) -> 54.9875 | AF59: =IF(Inputs!$D$4=1,AF35,(1-Inputs!$E$132)*AG35+Inputs!$E$132*AH35) -> 54.9875 | AL59: =IF(Inputs!$D$4=1,AL35,(1-Inputs!$E$132)*AM35+Inputs!$E$132*AN35) -> 54.9875 | AR59: =IF(Inputs!$D$4=1,AR35,(1-Inputs!$E$132)*AS35+Inputs!$E$132*AT35) -> 54.9875 | AX59: =IF(Inputs!$D$4=1,AX35,(1-Inputs!$E$132)*AY35+Inputs!$E$132*AZ35) -> 54.9875 | BD59: =IF(Inputs!$D$4=1,BD35,(1-Inputs!$E$132)*BE35+Inputs!$E$132*BF35) -> 54.9875
A60: Paid CAC per new customer (by stage) | B60: =IF(Inputs!$D$4=1,Inputs!$G$111,Inputs!$G$112)*$B$7 -> 45 | H60: =IF(Inputs!$D$4=1,Inputs!$D$111,Inputs!$D$112)*$H$7 -> 65 | N60: =IF(Inputs!$D$4=1,Inputs!$E$111,Inputs!$E$112)*$N$7 -> 45 | T60: =IF(Inputs!$D$4=1,Inputs!$F$111,Inputs!$F$112)*$T$7 -> 32 | Z60: =IF(Inputs!$D$4=1,Inputs!$E$111,Inputs!$E$112)*$Z$7 -> 58.5 | AF60: =IF(Inputs!$D$4=1,Inputs!$E$111,Inputs!$E$112)*$AF$7 -> 45 | AL60: =IF(Inputs!$D$4=1,Inputs!$E$111,Inputs!$E$112)*$AL$7 -> 45 | AR60: =IF(Inputs!$D$4=1,Inputs!$E$111,Inputs!$E$112)*$AR$7 -> 45 | AX60: =IF(Inputs!$D$4=1,Inputs!$E$111,Inputs!$E$112)*$AX$7 -> 45 | BD60: =IF(Inputs!$D$4=1,Inputs!$E$111,Inputs!$E$112)*$BD$7 -> 45
A61: FIRST-ORDER CONTRIBUTION AFTER CAC | B61: =B57-B60 -> -40.000804 | H61: =H57-H60 -> -88.056981 | N61: =N57-N60 -> -40.000804 | T61: =T57-T60 -> 0.29912199 | Z61: =Z57-Z60 -> -53.500804 | AF61: =AF57-AF60 -> -42.663779 | AL61: =AL57-AL60 -> -42.244804 | AR61: =AR57-AR60 -> -40.000804 | AX61: =AX57-AX60 -> -40.000804 | BD61: =BD57-BD60 -> -44.000247
A62: First-order contribution margin before ads | B62: =IFERROR(B57/B58,0) -> 0.095335328 | H62: =IFERROR(H57/H58,0) -> -0.52535562 | N62: =IFERROR(N57/N58,0) -> 0.095335328 | T62: =IFERROR(T57/T58,0) -> 0.48792744 | Z62: =IFERROR(Z57/Z58,0) -> 0.095335328 | AF62: =IFERROR(AF57/AF58,0) -> 0.044552047 | AL62: =IFERROR(AL57/AL58,0) -> 0.052541955 | AR62: =IFERROR(AR57/AR58,0) -> 0.095335328 | AX62: =IFERROR(AX57/AX58,0) -> 0.095335328 | BD62: =IFERROR(BD57/BD58,0) -> 0.020039722
A63: First-order contribution - subscribers | B63: =B57 -> 4.9991963 | H63: =H57 -> -23.056981 | N63: =N57 -> 4.9991963 | T63: =T57 -> 32.299122 | Z63: =Z57 -> 4.9991963 | AF63: =AF57 -> 2.3362214 | AL63: =AL57 -> 2.7551963 | AR63: =AR57 -> 4.9991963 | AX63: =AX57 -> 4.9991963 | BD63: =BD57 -> 0.99975265
A64: Notes: (a) at test stage the supplier ships free, there is no 3PL and returns to China are written off, so refunds keep the product cost. Litter-mat cross-sell is applied only at private-label stage (conservative). Cohort first-order mix = (b) and (c) weighted by cross-sell attach, or (a) when Inputs!D4 = 1. | B64: =B57 -> 4.9991963 | H64: =H57 -> -23.056981 | N64: =N57 -> 4.9991963 | T64: =T57 -> 32.299122 | Z64: =Z57 -> 4.9991963 | AF64: =AF57 -> 2.3362214 | AL64: =AL57 -> 2.7551963 | AR64: =AR57 -> 4.9991963 | AX64: =AX57 -> 4.9991963 | BD64: =BD57 -> 0.99975265

Sheet Cat_Cohort
A1: Cat_Cohort: 24-month cohort of 100 acquired customers (BASE CASE)
A2: LTV = contribution profit (never revenue). First-order profitability is reported separately so subscription renewals cannot hide an unprofitable first order. Segments: one-time only, occasional repeat buyers (one-time filter packs), filter subscribers (90-day).
A4: ="SELECTED SCENARIO COHORT: "&Inputs!$E$3&" | stage: "&Inputs!$E$4 -> SELECTED SCENARIO COHORT: Base | stage: Private label (OEM + 3PL, CPA months 4-12)
A6: Customers acquired (N) | B6: =Inputs!$G$9 -> 100
A7: Subscription attach (after any shock) | B7: =MIN(1,Inputs!$G$133*Cat_UnitEcon!$B$10) -> 0.2
A8: Non-subscriber 12-month repeat rate | B8: =Inputs!$G$139 -> 0.2
A9: Segment: subscribers | B9: =$B$6*$B$7 -> 20
A10: Segment: occasional repeat buyers | B10: =$B$6*(1-$B$7)*$B$8 -> 16
A11: Segment: one-time only | B11: =$B$6-$B$9-$B$10 -> 64
A12: First-order contribution before ads, per customer (mix) | B12: =Cat_UnitEcon!$B$57 -> 4.9991963
A13: Paid CAC per new customer | B13: =Cat_UnitEcon!$B$60 -> 45
A14: Contribution per subscription renewal order | B14: =Cat_UnitEcon!$E$50 -> -3.419322
A15: Contribution per occasional repeat order | B15: =Cat_UnitEcon!$F$50 -> -1.79168
A16: Churn before first renewal (incl. involuntary) | B16: =1-(1-MIN(1,Inputs!$G$135*Cat_UnitEcon!$B$11))*(1-MIN(1,Inputs!$G$137*Cat_UnitEcon!$B$11))^$B$18 -> 0.26564001
A17: Churn per later cycle (incl. involuntary) | B17: =1-(1-MIN(1,Inputs!$G$136*Cat_UnitEcon!$B$11))*(1-MIN(1,Inputs!$G$137*Cat_UnitEcon!$B$11))^$B$18 -> 0.16772534
A18: Renewal cadence (months) | B18: =Inputs!$G$134 -> 3
A19: Occasional: month of first repeat | B19: =Inputs!$G$140 -> 4
A20: Occasional: months between orders | B20: =Inputs!$G$141 -> 4
A21: Occasional: probability of each further order | B21: =Inputs!$G$142 -> 0.6
A22: First-order contribution - subscriber | B22: =Cat_UnitEcon!$B$63 -> 4.9991963
A23: First-order contribution - non-subscriber | B23: =Cat_UnitEcon!$B$64 -> 4.9991963
A24: First-order gross revenue (mix) - reference | B24: =Cat_UnitEcon!$B$59 -> 54.9875
A25: Renewal order gross revenue - reference | B25: =Cat_UnitEcon!$E$35 -> 15.291
A26: Occasional order gross revenue - reference | B26: =Cat_UnitEcon!$F$35 -> 16.99
A28: Month | B28: Total 1-24 | C28: 1 | D28: 2 | E28: 3 | F28: 4 | G28: 5 | H28: 6 | I28: 7 | J28: 8 | K28: 9 | L28: 10 | M28: 11 | N28: 12 | O28: 13 | P28: 14 | Q28: 15 | R28: 16 | S28: 17 | T28: 18 | U28: 19 | V28: 20 | W28: 21 | X28: 22 | Y28: 23 | Z28: 24
A29: Subscription renewal orders (paying subscribers) | B29: =SUM(C29:Z29) -> 63.345136 | C29: =IF(AND(C$28>1,MOD(C$28-1,$B$18)=0),$B$9*(1-$B$16)*(1-$B$17)^((C$28-1)/$B$18-1),0) -> 0 | D29: =IF(AND(D$28>1,MOD(D$28-1,$B$18)=0),$B$9*(1-$B$16)*(1-$B$17)^((D$28-1)/$B$18-1),0) -> 0 | E29: =IF(AND(E$28>1,MOD(E$28-1,$B$18)=0),$B$9*(1-$B$16)*(1-$B$17)^((E$28-1)/$B$18-1),0) -> 0 | F29: =IF(AND(F$28>1,MOD(F$28-1,$B$18)=0),$B$9*(1-$B$16)*(1-$B$17)^((F$28-1)/$B$18-1),0) -> 14.6872 | G29: =IF(AND(G$28>1,MOD(G$28-1,$B$18)=0),$B$9*(1-$B$16)*(1-$B$17)^((G$28-1)/$B$18-1),0) -> 0 | H29: =IF(AND(H$28>1,MOD(H$28-1,$B$18)=0),$B$9*(1-$B$16)*(1-$B$17)^((H$28-1)/$B$18-1),0) -> 0 | I29: =IF(AND(I$28>1,MOD(I$28-1,$B$18)=0),$B$9*(1-$B$16)*(1-$B$17)^((I$28-1)/$B$18-1),0) -> 12.223784 | J29: =IF(AND(J$28>1,MOD(J$28-1,$B$18)=0),$B$9*(1-$B$16)*(1-$B$17)^((J$28-1)/$B$18-1),0) -> 0 | ... Z29: =IF(AND(Z$28>1,MOD(Z$28-1,$B$18)=0),$B$9*(1-$B$16)*(1-$B$17)^((Z$28-1)/$B$18-1),0) -> 0
A30: Occasional repeat orders | B30: =SUM(C30:Z30) -> 38.13376 | C30: =IF(AND(C$28>=$B$19,MOD(C$28-$B$19,$B$20)=0),$B$10*$B$21^((C$28-$B$19)/$B$20),0) -> 0 | D30: =IF(AND(D$28>=$B$19,MOD(D$28-$B$19,$B$20)=0),$B$10*$B$21^((D$28-$B$19)/$B$20),0) -> 0 | E30: =IF(AND(E$28>=$B$19,MOD(E$28-$B$19,$B$20)=0),$B$10*$B$21^((E$28-$B$19)/$B$20),0) -> 0 | F30: =IF(AND(F$28>=$B$19,MOD(F$28-$B$19,$B$20)=0),$B$10*$B$21^((F$28-$B$19)/$B$20),0) -> 16 | G30: =IF(AND(G$28>=$B$19,MOD(G$28-$B$19,$B$20)=0),$B$10*$B$21^((G$28-$B$19)/$B$20),0) -> 0 | H30: =IF(AND(H$28>=$B$19,MOD(H$28-$B$19,$B$20)=0),$B$10*$B$21^((H$28-$B$19)/$B$20),0) -> 0 | I30: =IF(AND(I$28>=$B$19,MOD(I$28-$B$19,$B$20)=0),$B$10*$B$21^((I$28-$B$19)/$B$20),0) -> 0 | J30: =IF(AND(J$28>=$B$19,MOD(J$28-$B$19,$B$20)=0),$B$10*$B$21^((J$28-$B$19)/$B$20),0) -> 9.6 | ... Z30: =IF(AND(Z$28>=$B$19,MOD(Z$28-$B$19,$B$20)=0),$B$10*$B$21^((Z$28-$B$19)/$B$20),0) -> 1.24416
A31: Contribution - one-time-only segment | B31: =SUM(C31:Z31) -> 319.94856 | C31: =IF(C$28=1,$B$11*$B$23,0) -> 319.94856 | D31: =IF(D$28=1,$B$11*$B$23,0) -> 0 | E31: =IF(E$28=1,$B$11*$B$23,0) -> 0 | F31: =IF(F$28=1,$B$11*$B$23,0) -> 0 | G31: =IF(G$28=1,$B$11*$B$23,0) -> 0 | H31: =IF(H$28=1,$B$11*$B$23,0) -> 0 | I31: =IF(I$28=1,$B$11*$B$23,0) -> 0 | J31: =IF(J$28=1,$B$11*$B$23,0) -> 0 | ... Z31: =IF(Z$28=1,$B$11*$B$23,0) -> 0
A32: Contribution - occasional repeat segment | B32: =SUM(C32:Z32) -> 11.663646 | C32: =IF(C$28=1,$B$10*$B$23,0)+C30*$B$15 -> 79.987141 | D32: =IF(D$28=1,$B$10*$B$23,0)+D30*$B$15 -> 0 | E32: =IF(E$28=1,$B$10*$B$23,0)+E30*$B$15 -> 0 | F32: =IF(F$28=1,$B$10*$B$23,0)+F30*$B$15 -> -28.66688 | G32: =IF(G$28=1,$B$10*$B$23,0)+G30*$B$15 -> 0 | H32: =IF(H$28=1,$B$10*$B$23,0)+H30*$B$15 -> 0 | I32: =IF(I$28=1,$B$10*$B$23,0)+I30*$B$15 -> 0 | J32: =IF(J$28=1,$B$10*$B$23,0)+J30*$B$15 -> -17.200128 | ... Z32: =IF(Z$28=1,$B$10*$B$23,0)+Z30*$B$15 -> -2.2291366
A33: Contribution - subscriber segment | B33: =SUM(C33:Z33) -> -116.61349 | C33: =IF(C$28=1,$B$9*$B$22,0)+C29*$B$14 -> 99.983927 | D33: =IF(D$28=1,$B$9*$B$22,0)+D29*$B$14 -> 0 | E33: =IF(E$28=1,$B$9*$B$22,0)+E29*$B$14 -> 0 | F33: =IF(F$28=1,$B$9*$B$22,0)+F29*$B$14 -> -50.220266 | G33: =IF(G$28=1,$B$9*$B$22,0)+G29*$B$14 -> 0 | H33: =IF(H$28=1,$B$9*$B$22,0)+H29*$B$14 -> 0 | I33: =IF(I$28=1,$B$9*$B$22,0)+I29*$B$14 -> -41.797054 | J33: =IF(J$28=1,$B$9*$B$22,0)+J29*$B$14 -> 0 | ... Z33: =IF(Z$28=1,$B$9*$B$22,0)+Z29*$B$14 -> 0
A34: Total contribution before CAC | B34: =SUM(C34:Z34) -> 214.99872 | C34: =SUM(C31:C33) -> 499.91963 | D34: =SUM(D31:D33) -> 0 | E34: =SUM(E31:E33) -> 0 | F34: =SUM(F31:F33) -> -78.887146 | G34: =SUM(G31:G33) -> 0 | H34: =SUM(H31:H33) -> 0 | I34: =SUM(I31:I33) -> -41.797054 | J34: =SUM(J31:J33) -> -17.200128 | ... Z34: =SUM(Z31:Z33) -> -2.2291366
A35: CAC (paid, month 1) | B35: =SUM(C35:Z35) -> -4500 | C35: =IF(C$28=1,-$B$6*$B$13,0) -> -4500 | D35: =IF(D$28=1,-$B$6*$B$13,0) -> 0 | E35: =IF(E$28=1,-$B$6*$B$13,0) -> 0 | F35: =IF(F$28=1,-$B$6*$B$13,0) -> 0 | G35: =IF(G$28=1,-$B$6*$B$13,0) -> 0 | H35: =IF(H$28=1,-$B$6*$B$13,0) -> 0 | I35: =IF(I$28=1,-$B$6*$B$13,0) -> 0 | J35: =IF(J$28=1,-$B$6*$B$13,0) -> 0 | ... Z35: =IF(Z$28=1,-$B$6*$B$13,0) -> 0
A36: Net contribution after CAC | B36: =SUM(C36:Z36) -> -4285.0013 | C36: =C34+C35 -> -4000.0804 | D36: =D34+D35 -> 0 | E36: =E34+E35 -> 0 | F36: =F34+F35 -> -78.887146 | G36: =G34+G35 -> 0 | H36: =H34+H35 -> 0 | I36: =I34+I35 -> -41.797054 | J36: =J34+J35 -> -17.200128 | ... Z36: =Z34+Z35 -> -2.2291366
A37: CUMULATIVE contribution after CAC | C37: =C36 -> -4000.0804 | D37: =C37+D36 -> -4000.0804 | E37: =D37+E36 -> -4000.0804 | F37: =E37+F36 -> -4078.9675 | G37: =F37+G36 -> -4078.9675 | H37: =G37+H36 -> -4078.9675 | I37: =H37+I36 -> -4120.7646 | J37: =I37+J36 -> -4137.9647 | K37: =J37+K36 -> -4137.9647 | ... Z37: =Y37+Z36 -> -4285.0013
A38: Cumulative contribution before CAC, per customer | C38: =SUM($C34:C34)/$B$6 -> 4.9991963 | D38: =SUM($C34:D34)/$B$6 -> 4.9991963 | E38: =SUM($C34:E34)/$B$6 -> 4.9991963 | F38: =SUM($C34:F34)/$B$6 -> 4.2103249 | G38: =SUM($C34:G34)/$B$6 -> 4.2103249 | H38: =SUM($C34:H34)/$B$6 -> 4.2103249 | I38: =SUM($C34:I34)/$B$6 -> 3.7923543 | J38: =SUM($C34:J34)/$B$6 -> 3.620353 | ... Z38: =SUM($C34:Z34)/$B$6 -> 2.1499872
A39: Gross revenue (reference only - NOT used for LTV) | B39: =SUM(C39:Z39) -> 7115.2531 | C39: =IF(C$28=1,$B$6*$B$24,0)+C29*$B$25+C30*$B$26 -> 5498.75 | D39: =IF(D$28=1,$B$6*$B$24,0)+D29*$B$25+D30*$B$26 -> 0 | E39: =IF(E$28=1,$B$6*$B$24,0)+E29*$B$25+E30*$B$26 -> 0 | F39: =IF(F$28=1,$B$6*$B$24,0)+F29*$B$25+F30*$B$26 -> 496.42197 | G39: =IF(G$28=1,$B$6*$B$24,0)+G29*$B$25+G30*$B$26 -> 0 | H39: =IF(H$28=1,$B$6*$B$24,0)+H29*$B$25+H30*$B$26 -> 0 | I39: =IF(I$28=1,$B$6*$B$24,0)+I29*$B$25+I30*$B$26 -> 186.91388 | J39: =IF(J$28=1,$B$6*$B$24,0)+J29*$B$25+J30*$B$26 -> 163.104 | ... Z39: =IF(Z$28=1,$B$6*$B$24,0)+Z29*$B$25+Z30*$B$26 -> 21.138278
A40: Payback helper (month if cumulative >= 0, else 99) | C40: =IF(C37>=0,C$28,99) -> 99 | D40: =IF(D37>=0,D$28,99) -> 99 | E40: =IF(E37>=0,E$28,99) -> 99 | F40: =IF(F37>=0,F$28,99) -> 99 | G40: =IF(G37>=0,G$28,99) -> 99 | H40: =IF(H37>=0,H$28,99) -> 99 | I40: =IF(I37>=0,I$28,99) -> 99 | J40: =IF(J37>=0,J$28,99) -> 99 | ... Z40: =IF(Z37>=0,Z$28,99) -> 99
A42: FIRST-ORDER contribution before ads, per customer | B42: =$B$12 -> 4.9991963
A43: FIRST-ORDER contribution after CAC, per customer | B43: =$B$12-$B$13 -> -40.000804
A44: Is the first order profitable after CAC? | B44: =IF(B43>=0,"YES - first order covers CAC","NO - first order loses money after CAC") -> NO - first order loses money after CAC
A45: Payback month (numeric; 99 = none within 24 months) | B45: =MIN(C40:Z40) -> 99
A46: Payback (display) | B46: =IF(B45>24,"No payback within 24 months","Month "&B45) -> No payback within 24 months
A47: 12-month contribution LTV per customer (before CAC) | B47: =SUM(C34:N34)/$B$6 -> 3.169286
A48: 24-month contribution LTV per customer (before CAC) | B48: =SUM(C34:Z34)/$B$6 -> 2.1499872
A49: 12-month contribution LTV net of CAC | B49: =B47-$B$13 -> -41.830714
A50: 24-month contribution LTV net of CAC | B50: =B48-$B$13 -> -42.850013
A51: 12-month LTV:CAC (contribution basis) | B51: =IFERROR(B47/$B$13,0) -> 0.070428577
A52: 24-month LTV:CAC | B52: =IFERROR(B48/$B$13,0) -> 0.047777494
A53: 12-month LTV : blended CAC (info only) | B53: =IFERROR(B47/($B$13*Inputs!$G$121),0) -> 0.08285715
A54: Cohort contribution from subscription renewals, months 1-24 | B54: =B29*$B$14 -> -216.59742
A55: Renewal contribution per subscriber, 12 months | B55: =IFERROR(SUM(C29:N29)*$B$14/$B$9,0) -> -6.3401975
A56: Repeat contribution per occasional buyer, 12 months | B56: =IFERROR(SUM(C30:N30)*$B$15/$B$10,0) -> -3.5116928
A57: Orders per acquired customer, 12 months | B57: =($B$6+SUM(C29:N29)+SUM(C30:N30))/$B$6 -> 1.6844453
A58: Renewal contribution per subscriber, 24 months | B58: =IFERROR(SUM(C29:Z29)*$B$14/$B$9,0) -> -10.829871
A59: Repeat contribution per occasional buyer, 24 months | B59: =IFERROR(SUM(C30:Z30)*$B$15/$B$10,0) -> -4.2702184
A62: ENGINE BLOCKS BELOW (same formulas; feed Scenarios and Sensitivity; do not edit)
A64: Engine cohort: PESSIMISTIC (engine)
A66: Customers acquired (N) | B66: =Inputs!$D$9 -> 100
A67: Subscription attach (after any shock) | B67: =MIN(1,Inputs!$D$133*Cat_UnitEcon!$H$10) -> 0.1
A68: Non-subscriber 12-month repeat rate | B68: =Inputs!$D$139 -> 0.12
A69: Segment: subscribers | B69: =$B$66*$B$67 -> 10
A70: Segment: occasional repeat buyers | B70: =$B$66*(1-$B$67)*$B$68 -> 10.8
A71: Segment: one-time only | B71: =$B$66-$B$69-$B$70 -> 79.2
A72: First-order contribution before ads, per customer (mix) | B72: =Cat_UnitEcon!$H$57 -> -23.056981
A73: Paid CAC per new customer | B73: =Cat_UnitEcon!$H$60 -> 65
A74: Contribution per subscription renewal order | B74: =Cat_UnitEcon!$K$50 -> -9.0517825
A75: Contribution per occasional repeat order | B75: =Cat_UnitEcon!$L$50 -> -6.92695
A76: Churn before first renewal (incl. involuntary) | B76: =1-(1-MIN(1,Inputs!$D$135*Cat_UnitEcon!$H$11))*(1-MIN(1,Inputs!$D$137*Cat_UnitEcon!$H$11))^$B$78 -> 0.36930565
A77: Churn per later cycle (incl. involuntary) | B77: =1-(1-MIN(1,Inputs!$D$136*Cat_UnitEcon!$H$11))*(1-MIN(1,Inputs!$D$137*Cat_UnitEcon!$H$11))^$B$78 -> 0.26257276
A78: Renewal cadence (months) | B78: =Inputs!$D$134 -> 3
A79: Occasional: month of first repeat | B79: =Inputs!$D$140 -> 5
A80: Occasional: months between orders | B80: =Inputs!$D$141 -> 6
A81: Occasional: probability of each further order | B81: =Inputs!$D$142 -> 0.5
A82: First-order contribution - subscriber | B82: =Cat_UnitEcon!$H$63 -> -23.056981
A83: First-order contribution - non-subscriber | B83: =Cat_UnitEcon!$H$64 -> -23.056981
A84: First-order gross revenue (mix) - reference | B84: =Cat_UnitEcon!$H$59 -> 47.5385
A85: Renewal order gross revenue - reference | B85: =Cat_UnitEcon!$K$35 -> 12.7415
A86: Occasional order gross revenue - reference | B86: =Cat_UnitEcon!$L$35 -> 14.99
A88: Month | B88: Total 1-24 | C88: 1 | D88: 2 | E88: 3 | F88: 4 | G88: 5 | H88: 6 | I88: 7 | J88: 8 | K88: 9 | L88: 10 | M88: 11 | N88: 12 | O88: 13 | P88: 14 | Q88: 15 | R88: 16 | S88: 17 | T88: 18 | U88: 19 | V88: 20 | W88: 21 | X88: 22 | Y88: 23 | Z88: 24
A89: Subscription renewal orders (paying subscribers) | B89: =SUM(C89:Z89) -> 21.171377 | C89: =IF(AND(C$88>1,MOD(C$88-1,$B$78)=0),$B$69*(1-$B$76)*(1-$B$77)^((C$88-1)/$B$78-1),0) -> 0 | D89: =IF(AND(D$88>1,MOD(D$88-1,$B$78)=0),$B$69*(1-$B$76)*(1-$B$77)^((D$88-1)/$B$78-1),0) -> 0 | E89: =IF(AND(E$88>1,MOD(E$88-1,$B$78)=0),$B$69*(1-$B$76)*(1-$B$77)^((E$88-1)/$B$78-1),0) -> 0 | F89: =IF(AND(F$88>1,MOD(F$88-1,$B$78)=0),$B$69*(1-$B$76)*(1-$B$77)^((F$88-1)/$B$78-1),0) -> 6.3069435 | G89: =IF(AND(G$88>1,MOD(G$88-1,$B$78)=0),$B$69*(1-$B$76)*(1-$B$77)^((G$88-1)/$B$78-1),0) -> 0 | H89: =IF(AND(H$88>1,MOD(H$88-1,$B$78)=0),$B$69*(1-$B$76)*(1-$B$77)^((H$88-1)/$B$78-1),0) -> 0 | I89: =IF(AND(I$88>1,MOD(I$88-1,$B$78)=0),$B$69*(1-$B$76)*(1-$B$77)^((I$88-1)/$B$78-1),0) -> 4.6509119 | J89: =IF(AND(J$88>1,MOD(J$88-1,$B$78)=0),$B$69*(1-$B$76)*(1-$B$77)^((J$88-1)/$B$78-1),0) -> 0 | ... Z89: =IF(AND(Z$88>1,MOD(Z$88-1,$B$78)=0),$B$69*(1-$B$76)*(1-$B$77)^((Z$88-1)/$B$78-1),0) -> 0
A90: Occasional repeat orders | B90: =SUM(C90:Z90) -> 20.25 | C90: =IF(AND(C$88>=$B$79,MOD(C$88-$B$79,$B$80)=0),$B$70*$B$81^((C$88-$B$79)/$B$80),0) -> 0 | D90: =IF(AND(D$88>=$B$79,MOD(D$88-$B$79,$B$80)=0),$B$70*$B$81^((D$88-$B$79)/$B$80),0) -> 0 | E90: =IF(AND(E$88>=$B$79,MOD(E$88-$B$79,$B$80)=0),$B$70*$B$81^((E$88-$B$79)/$B$80),0) -> 0 | F90: =IF(AND(F$88>=$B$79,MOD(F$88-$B$79,$B$80)=0),$B$70*$B$81^((F$88-$B$79)/$B$80),0) -> 0 | G90: =IF(AND(G$88>=$B$79,MOD(G$88-$B$79,$B$80)=0),$B$70*$B$81^((G$88-$B$79)/$B$80),0) -> 10.8 | H90: =IF(AND(H$88>=$B$79,MOD(H$88-$B$79,$B$80)=0),$B$70*$B$81^((H$88-$B$79)/$B$80),0) -> 0 | I90: =IF(AND(I$88>=$B$79,MOD(I$88-$B$79,$B$80)=0),$B$70*$B$81^((I$88-$B$79)/$B$80),0) -> 0 | J90: =IF(AND(J$88>=$B$79,MOD(J$88-$B$79,$B$80)=0),$B$70*$B$81^((J$88-$B$79)/$B$80),0) -> 0 | ... Z90: =IF(AND(Z$88>=$B$79,MOD(Z$88-$B$79,$B$80)=0),$B$70*$B$81^((Z$88-$B$79)/$B$80),0) -> 0
A91: Contribution - one-time-only segment | B91: =SUM(C91:Z91) -> -1826.1129 | C91: =IF(C$88=1,$B$71*$B$83,0) -> -1826.1129 | D91: =IF(D$88=1,$B$71*$B$83,0) -> 0 | E91: =IF(E$88=1,$B$71*$B$83,0) -> 0 | F91: =IF(F$88=1,$B$71*$B$83,0) -> 0 | G91: =IF(G$88=1,$B$71*$B$83,0) -> 0 | H91: =IF(H$88=1,$B$71*$B$83,0) -> 0 | I91: =IF(I$88=1,$B$71*$B$83,0) -> 0 | J91: =IF(J$88=1,$B$71*$B$83,0) -> 0 | ... Z91: =IF(Z$88=1,$B$71*$B$83,0) -> 0
A92: Contribution - occasional repeat segment | B92: =SUM(C92:Z92) -> -389.28613 | C92: =IF(C$88=1,$B$70*$B$83,0)+C90*$B$75 -> -249.01539 | D92: =IF(D$88=1,$B$70*$B$83,0)+D90*$B$75 -> 0 | E92: =IF(E$88=1,$B$70*$B$83,0)+E90*$B$75 -> 0 | F92: =IF(F$88=1,$B$70*$B$83,0)+F90*$B$75 -> 0 | G92: =IF(G$88=1,$B$70*$B$83,0)+G90*$B$75 -> -74.81106 | H92: =IF(H$88=1,$B$70*$B$83,0)+H90*$B$75 -> 0 | I92: =IF(I$88=1,$B$70*$B$83,0)+I90*$B$75 -> 0 | J92: =IF(J$88=1,$B$70*$B$83,0)+J90*$B$75 -> 0 | ... Z92: =IF(Z$88=1,$B$70*$B$83,0)+Z90*$B$75 -> 0
A93: Contribution - subscriber segment | B93: =SUM(C93:Z93) -> -422.20851 | C93: =IF(C$88=1,$B$69*$B$82,0)+C89*$B$74 -> -230.56981 | D93: =IF(D$88=1,$B$69*$B$82,0)+D89*$B$74 -> 0 | E93: =IF(E$88=1,$B$69*$B$82,0)+E89*$B$74 -> 0 | F93: =IF(F$88=1,$B$69*$B$82,0)+F89*$B$74 -> -57.089081 | G93: =IF(G$88=1,$B$69*$B$82,0)+G89*$B$74 -> 0 | H93: =IF(H$88=1,$B$69*$B$82,0)+H89*$B$74 -> 0 | I93: =IF(I$88=1,$B$69*$B$82,0)+I89*$B$74 -> -42.099043 | J93: =IF(J$88=1,$B$69*$B$82,0)+J89*$B$74 -> 0 | ... Z93: =IF(Z$88=1,$B$69*$B$82,0)+Z89*$B$74 -> 0
A94: Total contribution before CAC | B94: =SUM(C94:Z94) -> -2637.6075 | C94: =SUM(C91:C93) -> -2305.6981 | D94: =SUM(D91:D93) -> 0 | E94: =SUM(E91:E93) -> 0 | F94: =SUM(F91:F93) -> -57.089081 | G94: =SUM(G91:G93) -> -74.81106 | H94: =SUM(H91:H93) -> 0 | I94: =SUM(I91:I93) -> -42.099043 | J94: =SUM(J91:J93) -> 0 | ... Z94: =SUM(Z91:Z93) -> 0
A95: CAC (paid, month 1) | B95: =SUM(C95:Z95) -> -6500 | C95: =IF(C$88=1,-$B$66*$B$73,0) -> -6500 | D95: =IF(D$88=1,-$B$66*$B$73,0) -> 0 | E95: =IF(E$88=1,-$B$66*$B$73,0) -> 0 | F95: =IF(F$88=1,-$B$66*$B$73,0) -> 0 | G95: =IF(G$88=1,-$B$66*$B$73,0) -> 0 | H95: =IF(H$88=1,-$B$66*$B$73,0) -> 0 | I95: =IF(I$88=1,-$B$66*$B$73,0) -> 0 | J95: =IF(J$88=1,-$B$66*$B$73,0) -> 0 | ... Z95: =IF(Z$88=1,-$B$66*$B$73,0) -> 0
A96: Net contribution after CAC | B96: =SUM(C96:Z96) -> -9137.6075 | C96: =C94+C95 -> -8805.6981 | D96: =D94+D95 -> 0 | E96: =E94+E95 -> 0 | F96: =F94+F95 -> -57.089081 | G96: =G94+G95 -> -74.81106 | H96: =H94+H95 -> 0 | I96: =I94+I95 -> -42.099043 | J96: =J94+J95 -> 0 | ... Z96: =Z94+Z95 -> 0
A97: CUMULATIVE contribution after CAC | C97: =C96 -> -8805.6981 | D97: =C97+D96 -> -8805.6981 | E97: =D97+E96 -> -8805.6981 | F97: =E97+F96 -> -8862.7872 | G97: =F97+G96 -> -8937.5982 | H97: =G97+H96 -> -8937.5982 | I97: =H97+I96 -> -8979.6973 | J97: =I97+J96 -> -8979.6973 | K97: =J97+K96 -> -8979.6973 | ... Z97: =Y97+Z96 -> -9137.6075
A98: Cumulative contribution before CAC, per customer | C98: =SUM($C94:C94)/$B$66 -> -23.056981 | D98: =SUM($C94:D94)/$B$66 -> -23.056981 | E98: =SUM($C94:E94)/$B$66 -> -23.056981 | F98: =SUM($C94:F94)/$B$66 -> -23.627872 | G98: =SUM($C94:G94)/$B$66 -> -24.375982 | H98: =SUM($C94:H94)/$B$66 -> -24.375982 | I98: =SUM($C94:I94)/$B$66 -> -24.796973 | J98: =SUM($C94:J94)/$B$66 -> -24.796973 | ... Z98: =SUM($C94:Z94)/$B$66 -> -26.376075
A99: Gross revenue (reference only - NOT used for LTV) | B99: =SUM(C99:Z99) -> 5327.1526 | C99: =IF(C$88=1,$B$66*$B$84,0)+C89*$B$85+C90*$B$86 -> 4753.85 | D99: =IF(D$88=1,$B$66*$B$84,0)+D89*$B$85+D90*$B$86 -> 0 | E99: =IF(E$88=1,$B$66*$B$84,0)+E89*$B$85+E90*$B$86 -> 0 | F99: =IF(F$88=1,$B$66*$B$84,0)+F89*$B$85+F90*$B$86 -> 80.359921 | G99: =IF(G$88=1,$B$66*$B$84,0)+G89*$B$85+G90*$B$86 -> 161.892 | H99: =IF(H$88=1,$B$66*$B$84,0)+H89*$B$85+H90*$B$86 -> 0 | I99: =IF(I$88=1,$B$66*$B$84,0)+I89*$B$85+I90*$B$86 -> 59.259594 | J99: =IF(J$88=1,$B$66*$B$84,0)+J89*$B$85+J90*$B$86 -> 0 | ... Z99: =IF(Z$88=1,$B$66*$B$84,0)+Z89*$B$85+Z90*$B$86 -> 0
A100: Payback helper (month if cumulative >= 0, else 99) | C100: =IF(C97>=0,C$88,99) -> 99 | D100: =IF(D97>=0,D$88,99) -> 99 | E100: =IF(E97>=0,E$88,99) -> 99 | F100: =IF(F97>=0,F$88,99) -> 99 | G100: =IF(G97>=0,G$88,99) -> 99 | H100: =IF(H97>=0,H$88,99) -> 99 | I100: =IF(I97>=0,I$88,99) -> 99 | J100: =IF(J97>=0,J$88,99) -> 99 | ... Z100: =IF(Z97>=0,Z$88,99) -> 99
A102: FIRST-ORDER contribution before ads, per customer | B102: =$B$72 -> -23.056981
A103: FIRST-ORDER contribution after CAC, per customer | B103: =$B$72-$B$73 -> -88.056981
A104: Is the first order profitable after CAC? | B104: =IF(B103>=0,"YES - first order covers CAC","NO - first order loses money after CAC") -> NO - first order loses money after CAC
A105: Payback month (numeric; 99 = none within 24 months) | B105: =MIN(C100:Z100) -> 99
A106: Payback (display) | B106: =IF(B105>24,"No payback within 24 months","Month "&B105) -> No payback within 24 months
A107: 12-month contribution LTV per customer (before CAC) | B107: =SUM(C94:N94)/$B$66 -> -25.481478
A108: 24-month contribution LTV per customer (before CAC) | B108: =SUM(C94:Z94)/$B$66 -> -26.376075
A109: 12-month contribution LTV net of CAC | B109: =B107-$B$73 -> -90.481478
A110: 24-month contribution LTV net of CAC | B110: =B108-$B$73 -> -91.376075
...

Sheet Espresso_UnitEcon
A1: Espresso_UnitEcon: per-order contribution, Dedica 51mm kit (SHADOW CASE)
A2: Group 1 follows the scenario selector; groups 2-4 are the Pessimistic / Base / Optimistic engine for Scenarios. Beans ship from the US roaster (second parcel) at Roastify / Dripshipper published rates.
A3: Costs shown as negatives. Contribution = net revenue less all variable costs (product, fulfillment, postage, payments, warranty, returns, chargebacks, affiliates). Fixed costs (apps, 3PL storage, UGC) are in Launch_Budget.
A5: Scenario group | B5: ="SELECTED scenario: "&Inputs!$E$3 -> SELECTED scenario: Base | H5: PESSIMISTIC (engine) | N5: BASE (engine) | T5: OPTIMISTIC (engine)
A6: Inputs column used | B6: G = Selected | H6: D = Pessimistic | N6: E = Base | T6: F = Optimistic
A7: Multiplier - paid CPA | B7: 1 | H7: 1 | N7: 1 | T7: 1
A8: Multiplier - supplier unit cost (COGS) | B8: 1 | H8: 1 | N8: 1 | T8: 1
A9: Multiplier - postage | B9: 1 | H9: 1 | N9: 1 | T9: 1
A10: Multiplier - subscription attach (used in cohort) | B10: 1 | H10: 1 | N10: 1 | T10: 1
A11: Multiplier - churn (used in cohort) | B11: 1 | H11: 1 | N11: 1 | T11: 1
A12: Multiplier - refunds, replacements, returns | B12: 1 | H12: 1 | N12: 1 | T12: 1
A14: Landed cost build (per unit, value in first column of each group)
A15: Test-stage kit landed (AliExpress x (1 + duty + AutoDS fee)) | B15: =Inputs!$G$33*$B$8*(1+Inputs!$G$34+Inputs!$G$27) -> 56.862 | H15: =Inputs!$D$33*$H$8*(1+Inputs!$D$34+Inputs!$D$27) -> 93.66672 | N15: =Inputs!$E$33*$N$8*(1+Inputs!$E$34+Inputs!$E$27) -> 56.862 | T15: =Inputs!$F$33*$T$8*(1+Inputs!$F$34+Inputs!$F$27) -> 31.81
A16: PL kit FOB (portafilter + tamper + WDT + screen) | B16: =Inputs!$G$65*$B$8 -> 19.3 | H16: =Inputs!$D$65*$H$8 -> 43 | N16: =Inputs!$E$65*$N$8 -> 19.3 | T16: =Inputs!$F$65*$T$8 -> 13.67
A17: PL duty | B17: =$B$16*Inputs!$G$66 -> 7.9902 | H17: =$H$16*Inputs!$D$66 -> 17.802 | N17: =$N$16*Inputs!$E$66 -> 7.9902 | T17: =$T$16*Inputs!$F$66 -> 3.81393
A18: PL freight per kit | B18: =Inputs!$G$67 -> 1.5 | H18: =Inputs!$D$67 -> 2.5 | N18: =Inputs!$E$67 -> 1.5 | T18: =Inputs!$F$67 -> 1
A19: PL customs entry fees per kit | B19: =(Inputs!$G$41+Inputs!$G$42+Inputs!$G$43+MAX(Inputs!$G$45,MIN(Inputs!$G$46,Inputs!$G$44*Inputs!$G$68*$B$16))+Inputs!$G$47*Inputs!$G$68*$B$16)/Inputs!$G$68 -> 1.567025 | H19: =(Inputs!$D$41+Inputs!$D$42+Inputs!$D$43+MAX(Inputs!$D$45,MIN(Inputs!$D$46,Inputs!$D$44*Inputs!$D$68*$H$16))+Inputs!$D$47*Inputs!$D$68*$H$16)/Inputs!$D$68 -> 4.38955 | N19: =(Inputs!$E$41+Inputs!$E$42+Inputs!$E$43+MAX(Inputs!$E$45,MIN(Inputs!$E$46,Inputs!$E$44*Inputs!$E$68*$N$16))+Inputs!$E$47*Inputs!$E$68*$N$16)/Inputs!$E$68 -> 1.567025 | T19: =(Inputs!$F$41+Inputs!$F$42+Inputs!$F$43+MAX(Inputs!$F$45,MIN(Inputs!$F$46,Inputs!$F$44*Inputs!$F$68*$T$16))+Inputs!$F$47*Inputs!$F$68*$T$16)/Inputs!$F$68 -> 0.6956875
A20: PL kit packaging | B20: =Inputs!$G$69 -> 1 | H20: =Inputs!$D$69 -> 1.5 | N20: =Inputs!$E$69 -> 1 | T20: =Inputs!$F$69 -> 0.7
A21: PL certification amortization (Prop 65 + food-contact) | B21: =(Inputs!$G$50+Inputs!$G$51)/Inputs!$G$70 -> 3.3 | H21: =(Inputs!$D$50+Inputs!$D$51)/Inputs!$D$70 -> 8 | N21: =(Inputs!$E$50+Inputs!$E$51)/Inputs!$E$70 -> 3.3 | T21: =(Inputs!$F$50+Inputs!$F$51)/Inputs!$F$70 -> 1.05
A22: PL kit landed cost | B22: =SUM(B16:B21) -> 34.657225 | H22: =SUM(H16:H21) -> 77.19155 | N22: =SUM(N16:N21) -> 34.657225 | T22: =SUM(T16:T21) -> 20.929617
A23: Bean product cost per shipment (bags x roaster price) | B23: =Inputs!$G$23*Inputs!$G$72*$B$8 -> 24 | H23: =Inputs!$D$23*Inputs!$D$72*$H$8 -> 26.4 | N23: =Inputs!$E$23*Inputs!$E$72*$N$8 -> 24 | T23: =Inputs!$F$23*Inputs!$F$72*$T$8 -> 18.78
A24: Roaster dropship shipping per shipment | B24: =Inputs!$G$73+(Inputs!$G$23-1)*Inputs!$G$74 -> 5.75 | H24: =Inputs!$D$73+(Inputs!$D$23-1)*Inputs!$D$74 -> 5.75 | N24: =Inputs!$E$73+(Inputs!$E$23-1)*Inputs!$E$74 -> 5.75 | T24: =Inputs!$F$73+(Inputs!$F$23-1)*Inputs!$F$74 -> 0
A26: Order type | B26: (a) Dedica kit first order - TEST stage (AliExpress) | C26: (b) Dedica kit first order - PRIVATE LABEL | D26: (c) Kit + first bean shipment (subscription) - PL | E26: (d) Bean subscription renewal (monthly) | F26: (e) Beans - one-time repeat order | H26: (a) Dedica kit first order - TEST stage (AliExpress) | I26: (b) Dedica kit first order - PRIVATE LABEL | J26: (c) Kit + first bean shipment (subscription) - PL | K26: (d) Bean subscription renewal (monthly) | L26: (e) Beans - one-time repeat order | N26: (a) Dedica kit first order - TEST stage (AliExpress) | O26: (b) Dedica kit first order - PRIVATE LABEL | P26: (c) Kit + first bean shipment (subscription) - PL | Q26: (d) Bean subscription renewal (monthly) | R26: (e) Beans - one-time repeat order | T26: (a) Dedica kit first order - TEST stage (AliExpress) | U26: (b) Dedica kit first order - PRIVATE LABEL | V26: (c) Kit + first bean shipment (subscription) - PL | W26: (d) Bean subscription renewal (monthly) | X26: (e) Beans - one-time repeat order
A27: Stage | B27: Test | C27: Private label | D27: Private label | E27: Renewal | F27: One-time | H27: Test | I27: Private label | J27: Private label | K27: Renewal | L27: One-time | N27: Test | O27: Private label | P27: Private label | Q27: Renewal | R27: One-time | T27: Test | U27: Private label | V27: Private label | W27: Renewal | X27: One-time
A28: Kit units | B28: 1 | C28: 1 | D28: 1 | E28: 0 | F28: 0 | H28: 1 | I28: 1 | J28: 1 | K28: 0 | L28: 0 | N28: 1 | O28: 1 | P28: 1 | Q28: 0 | R28: 0 | T28: 1 | U28: 1 | V28: 1 | W28: 0 | X28: 0
A29: Bean shipments at subscription price | B29: 0 | C29: 0 | D29: 1 | E29: 1 | F29: 0 | H29: 0 | I29: 0 | J29: 1 | K29: 1 | L29: 0 | N29: 0 | O29: 0 | P29: 1 | Q29: 1 | R29: 0 | T29: 0 | U29: 0 | V29: 1 | W29: 1 | X29: 0
A30: Bean shipments at one-time price | B30: 0 | C30: 0 | D30: 0 | E30: 0 | F30: 1 | H30: 0 | I30: 0 | J30: 0 | K30: 0 | L30: 1 | N30: 0 | O30: 0 | P30: 0 | Q30: 0 | R30: 1 | T30: 0 | U30: 0 | V30: 0 | W30: 0 | X30: 1
A31: Revenue - kit | B31: =B28*Inputs!$G$18 -> 84.99 | C31: =C28*Inputs!$G$18 -> 84.99 | D31: =D28*Inputs!$G$18 -> 84.99 | E31: =E28*Inputs!$G$18 -> 0 | F31: =F28*Inputs!$G$18 -> 0 | H31: =H28*Inputs!$D$18 -> 74.99 | I31: =I28*Inputs!$D$18 -> 74.99 | J31: =J28*Inputs!$D$18 -> 74.99 | K31: =K28*Inputs!$D$18 -> 0 | L31: =L28*Inputs!$D$18 -> 0 | N31: =N28*Inputs!$E$18 -> 84.99 | O31: =O28*Inputs!$E$18 -> 84.99 | P31: =P28*Inputs!$E$18 -> 84.99 | Q31: =Q28*Inputs!$E$18 -> 0 | R31: =R28*Inputs!$E$18 -> 0 | T31: =T28*Inputs!$F$18 -> 99.99 | U31: =U28*Inputs!$F$18 -> 99.99 | V31: =V28*Inputs!$F$18 -> 99.99 | W31: =W28*Inputs!$F$18 -> 0 | X31: =X28*Inputs!$F$18 -> 0
A32: Revenue - beans (subscription) | B32: =B29*Inputs!$G$22 -> 0 | C32: =C29*Inputs!$G$22 -> 0 | D32: =D29*Inputs!$G$22 -> 35.991 | E32: =E29*Inputs!$G$22 -> 35.991 | F32: =F29*Inputs!$G$22 -> 0 | H32: =H29*Inputs!$D$22 -> 0 | I32: =I29*Inputs!$D$22 -> 0 | J32: =J29*Inputs!$D$22 -> 34.191 | K32: =K29*Inputs!$D$22 -> 34.191 | L32: =L29*Inputs!$D$22 -> 0 | N32: =N29*Inputs!$E$22 -> 0 | O32: =O29*Inputs!$E$22 -> 0 | P32: =P29*Inputs!$E$22 -> 35.991 | Q32: =Q29*Inputs!$E$22 -> 35.991 | R32: =R29*Inputs!$E$22 -> 0 | T32: =T29*Inputs!$F$22 -> 0 | U32: =U29*Inputs!$F$22 -> 0 | V32: =V29*Inputs!$F$22 -> 39.591 | W32: =W29*Inputs!$F$22 -> 39.591 | X32: =X29*Inputs!$F$22 -> 0
A33: Revenue - beans (one-time) | B33: =B30*Inputs!$G$20 -> 0 | C33: =C30*Inputs!$G$20 -> 0 | D33: =D30*Inputs!$G$20 -> 0 | E33: =E30*Inputs!$G$20 -> 0 | F33: =F30*Inputs!$G$20 -> 39.99 | H33: =H30*Inputs!$D$20 -> 0 | I33: =I30*Inputs!$D$20 -> 0 | J33: =J30*Inputs!$D$20 -> 0 | K33: =K30*Inputs!$D$20 -> 0 | L33: =L30*Inputs!$D$20 -> 37.99 | N33: =N30*Inputs!$E$20 -> 0 | O33: =O30*Inputs!$E$20 -> 0 | P33: =P30*Inputs!$E$20 -> 0 | Q33: =Q30*Inputs!$E$20 -> 0 | R33: =R30*Inputs!$E$20 -> 39.99 | T33: =T30*Inputs!$F$20 -> 0 | U33: =U30*Inputs!$F$20 -> 0 | V33: =V30*Inputs!$F$20 -> 0 | W33: =W30*Inputs!$F$20 -> 0 | X33: =X30*Inputs!$F$20 -> 43.99
A34: Shipping charged to customer | B34: 0 | C34: 0 | D34: 0 | E34: 0 | F34: 0 | H34: 0 | I34: 0 | J34: 0 | K34: 0 | L34: 0 | N34: 0 | O34: 0 | P34: 0 | Q34: 0 | R34: 0 | T34: 0 | U34: 0 | V34: 0 | W34: 0 | X34: 0
A35: Gross revenue | B35: =SUM(B31:B34) -> 84.99 | C35: =SUM(C31:C34) -> 84.99 | D35: =SUM(D31:D34) -> 120.981 | E35: =SUM(E31:E34) -> 35.991 | F35: =SUM(F31:F34) -> 39.99 | H35: =SUM(H31:H34) -> 74.99 | I35: =SUM(I31:I34) -> 74.99 | J35: =SUM(J31:J34) -> 109.181 | K35: =SUM(K31:K34) -> 34.191 | L35: =SUM(L31:L34) -> 37.99 | N35: =SUM(N31:N34) -> 84.99 | O35: =SUM(O31:O34) -> 84.99 | P35: =SUM(P31:P34) -> 120.981 | Q35: =SUM(Q31:Q34) -> 35.991 | R35: =SUM(R31:R34) -> 39.99 | T35: =SUM(T31:T34) -> 99.99 | U35: =SUM(U31:U34) -> 99.99 | V35: =SUM(V31:V34) -> 139.581 | W35: =SUM(W31:W34) -> 39.591 | X35: =SUM(X31:X34) -> 43.99
A36: Refunds / returns (revenue reversed) | B36: =-(B31*Inputs!$G$105+(B32+B33)*Inputs!$G$107)*$B$12 -> -5.9493 | C36: =-(C31*Inputs!$G$105+(C32+C33)*Inputs!$G$107)*$B$12 -> -5.9493 | D36: =-(D31*Inputs!$G$105+(D32+D33)*Inputs!$G$107)*$B$12 -> -6.30921 | E36: =-(E31*Inputs!$G$105+(E32+E33)*Inputs!$G$107)*$B$12 -> -0.35991 | F36: =-(F31*Inputs!$G$105+(F32+F33)*Inputs!$G$107)*$B$12 -> -0.3999 | H36: =-(H31*Inputs!$D$105+(H32+H33)*Inputs!$D$107)*$H$12 -> -8.9988 | I36: =-(I31*Inputs!$D$105+(I32+I33)*Inputs!$D$107)*$H$12 -> -8.9988 | J36: =-(J31*Inputs!$D$105+(J32+J33)*Inputs!$D$107)*$H$12 -> -9.68262 | K36: =-(K31*Inputs!$D$105+(K32+K33)*Inputs!$D$107)*$H$12 -> -0.68382 | L36: =-(L31*Inputs!$D$105+(L32+L33)*Inputs!$D$107)*$H$12 -> -0.7598 | N36: =-(N31*Inputs!$E$105+(N32+N33)*Inputs!$E$107)*$N$12 -> -5.9493 | O36: =-(O31*Inputs!$E$105+(O32+O33)*Inputs!$E$107)*$N$12 -> -5.9493 | P36: =-(P31*Inputs!$E$105+(P32+P33)*Inputs!$E$107)*$N$12 -> -6.30921 | Q36: =-(Q31*Inputs!$E$105+(Q32+Q33)*Inputs!$E$107)*$N$12 -> -0.35991 | R36: =-(R31*Inputs!$E$105+(R32+R33)*Inputs!$E$107)*$N$12 -> -0.3999 | T36: =-(T31*Inputs!$F$105+(T32+T33)*Inputs!$F$107)*$T$12 -> -3.9996 | U36: =-(U31*Inputs!$F$105+(U32+U33)*Inputs!$F$107)*$T$12 -> -3.9996 | V36: =-(V31*Inputs!$F$105+(V32+V33)*Inputs!$F$107)*$T$12 -> -4.197555 | W36: =-(W31*Inputs!$F$105+(W32+W33)*Inputs!$F$107)*$T$12 -> -0.197955 | X36: =-(X31*Inputs!$F$105+(X32+X33)*Inputs!$F$107)*$T$12 -> -0.21995
A37: Net revenue | B37: =B35+B36 -> 79.0407 | C37: =C35+C36 -> 79.0407 | D37: =D35+D36 -> 114.67179 | E37: =E35+E36 -> 35.63109 | F37: =F35+F36 -> 39.5901 | H37: =H35+H36 -> 65.9912 | I37: =I35+I36 -> 65.9912 | J37: =J35+J36 -> 99.49838 | K37: =K35+K36 -> 33.50718 | L37: =L35+L36 -> 37.2302 | N37: =N35+N36 -> 79.0407 | O37: =O35+O36 -> 79.0407 | P37: =P35+P36 -> 114.67179 | Q37: =Q35+Q36 -> 35.63109 | R37: =R35+R36 -> 39.5901 | T37: =T35+T36 -> 95.9904 | U37: =U35+U36 -> 95.9904 | V37: =V35+V36 -> 135.38344 | W37: =W35+W36 -> 39.393045 | X37: =X35+X36 -> 43.77005
A38: Product cost - kit | B38: =-B28*$B$15 -> -56.862 | C38: =-C28*$B$22 -> -34.657225 | D38: =-D28*$B$22 -> -34.657225 | E38: =-E28*$B$22 -> 0 | F38: =-F28*$B$22 -> 0 | H38: =-H28*$H$15 -> -93.66672 | I38: =-I28*$H$22 -> -77.19155 | J38: =-J28*$H$22 -> -77.19155 | K38: =-K28*$H$22 -> 0 | L38: =-L28*$H$22 -> 0 | N38: =-N28*$N$15 -> -56.862 | O38: =-O28*$N$22 -> -34.657225 | P38: =-P28*$N$22 -> -34.657225 | Q38: =-Q28*$N$22 -> 0 | R38: =-R28*$N$22 -> 0 | T38: =-T28*$T$15 -> -31.81 | U38: =-U28*$T$22 -> -20.929617 | V38: =-V28*$T$22 -> -20.929617 | W38: =-W28*$T$22 -> 0 | X38: =-X28*$T$22 -> 0
A39: Product cost - beans | B39: =-(B29+B30)*$B$23 -> 0 | C39: =-(C29+C30)*$B$23 -> 0 | D39: =-(D29+D30)*$B$23 -> -24 | E39: =-(E29+E30)*$B$23 -> -24 | F39: =-(F29+F30)*$B$23 -> -24 | H39: =-(H29+H30)*$H$23 -> 0 | I39: =-(I29+I30)*$H$23 -> 0 | J39: =-(J29+J30)*$H$23 -> -26.4 | K39: =-(K29+K30)*$H$23 -> -26.4 | L39: =-(L29+L30)*$H$23 -> -26.4 | N39: =-(N29+N30)*$N$23 -> 0 | O39: =-(O29+O30)*$N$23 -> 0 | P39: =-(P29+P30)*$N$23 -> -24 | Q39: =-(Q29+Q30)*$N$23 -> -24 | R39: =-(R29+R30)*$N$23 -> -24 | T39: =-(T29+T30)*$T$23 -> 0 | U39: =-(U29+U30)*$T$23 -> 0 | V39: =-(V29+V30)*$T$23 -> -18.78 | W39: =-(W29+W30)*$T$23 -> -18.78 | X39: =-(X29+X30)*$T$23 -> -18.78
A40: Roaster shipping (beans) | B40: =-(B29+B30)*$B$24*$B$9 -> 0 | C40: =-(C29+C30)*$B$24*$B$9 -> 0 | D40: =-(D29+D30)*$B$24*$B$9 -> -5.75 | E40: =-(E29+E30)*$B$24*$B$9 -> -5.75 | F40: =-(F29+F30)*$B$24*$B$9 -> -5.75 | H40: =-(H29+H30)*$H$24*$H$9 -> 0 | I40: =-(I29+I30)*$H$24*$H$9 -> 0 | J40: =-(J29+J30)*$H$24*$H$9 -> -5.75 | K40: =-(K29+K30)*$H$24*$H$9 -> -5.75 | L40: =-(L29+L30)*$H$24*$H$9 -> -5.75 | N40: =-(N29+N30)*$N$24*$N$9 -> 0 | O40: =-(O29+O30)*$N$24*$N$9 -> 0 | P40: =-(P29+P30)*$N$24*$N$9 -> -5.75 | Q40: =-(Q29+Q30)*$N$24*$N$9 -> -5.75 | R40: =-(R29+R30)*$N$24*$N$9 -> -5.75 | T40: =-(T29+T30)*$T$24*$T$9 -> 0 | U40: =-(U29+U30)*$T$24*$T$9 -> 0 | V40: =-(V29+V30)*$T$24*$T$9 -> 0 | W40: =-(W29+W30)*$T$24*$T$9 -> 0 | X40: =-(X29+X30)*$T$24*$T$9 -> 0
A41: 3PL pick/pack + packaging - kit (incl. uplift) | B41: 0 | C41: =-C28*(Inputs!$G$88+(Inputs!$G$19-1)*Inputs!$G$89+Inputs!$G$90)*(1+Inputs!$G$92) -> -6.9 | D41: =-D28*(Inputs!$G$88+(Inputs!$G$19-1)*Inputs!$G$89+Inputs!$G$90)*(1+Inputs!$G$92) -> -6.9 | E41: 0 | F41: 0 | H41: 0 | I41: =-I28*(Inputs!$D$88+(Inputs!$D$19-1)*Inputs!$D$89+Inputs!$D$90)*(1+Inputs!$D$92) -> -9.45 | J41: =-J28*(Inputs!$D$88+(Inputs!$D$19-1)*Inputs!$D$89+Inputs!$D$90)*(1+Inputs!$D$92) -> -9.45 | K41: 0 | L41: 0 | N41: 0 | O41: =-O28*(Inputs!$E$88+(Inputs!$E$19-1)*Inputs!$E$89+Inputs!$E$90)*(1+Inputs!$E$92) -> -6.9 | P41: =-P28*(Inputs!$E$88+(Inputs!$E$19-1)*Inputs!$E$89+Inputs!$E$90)*(1+Inputs!$E$92) -> -6.9 | Q41: 0 | R41: 0 | T41: 0 | U41: =-U28*(Inputs!$F$88+(Inputs!$F$19-1)*Inputs!$F$89+Inputs!$F$90)*(1+Inputs!$F$92) -> -4.62 | V41: =-V28*(Inputs!$F$88+(Inputs!$F$19-1)*Inputs!$F$89+Inputs!$F$90)*(1+Inputs!$F$92) -> -4.62 | W41: 0 | X41: 0
A42: Postage - kit (USPS Ground Advantage) | B42: 0 | C42: =-C28*Inputs!$G$86*$B$9 -> -12.12 | D42: =-D28*Inputs!$G$86*$B$9 -> -12.12 | E42: 0 | F42: 0 | H42: 0 | I42: =-I28*Inputs!$D$86*$H$9 -> -14.21 | J42: =-J28*Inputs!$D$86*$H$9 -> -14.21 | K42: 0 | L42: 0 | N42: 0 | O42: =-O28*Inputs!$E$86*$N$9 -> -12.12 | P42: =-P28*Inputs!$E$86*$N$9 -> -12.12 | Q42: 0 | R42: 0 | T42: 0 | U42: =-U28*Inputs!$F$86*$T$9 -> -11.222222 | V42: =-V28*Inputs!$F$86*$T$9 -> -11.222222 | W42: 0 | X42: 0
A43: Payment processing | B43: =-(Inputs!$G$100*B35+Inputs!$G$101) -> -2.76471 | C43: =-(Inputs!$G$100*C35+Inputs!$G$101) -> -2.76471 | D43: =-(Inputs!$G$100*D35+Inputs!$G$101) -> -3.808449 | E43: =-(Inputs!$G$100*E35+Inputs!$G$101) -> -1.343739 | F43: =-(Inputs!$G$100*F35+Inputs!$G$101) -> -1.45971 | H43: =-(Inputs!$D$100*H35+Inputs!$D$101) -> -2.47471 | I43: =-(Inputs!$D$100*I35+Inputs!$D$101) -> -2.47471 | J43: =-(Inputs!$D$100*J35+Inputs!$D$101) -> -3.466249 | K43: =-(Inputs!$D$100*K35+Inputs!$D$101) -> -1.291539 | L43: =-(Inputs!$D$100*L35+Inputs!$D$101) -> -1.40171 | N43: =-(Inputs!$E$100*N35+Inputs!$E$101) -> -2.76471 | O43: =-(Inputs!$E$100*O35+Inputs!$E$101) -> -2.76471 | P43: =-(Inputs!$E$100*P35+Inputs!$E$101) -> -3.808449 | Q43: =-(Inputs!$E$100*Q35+Inputs!$E$101) -> -1.343739 | R43: =-(Inputs!$E$100*R35+Inputs!$E$101) -> -1.45971 | T43: =-(Inputs!$F$100*T35+Inputs!$F$101) -> -3.19971 | U43: =-(Inputs!$F$100*U35+Inputs!$F$101) -> -3.19971 | V43: =-(Inputs!$F$100*V35+Inputs!$F$101) -> -4.347849 | W43: =-(Inputs!$F$100*W35+Inputs!$F$101) -> -1.448139 | X43: =-(Inputs!$F$100*X35+Inputs!$F$101) -> -1.57571
A44: Warranty replacements (expected) | B44: =-Inputs!$G$106*$B$12*$B$15 -> -1.13724 | C44: =-Inputs!$G$106*$B$12*($B$22+(Inputs!$G$88+(Inputs!$G$19-1)*Inputs!$G$89+Inputs!$G$90)*(1+Inputs!$G$92)+Inputs!$G$86*$B$9) -> -1.0735445 | D44: =-Inputs!$G$106*$B$12*($B$22+(Inputs!$G$88+(Inputs!$G$19-1)*Inputs!$G$89+Inputs!$G$90)*(1+Inputs!$G$92)+Inputs!$G$86*$B$9) -> -1.0735445 | E44: 0 | F44: 0 | H44: =-Inputs!$D$106*$H$12*$H$15 -> -2.8100016 | I44: =-Inputs!$D$106*$H$12*($H$22+(Inputs!$D$88+(Inputs!$D$19-1)*Inputs!$D$89+Inputs!$D$90)*(1+Inputs!$D$92)+Inputs!$D$86*$H$9) -> -3.0255465 | J44: =-Inputs!$D$106*$H$12*($H$22+(Inputs!$D$88+(Inputs!$D$19-1)*Inputs!$D$89+Inputs!$D$90)*(1+Inputs!$D$92)+Inputs!$D$86*$H$9) -> -3.0255465 | K44: 0 | L44: 0 | N44: =-Inputs!$E$106*$N$12*$N$15 -> -1.13724 | O44: =-Inputs!$E$106*$N$12*($N$22+(Inputs!$E$88+(Inputs!$E$19-1)*Inputs!$E$89+Inputs!$E$90)*(1+Inputs!$E$92)+Inputs!$E$86*$N$9) -> -1.0735445 | P44: =-Inputs!$E$106*$N$12*($N$22+(Inputs!$E$88+(Inputs!$E$19-1)*Inputs!$E$89+Inputs!$E$90)*(1+Inputs!$E$92)+Inputs!$E$86*$N$9) -> -1.0735445 | Q44: 0 | R44: 0 | T44: =-Inputs!$F$106*$T$12*$T$15 -> -0.3181 | U44: =-Inputs!$F$106*$T$12*($T$22+(Inputs!$F$88+(Inputs!$F$19-1)*Inputs!$F$89+Inputs!$F$90)*(1+Inputs!$F$92)+Inputs!$F$86*$T$9) -> -0.3677184 | V44: =-Inputs!$F$106*$T$12*($T$22+(Inputs!$F$88+(Inputs!$F$19-1)*Inputs!$F$89+Inputs!$F$90)*(1+Inputs!$F$92)+Inputs!$F$86*$T$9) -> -0.3677184 | W44: 0 | X44: 0
A45: Lost / duty-refused parcels (test stage) | B45: =-Inputs!$G$28*$B$15 -> -2.8431 | C45: 0 | D45: 0 | E45: 0 | F45: 0 | H45: =-Inputs!$D$28*$H$15 -> -6.5566704 | I45: 0 | J45: 0 | K45: 0 | L45: 0 | N45: =-Inputs!$E$28*$N$15 -> -2.8431 | O45: 0 | P45: 0 | Q45: 0 | R45: 0 | T45: =-Inputs!$F$28*$T$15 -> -0.6362 | U45: 0 | V45: 0 | W45: 0 | X45: 0
A46: Returns processing (3PL) | B46: 0 | C46: =-Inputs!$G$105*$B$12*Inputs!$G$93 -> -0.2842 | D46: =-Inputs!$G$105*$B$12*Inputs!$G$93 -> -0.2842 | E46: 0 | F46: 0 | H46: 0 | I46: =-Inputs!$D$105*$H$12*Inputs!$D$93 -> -0.84 | J46: =-Inputs!$D$105*$H$12*Inputs!$D$93 -> -0.84 | K46: 0 | L46: 0 | N46: 0 | O46: =-Inputs!$E$105*$N$12*Inputs!$E$93 -> -0.2842 | P46: =-Inputs!$E$105*$N$12*Inputs!$E$93 -> -0.2842 | Q46: 0 | R46: 0 | T46: 0 | U46: =-Inputs!$F$105*$T$12*Inputs!$F$93 -> -0.04 | V46: =-Inputs!$F$105*$T$12*Inputs!$F$93 -> -0.04 | W46: 0 | X46: 0
A47: Chargebacks (expected) | B47: =-Inputs!$G$108*(B35+Inputs!$G$109) -> -0.29997 | C47: =-Inputs!$G$108*(C35+Inputs!$G$109) -> -0.29997 | D47: =-Inputs!$G$108*(D35+Inputs!$G$109) -> -0.407943 | E47: =-Inputs!$G$108*(E35+Inputs!$G$109) -> -0.152973 | F47: =-Inputs!$G$108*(F35+Inputs!$G$109) -> -0.16497 | H47: =-Inputs!$D$108*(H35+Inputs!$D$109) -> -0.53994 | I47: =-Inputs!$D$108*(I35+Inputs!$D$109) -> -0.53994 | J47: =-Inputs!$D$108*(J35+Inputs!$D$109) -> -0.745086 | K47: =-Inputs!$D$108*(K35+Inputs!$D$109) -> -0.295146 | L47: =-Inputs!$D$108*(L35+Inputs!$D$109) -> -0.31794 | N47: =-Inputs!$E$108*(N35+Inputs!$E$109) -> -0.29997 | O47: =-Inputs!$E$108*(O35+Inputs!$E$109) -> -0.29997 | P47: =-Inputs!$E$108*(P35+Inputs!$E$109) -> -0.407943 | Q47: =-Inputs!$E$108*(Q35+Inputs!$E$109) -> -0.152973 | R47: =-Inputs!$E$108*(R35+Inputs!$E$109) -> -0.16497 | T47: =-Inputs!$F$108*(T35+Inputs!$F$109) -> -0.172485 | U47: =-Inputs!$F$108*(U35+Inputs!$F$109) -> -0.172485 | V47: =-Inputs!$F$108*(V35+Inputs!$F$109) -> -0.2318715 | W47: =-Inputs!$F$108*(W35+Inputs!$F$109) -> -0.0818865 | X47: =-Inputs!$F$108*(X35+Inputs!$F$109) -> -0.088485
A48: Affiliate commissions (expected) | B48: =-Inputs!$G$122*Inputs!$G$124*B35 -> -0.50994 | C48: =-Inputs!$G$122*Inputs!$G$124*C35 -> -0.50994 | D48: =-Inputs!$G$122*Inputs!$G$124*D35 -> -0.725886 | E48: 0 | F48: 0 | H48: =-Inputs!$D$122*Inputs!$D$124*H35 -> -0.269964 | I48: =-Inputs!$D$122*Inputs!$D$124*I35 -> -0.269964 | J48: =-Inputs!$D$122*Inputs!$D$124*J35 -> -0.3930516 | K48: 0 | L48: 0 | N48: =-Inputs!$E$122*Inputs!$E$124*N35 -> -0.50994 | O48: =-Inputs!$E$122*Inputs!$E$124*O35 -> -0.50994 | P48: =-Inputs!$E$122*Inputs!$E$124*P35 -> -0.725886 | Q48: 0 | R48: 0 | T48: =-Inputs!$F$122*Inputs!$F$124*T35 -> -0.79992 | U48: =-Inputs!$F$122*Inputs!$F$124*U35 -> -0.79992 | V48: =-Inputs!$F$122*Inputs!$F$124*V35 -> -1.116648 | W48: 0 | X48: 0
A49: Total variable costs | B49: =SUM(B38:B48) -> -64.41696 | C49: =SUM(C38:C48) -> -58.609589 | D49: =SUM(D38:D48) -> -89.727247 | E49: =SUM(E38:E48) -> -31.246712 | F49: =SUM(F38:F48) -> -31.37468 | H49: =SUM(H38:H48) -> -106.31801 | I49: =SUM(I38:I48) -> -108.00171 | J49: =SUM(J38:J48) -> -141.47148 | K49: =SUM(K38:K48) -> -33.736685 | L49: =SUM(L38:L48) -> -33.86965 | N49: =SUM(N38:N48) -> -64.41696 | O49: =SUM(O38:O48) -> -58.609589 | P49: =SUM(P38:P48) -> -89.727247 | Q49: =SUM(Q38:Q48) -> -31.246712 | R49: =SUM(R38:R48) -> -31.37468 | T49: =SUM(T38:T48) -> -36.936415 | U49: =SUM(U38:U48) -> -41.351673 | V49: =SUM(V38:V48) -> -61.655927 | W49: =SUM(W38:W48) -> -20.310026 | X49: =SUM(X38:X48) -> -20.444195
A50: CONTRIBUTION BEFORE ADS | B50: =B37+B49 -> 14.62374 | C50: =C37+C49 -> 20.431111 | D50: =D37+D49 -> 24.944542 | E50: =E37+E49 -> 4.384378 | F50: =F37+F49 -> 8.21542 | H50: =H37+H49 -> -40.326806 | I50: =I37+I49 -> -42.010511 | J50: =J37+J49 -> -41.973103 | K50: =K37+K49 -> -0.229505 | L50: =L37+L49 -> 3.36055 | N50: =N37+N49 -> 14.62374 | O50: =O37+O49 -> 20.431111 | P50: =P37+P49 -> 24.944542 | Q50: =Q37+Q49 -> 4.384378 | R50: =R37+R49 -> 8.21542 | T50: =T37+T49 -> 59.053985 | U50: =U37+U49 -> 54.638727 | V50: =V37+V49 -> 73.727518 | W50: =W37+W49 -> 19.083019 | X50: =X37+X49 -> 23.325855
A51: Contribution margin (% of net revenue) | B51: =IFERROR(B50/B37,0) -> 0.18501531 | C51: =IFERROR(C50/C37,0) -> 0.25848848 | D51: =IFERROR(D50/D37,0) -> 0.2175299 | E51: =IFERROR(E50/E37,0) -> 0.12304922 | F51: =IFERROR(F50/F37,0) -> 0.20751198 | H51: =IFERROR(H50/H37,0) -> -0.61109369 | I51: =IFERROR(I50/I37,0) -> -0.63660777 | J51: =IFERROR(J50/J37,0) -> -0.4218471 | K51: =IFERROR(K50/K37,0) -> -0.0068494275 | L51: =IFERROR(L50/L37,0) -> 0.090264087 | N51: =IFERROR(N50/N37,0) -> 0.18501531 | O51: =IFERROR(O50/O37,0) -> 0.25848848 | P51: =IFERROR(P50/P37,0) -> 0.2175299 | Q51: =IFERROR(Q50/Q37,0) -> 0.12304922 | R51: =IFERROR(R50/R37,0) -> 0.20751198 | T51: =IFERROR(T50/T37,0) -> 0.6152072 | U51: =IFERROR(U50/U37,0) -> 0.56921033 | V51: =IFERROR(V50/V37,0) -> 0.54458297 | W51: =IFERROR(W50/W37,0) -> 0.48442611 | X51: =IFERROR(X50/X37,0) -> 0.53291817
A52: Paid CPA (first orders only) | B52: =-Inputs!$G$113*$B$7 -> -60 | C52: =-Inputs!$G$114*$B$7 -> -45 | D52: =-Inputs!$G$114*$B$7 -> -45 | E52: 0 | F52: 0 | H52: =-Inputs!$D$113*$H$7 -> -85 | I52: =-Inputs!$D$114*$H$7 -> -64 | J52: =-Inputs!$D$114*$H$7 -> -64 | K52: 0 | L52: 0 | N52: =-Inputs!$E$113*$N$7 -> -60 | O52: =-Inputs!$E$114*$N$7 -> -45 | P52: =-Inputs!$E$114*$N$7 -> -45 | Q52: 0 | R52: 0 | T52: =-Inputs!$F$113*$T$7 -> -40 | U52: =-Inputs!$F$114*$T$7 -> -30 | V52: =-Inputs!$F$114*$T$7 -> -30 | W52: 0 | X52: 0
A53: CONTRIBUTION AFTER CPA | B53: =B50+B52 -> -45.37626 | C53: =C50+C52 -> -24.568889 | D53: =D50+D52 -> -20.055458 | E53: =E50+E52 -> 4.384378 | F53: =F50+F52 -> 8.21542 | H53: =H50+H52 -> -125.32681 | I53: =I50+I52 -> -106.01051 | J53: =J50+J52 -> -105.9731 | K53: =K50+K52 -> -0.229505 | L53: =L50+L52 -> 3.36055 | N53: =N50+N52 -> -45.37626 | O53: =O50+O52 -> -24.568889 | P53: =P50+P52 -> -20.055458 | Q53: =Q50+Q52 -> 4.384378 | R53: =R50+R52 -> 8.21542 | T53: =T50+T52 -> 19.053985 | U53: =U50+U52 -> 24.638727 | V53: =V50+V52 -> 43.727518 | W53: =W50+W52 -> 19.083019 | X53: =X50+X52 -> 23.325855
A54: Break-even CPA (= contribution before ads) | B54: =B50 -> 14.62374 | C54: =C50 -> 20.431111 | D54: =D50 -> 24.944542 | E54: n/a | F54: n/a | H54: =H50 -> -40.326806 | I54: =I50 -> -42.010511 | J54: =J50 -> -41.973103 | K54: n/a | L54: n/a | N54: =N50 -> 14.62374 | O54: =O50 -> 20.431111 | P54: =P50 -> 24.944542 | Q54: n/a | R54: n/a | T54: =T50 -> 59.053985 | U54: =U50 -> 54.638727 | V54: =V50 -> 73.727518 | W54: n/a | X54: n/a
A56: Cohort first-order mix (per new customer; value in first column of each group)
A57: First-order contribution before ads (mix) | B57: =IF(Inputs!$D$4=1,B50+Inputs!$G$144*E50,(1-Inputs!$G$144)*C50+Inputs!$G$144*D50) -> 21.108125 | H57: =IF(Inputs!$D$4=1,H50+Inputs!$D$144*K50,(1-Inputs!$D$144)*I50+Inputs!$D$144*J50) -> -42.007518 | N57: =IF(Inputs!$D$4=1,N50+Inputs!$E$144*Q50,(1-Inputs!$E$144)*O50+Inputs!$E$144*P50) -> 21.108125 | T57: =IF(Inputs!$D$4=1,T50+Inputs!$F$144*W50,(1-Inputs!$F$144)*U50+Inputs!$F$144*V50) -> 59.410925
A58: First-order net revenue (mix) | B58: =IF(Inputs!$D$4=1,B37+Inputs!$G$144*E37,(1-Inputs!$G$144)*C37+Inputs!$G$144*D37) -> 84.385363 | H58: =IF(Inputs!$D$4=1,H37+Inputs!$D$144*K37,(1-Inputs!$D$144)*I37+Inputs!$D$144*J37) -> 68.671774 | N58: =IF(Inputs!$D$4=1,N37+Inputs!$E$144*Q37,(1-Inputs!$E$144)*O37+Inputs!$E$144*P37) -> 84.385363 | T58: =IF(Inputs!$D$4=1,T37+Inputs!$F$144*W37,(1-Inputs!$F$144)*U37+Inputs!$F$144*V37) -> 105.83866
A59: First-order gross revenue (mix) | B59: =IF(Inputs!$D$4=1,B35+Inputs!$G$144*E35,(1-Inputs!$G$144)*C35+Inputs!$G$144*D35) -> 90.38865 | H59: =IF(Inputs!$D$4=1,H35+Inputs!$D$144*K35,(1-Inputs!$D$144)*I35+Inputs!$D$144*J35) -> 77.72528 | N59: =IF(Inputs!$D$4=1,N35+Inputs!$E$144*Q35,(1-Inputs!$E$144)*O35+Inputs!$E$144*P35) -> 90.38865 | T59: =IF(Inputs!$D$4=1,T35+Inputs!$F$144*W35,(1-Inputs!$F$144)*U35+Inputs!$F$144*V35) -> 109.88775
A60: Paid CAC per new customer (by stage) | B60: =IF(Inputs!$D$4=1,Inputs!$G$113,Inputs!$G$114)*$B$7 -> 45 | H60: =IF(Inputs!$D$4=1,Inputs!$D$113,Inputs!$D$114)*$H$7 -> 64 | N60: =IF(Inputs!$D$4=1,Inputs!$E$113,Inputs!$E$114)*$N$7 -> 45 | T60: =IF(Inputs!$D$4=1,Inputs!$F$113,Inputs!$F$114)*$T$7 -> 30
A61: FIRST-ORDER CONTRIBUTION AFTER CAC | B61: =B57-B60 -> -23.891875 | H61: =H57-H60 -> -106.00752 | N61: =N57-N60 -> -23.891875 | T61: =T57-T60 -> 29.410925
A62: First-order contribution margin before ads | B62: =IFERROR(B57/B58,0) -> 0.25013965 | H62: =IFERROR(H57/H58,0) -> -0.61171447 | N62: =IFERROR(N57/N58,0) -> 0.25013965 | T62: =IFERROR(T57/T58,0) -> 0.56133481
A63: First-order contribution - subscribers | B63: =IF(Inputs!$D$4=1,B50+E50,D50) -> 24.944542 | H63: =IF(Inputs!$D$4=1,H50+K50,J50) -> -41.973103 | N63: =IF(Inputs!$D$4=1,N50+Q50,P50) -> 24.944542 | T63: =IF(Inputs!$D$4=1,T50+W50,V50) -> 73.727518
A64: Notes: first-order mix = (b) for non-subscribers and (c) for subscribers (subscription attach on Inputs), or (a) + (d) at test stage. Kit and beans ship as two parcels from two origins. | B64: =IF(Inputs!$D$4=1,B50,C50) -> 20.431111 | H64: =IF(Inputs!$D$4=1,H50,I50) -> -42.010511 | N64: =IF(Inputs!$D$4=1,N50,O50) -> 20.431111 | T64: =IF(Inputs!$D$4=1,T50,U50) -> 54.638727

Sheet Espresso_Cohort
A1: Espresso_Cohort: 24-month cohort of 100 acquired customers (SHADOW CASE)
A2: LTV = contribution profit. Segments: one-time only, occasional bean buyers, monthly bean subscribers (Roastify/Dripshipper dropship).
A4: ="SELECTED SCENARIO COHORT: "&Inputs!$E$3&" | stage: "&Inputs!$E$4 -> SELECTED SCENARIO COHORT: Base | stage: Private label (OEM + 3PL, CPA months 4-12)
A6: Customers acquired (N) | B6: =Inputs!$G$9 -> 100
A7: Subscription attach (after any shock) | B7: =MIN(1,Inputs!$G$144*Espresso_UnitEcon!$B$10) -> 0.15
A8: Non-subscriber 12-month repeat rate | B8: =Inputs!$G$147 -> 0.15
A9: Segment: subscribers | B9: =$B$6*$B$7 -> 15
A10: Segment: occasional repeat buyers | B10: =$B$6*(1-$B$7)*$B$8 -> 12.75
A11: Segment: one-time only | B11: =$B$6-$B$9-$B$10 -> 72.25
A12: First-order contribution before ads, per customer (mix) | B12: =Espresso_UnitEcon!$B$57 -> 21.108125
A13: Paid CAC per new customer | B13: =Espresso_UnitEcon!$B$60 -> 45
A14: Contribution per subscription renewal order | B14: =Espresso_UnitEcon!$E$50 -> 4.384378
A15: Contribution per occasional repeat order | B15: =Espresso_UnitEcon!$F$50 -> 8.21542
A16: First-month drop (incl. involuntary) | B16: =1-(1-MIN(1,Inputs!$G$145*Espresso_UnitEcon!$B$11))*(1-MIN(1,Inputs!$G$137*Espresso_UnitEcon!$B$11)) -> 0.18574
A17: Monthly churn after month 2 (incl. involuntary) | B17: =1-(1-MIN(1,Inputs!$G$146*Espresso_UnitEcon!$B$11))*(1-MIN(1,Inputs!$G$137*Espresso_UnitEcon!$B$11)) -> 0.07651
A18: Renewal cadence (months) | B18: 1
A19: Occasional: month of first repeat | B19: =Inputs!$G$148 -> 2
A20: Occasional: months between orders | B20: =Inputs!$G$149 -> 3
A21: Occasional: probability of each further order | B21: =Inputs!$G$150 -> 0.5
A22: First-order contribution - subscriber | B22: =Espresso_UnitEcon!$B$63 -> 24.944542
A23: First-order contribution - non-subscriber | B23: =Espresso_UnitEcon!$B$64 -> 20.431111
A24: First-order gross revenue (mix) - reference | B24: =Espresso_UnitEcon!$B$59 -> 90.38865
A25: Renewal order gross revenue - reference | B25: =Espresso_UnitEcon!$E$35 -> 35.991
A26: Occasional order gross revenue - reference | B26: =Espresso_UnitEcon!$F$35 -> 39.99
A28: Month | B28: Total 1-24 | C28: 1 | D28: 2 | E28: 3 | F28: 4 | G28: 5 | H28: 6 | I28: 7 | J28: 8 | K28: 9 | L28: 10 | M28: 11 | N28: 12 | O28: 13 | P28: 14 | Q28: 15 | R28: 16 | S28: 17 | T28: 18 | U28: 19 | V28: 20 | W28: 21 | X28: 22 | Y28: 23 | Z28: 24
A29: Subscription renewal orders (paying subscribers) | B29: =SUM(C29:Z29) -> 134.04758 | C29: =IF(C$28>=2,$B$9*(1-$B$16)*(1-$B$17)^(C$28-2),0) -> 0 | D29: =IF(D$28>=2,$B$9*(1-$B$16)*(1-$B$17)^(D$28-2),0) -> 12.2139 | E29: =IF(E$28>=2,$B$9*(1-$B$16)*(1-$B$17)^(E$28-2),0) -> 11.279415 | F29: =IF(F$28>=2,$B$9*(1-$B$16)*(1-$B$17)^(F$28-2),0) -> 10.416427 | G29: =IF(G$28>=2,$B$9*(1-$B$16)*(1-$B$17)^(G$28-2),0) -> 9.6194657 | H29: =IF(H$28>=2,$B$9*(1-$B$16)*(1-$B$17)^(H$28-2),0) -> 8.8834804 | I29: =IF(I$28>=2,$B$9*(1-$B$16)*(1-$B$17)^(I$28-2),0) -> 8.2038053 | J29: =IF(J$28>=2,$B$9*(1-$B$16)*(1-$B$17)^(J$28-2),0) -> 7.5761322 | ... Z29: =IF(Z$28>=2,$B$9*(1-$B$16)*(1-$B$17)^(Z$28-2),0) -> 2.120131
A30: Occasional repeat orders | B30: =SUM(C30:Z30) -> 25.400391 | C30: =IF(AND(C$28>=$B$19,MOD(C$28-$B$19,$B$20)=0),$B$10*$B$21^((C$28-$B$19)/$B$20),0) -> 0 | D30: =IF(AND(D$28>=$B$19,MOD(D$28-$B$19,$B$20)=0),$B$10*$B$21^((D$28-$B$19)/$B$20),0) -> 12.75 | E30: =IF(AND(E$28>=$B$19,MOD(E$28-$B$19,$B$20)=0),$B$10*$B$21^((E$28-$B$19)/$B$20),0) -> 0 | F30: =IF(AND(F$28>=$B$19,MOD(F$28-$B$19,$B$20)=0),$B$10*$B$21^((F$28-$B$19)/$B$20),0) -> 0 | G30: =IF(AND(G$28>=$B$19,MOD(G$28-$B$19,$B$20)=0),$B$10*$B$21^((G$28-$B$19)/$B$20),0) -> 6.375 | H30: =IF(AND(H$28>=$B$19,MOD(H$28-$B$19,$B$20)=0),$B$10*$B$21^((H$28-$B$19)/$B$20),0) -> 0 | I30: =IF(AND(I$28>=$B$19,MOD(I$28-$B$19,$B$20)=0),$B$10*$B$21^((I$28-$B$19)/$B$20),0) -> 0 | J30: =IF(AND(J$28>=$B$19,MOD(J$28-$B$19,$B$20)=0),$B$10*$B$21^((J$28-$B$19)/$B$20),0) -> 3.1875 | ... Z30: =IF(AND(Z$28>=$B$19,MOD(Z$28-$B$19,$B$20)=0),$B$10*$B$21^((Z$28-$B$19)/$B$20),0) -> 0
A31: Contribution - one-time-only segment | B31: =SUM(C31:Z31) -> 1476.1477 | C31: =IF(C$28=1,$B$11*$B$23,0) -> 1476.1477 | D31: =IF(D$28=1,$B$11*$B$23,0) -> 0 | E31: =IF(E$28=1,$B$11*$B$23,0) -> 0 | F31: =IF(F$28=1,$B$11*$B$23,0) -> 0 | G31: =IF(G$28=1,$B$11*$B$23,0) -> 0 | H31: =IF(H$28=1,$B$11*$B$23,0) -> 0 | I31: =IF(I$28=1,$B$11*$B$23,0) -> 0 | J31: =IF(J$28=1,$B$11*$B$23,0) -> 0 | ... Z31: =IF(Z$28=1,$B$11*$B$23,0) -> 0
A32: Contribution - occasional repeat segment | B32: =SUM(C32:Z32) -> 469.17154 | C32: =IF(C$28=1,$B$10*$B$23,0)+C30*$B$15 -> 260.49666 | D32: =IF(D$28=1,$B$10*$B$23,0)+D30*$B$15 -> 104.7466 | E32: =IF(E$28=1,$B$10*$B$23,0)+E30*$B$15 -> 0 | F32: =IF(F$28=1,$B$10*$B$23,0)+F30*$B$15 -> 0 | G32: =IF(G$28=1,$B$10*$B$23,0)+G30*$B$15 -> 52.373302 | H32: =IF(H$28=1,$B$10*$B$23,0)+H30*$B$15 -> 0 | I32: =IF(I$28=1,$B$10*$B$23,0)+I30*$B$15 -> 0 | J32: =IF(J$28=1,$B$10*$B$23,0)+J30*$B$15 -> 26.186651 | ... Z32: =IF(Z$28=1,$B$10*$B$23,0)+Z30*$B$15 -> 0
A33: Contribution - subscriber segment | B33: =SUM(C33:Z33) -> 961.88339 | C33: =IF(C$28=1,$B$9*$B$22,0)+C29*$B$14 -> 374.16814 | D33: =IF(D$28=1,$B$9*$B$22,0)+D29*$B$14 -> 53.550354 | E33: =IF(E$28=1,$B$9*$B$22,0)+E29*$B$14 -> 49.453217 | F33: =IF(F$28=1,$B$9*$B$22,0)+F29*$B$14 -> 45.669551 | G33: =IF(G$28=1,$B$9*$B$22,0)+G29*$B$14 -> 42.175374 | H33: =IF(H$28=1,$B$9*$B$22,0)+H29*$B$14 -> 38.948536 | I33: =IF(I$28=1,$B$9*$B$22,0)+I29*$B$14 -> 35.968584 | J33: =IF(J$28=1,$B$9*$B$22,0)+J29*$B$14 -> 33.216627 | ... Z33: =IF(Z$28=1,$B$9*$B$22,0)+Z29*$B$14 -> 9.2954557
A34: Total contribution before CAC | B34: =SUM(C34:Z34) -> 2907.2027 | C34: =SUM(C31:C33) -> 2110.8125 | D34: =SUM(D31:D33) -> 158.29696 | E34: =SUM(E31:E33) -> 49.453217 | F34: =SUM(F31:F33) -> 45.669551 | G34: =SUM(G31:G33) -> 94.548676 | H34: =SUM(H31:H33) -> 38.948536 | I34: =SUM(I31:I33) -> 35.968584 | J34: =SUM(J31:J33) -> 59.403278 | ... Z34: =SUM(Z31:Z33) -> 9.2954557
A35: CAC (paid, month 1) | B35: =SUM(C35:Z35) -> -4500 | C35: =IF(C$28=1,-$B$6*$B$13,0) -> -4500 | D35: =IF(D$28=1,-$B$6*$B$13,0) -> 0 | E35: =IF(E$28=1,-$B$6*$B$13,0) -> 0 | F35: =IF(F$28=1,-$B$6*$B$13,0) -> 0 | G35: =IF(G$28=1,-$B$6*$B$13,0) -> 0 | H35: =IF(H$28=1,-$B$6*$B$13,0) -> 0 | I35: =IF(I$28=1,-$B$6*$B$13,0) -> 0 | J35: =IF(J$28=1,-$B$6*$B$13,0) -> 0 | ... Z35: =IF(Z$28=1,-$B$6*$B$13,0) -> 0
A36: Net contribution after CAC | B36: =SUM(C36:Z36) -> -1592.7973 | C36: =C34+C35 -> -2389.1875 | D36: =D34+D35 -> 158.29696 | E36: =E34+E35 -> 49.453217 | F36: =F34+F35 -> 45.669551 | G36: =G34+G35 -> 94.548676 | H36: =H34+H35 -> 38.948536 | I36: =I34+I35 -> 35.968584 | J36: =J34+J35 -> 59.403278 | ... Z36: =Z34+Z35 -> 9.2954557
A37: CUMULATIVE contribution after CAC | C37: =C36 -> -2389.1875 | D37: =C37+D36 -> -2230.8905 | E37: =D37+E36 -> -2181.4373 | F37: =E37+F36 -> -2135.7677 | G37: =F37+G36 -> -2041.2191 | H37: =G37+H36 -> -2002.2705 | I37: =H37+I36 -> -1966.3019 | J37: =I37+J36 -> -1906.8987 | K37: =J37+K36 -> -1876.2234 | ... Z37: =Y37+Z36 -> -1592.7973
A38: Cumulative contribution before CAC, per customer | C38: =SUM($C34:C34)/$B$6 -> 21.108125 | D38: =SUM($C34:D34)/$B$6 -> 22.691095 | E38: =SUM($C34:E34)/$B$6 -> 23.185627 | F38: =SUM($C34:F34)/$B$6 -> 23.642323 | G38: =SUM($C34:G34)/$B$6 -> 24.587809 | H38: =SUM($C34:H34)/$B$6 -> 24.977295 | I38: =SUM($C34:I34)/$B$6 -> 25.336981 | J38: =SUM($C34:J34)/$B$6 -> 25.931013 | ... Z38: =SUM($C34:Z34)/$B$6 -> 29.072027
A39: Gross revenue (reference only - NOT used for LTV) | B39: =SUM(C39:Z39) -> 14879.133 | C39: =IF(C$28=1,$B$6*$B$24,0)+C29*$B$25+C30*$B$26 -> 9038.865 | D39: =IF(D$28=1,$B$6*$B$24,0)+D29*$B$25+D30*$B$26 -> 949.46297 | E39: =IF(E$28=1,$B$6*$B$24,0)+E29*$B$25+E30*$B$26 -> 405.95741 | F39: =IF(F$28=1,$B$6*$B$24,0)+F29*$B$25+F30*$B$26 -> 374.89761 | G39: =IF(G$28=1,$B$6*$B$24,0)+G29*$B$25+G30*$B$26 -> 601.15044 | H39: =IF(H$28=1,$B$6*$B$24,0)+H29*$B$25+H30*$B$26 -> 319.72534 | I39: =IF(I$28=1,$B$6*$B$24,0)+I29*$B$25+I30*$B$26 -> 295.26316 | J39: =IF(J$28=1,$B$6*$B$24,0)+J29*$B$25+J30*$B$26 -> 400.1407 | ... Z39: =IF(Z$28=1,$B$6*$B$24,0)+Z29*$B$25+Z30*$B$26 -> 76.305635
A40: Payback helper (month if cumulative >= 0, else 99) | C40: =IF(C37>=0,C$28,99) -> 99 | D40: =IF(D37>=0,D$28,99) -> 99 | E40: =IF(E37>=0,E$28,99) -> 99 | F40: =IF(F37>=0,F$28,99) -> 99 | G40: =IF(G37>=0,G$28,99) -> 99 | H40: =IF(H37>=0,H$28,99) -> 99 | I40: =IF(I37>=0,I$28,99) -> 99 | J40: =IF(J37>=0,J$28,99) -> 99 | ... Z40: =IF(Z37>=0,Z$28,99) -> 99
A42: FIRST-ORDER contribution before ads, per customer | B42: =$B$12 -> 21.108125
A43: FIRST-ORDER contribution after CAC, per customer | B43: =$B$12-$B$13 -> -23.891875
A44: Is the first order profitable after CAC? | B44: =IF(B43>=0,"YES - first order covers CAC","NO - first order loses money after CAC") -> NO - first order loses money after CAC
A45: Payback month (numeric; 99 = none within 24 months) | B45: =MIN(C40:Z40) -> 99
A46: Payback (display) | B46: =IF(B45>24,"No payback within 24 months","Month "&B45) -> No payback within 24 months
A47: 12-month contribution LTV per customer (before CAC) | B47: =SUM(C34:N34)/$B$6 -> 27.155183
A48: 24-month contribution LTV per customer (before CAC) | B48: =SUM(C34:Z34)/$B$6 -> 29.072027
A49: 12-month contribution LTV net of CAC | B49: =B47-$B$13 -> -17.844817
A50: 24-month contribution LTV net of CAC | B50: =B48-$B$13 -> -15.927973
A51: 12-month LTV:CAC (contribution basis) | B51: =IFERROR(B47/$B$13,0) -> 0.60344851
A52: 24-month LTV:CAC | B52: =IFERROR(B48/$B$13,0) -> 0.64604504
A53: 12-month LTV : blended CAC (info only) | B53: =IFERROR(B47/($B$13*Inputs!$G$121),0) -> 0.70993943
A54: Cohort contribution from subscription renewals, months 1-24 | B54: =B29*$B$14 -> 587.71525
A55: Renewal contribution per subscriber, 12 months | B55: =IFERROR(SUM(C29:N29)*$B$14/$B$9,0) -> 27.220393
A56: Repeat contribution per occasional buyer, 12 months | B56: =IFERROR(SUM(C30:N30)*$B$15/$B$10,0) -> 15.403912
A57: Orders per acquired customer, 12 months | B57: =($B$6+SUM(C29:N29)+SUM(C30:N30))/$B$6 -> 2.1703369
A58: Renewal contribution per subscriber, 24 months | B58: =IFERROR(SUM(C29:Z29)*$B$14/$B$9,0) -> 39.181017
A59: Repeat contribution per occasional buyer, 24 months | B59: =IFERROR(SUM(C30:Z30)*$B$15/$B$10,0) -> 16.366657
A62: ENGINE BLOCKS BELOW (same formulas; feed Scenarios and Sensitivity; do not edit)
A64: Engine cohort: PESSIMISTIC (engine)
A66: Customers acquired (N) | B66: =Inputs!$D$9 -> 100
A67: Subscription attach (after any shock) | B67: =MIN(1,Inputs!$D$144*Espresso_UnitEcon!$H$10) -> 0.08
A68: Non-subscriber 12-month repeat rate | B68: =Inputs!$D$147 -> 0.1
A69: Segment: subscribers | B69: =$B$66*$B$67 -> 8
A70: Segment: occasional repeat buyers | B70: =$B$66*(1-$B$67)*$B$68 -> 9.2
A71: Segment: one-time only | B71: =$B$66-$B$69-$B$70 -> 82.8
A72: First-order contribution before ads, per customer (mix) | B72: =Espresso_UnitEcon!$H$57 -> -42.007518
A73: Paid CAC per new customer | B73: =Espresso_UnitEcon!$H$60 -> 64
A74: Contribution per subscription renewal order | B74: =Espresso_UnitEcon!$K$50 -> -0.229505
A75: Contribution per occasional repeat order | B75: =Espresso_UnitEcon!$L$50 -> 3.36055
A76: First-month drop (incl. involuntary) | B76: =1-(1-MIN(1,Inputs!$D$145*Espresso_UnitEcon!$H$11))*(1-MIN(1,Inputs!$D$137*Espresso_UnitEcon!$H$11)) -> 0.2575
A77: Monthly churn after month 2 (incl. involuntary) | B77: =1-(1-MIN(1,Inputs!$D$146*Espresso_UnitEcon!$H$11))*(1-MIN(1,Inputs!$D$137*Espresso_UnitEcon!$H$11)) -> 0.109
A78: Renewal cadence (months) | B78: 1
A79: Occasional: month of first repeat | B79: =Inputs!$D$148 -> 3
A80: Occasional: months between orders | B80: =Inputs!$D$149 -> 4
A81: Occasional: probability of each further order | B81: =Inputs!$D$150 -> 0.4
A82: First-order contribution - subscriber | B82: =Espresso_UnitEcon!$H$63 -> -41.973103
A83: First-order contribution - non-subscriber | B83: =Espresso_UnitEcon!$H$64 -> -42.010511
A84: First-order gross revenue (mix) - reference | B84: =Espresso_UnitEcon!$H$59 -> 77.72528
A85: Renewal order gross revenue - reference | B85: =Espresso_UnitEcon!$K$35 -> 34.191
A86: Occasional order gross revenue - reference | B86: =Espresso_UnitEcon!$L$35 -> 37.99
A88: Month | B88: Total 1-24 | C88: 1 | D88: 2 | E88: 3 | F88: 4 | G88: 5 | H88: 6 | I88: 7 | J88: 8 | K88: 9 | L88: 10 | M88: 11 | N88: 12 | O88: 13 | P88: 14 | Q88: 15 | R88: 16 | S88: 17 | T88: 18 | U88: 19 | V88: 20 | W88: 21 | X88: 22 | Y88: 23 | Z88: 24
A89: Subscription renewal orders (paying subscribers) | B89: =SUM(C89:Z89) -> 50.662339 | C89: =IF(C$88>=2,$B$69*(1-$B$76)*(1-$B$77)^(C$88-2),0) -> 0 | D89: =IF(D$88>=2,$B$69*(1-$B$76)*(1-$B$77)^(D$88-2),0) -> 5.94 | E89: =IF(E$88>=2,$B$69*(1-$B$76)*(1-$B$77)^(E$88-2),0) -> 5.29254 | F89: =IF(F$88>=2,$B$69*(1-$B$76)*(1-$B$77)^(F$88-2),0) -> 4.7156531 | G89: =IF(G$88>=2,$B$69*(1-$B$76)*(1-$B$77)^(G$88-2),0) -> 4.2016469 | H89: =IF(H$88>=2,$B$69*(1-$B$76)*(1-$B$77)^(H$88-2),0) -> 3.7436674 | I89: =IF(I$88>=2,$B$69*(1-$B$76)*(1-$B$77)^(I$88-2),0) -> 3.3356077 | J89: =IF(J$88>=2,$B$69*(1-$B$76)*(1-$B$77)^(J$88-2),0) -> 2.9720264 | ... Z89: =IF(Z$88>=2,$B$69*(1-$B$76)*(1-$B$77)^(Z$88-2),0) -> 0.46891695
A90: Occasional repeat orders | B90: =SUM(C90:Z90) -> 15.270528 | C90: =IF(AND(C$88>=$B$79,MOD(C$88-$B$79,$B$80)=0),$B$70*$B$81^((C$88-$B$79)/$B$80),0) -> 0 | D90: =IF(AND(D$88>=$B$79,MOD(D$88-$B$79,$B$80)=0),$B$70*$B$81^((D$88-$B$79)/$B$80),0) -> 0 | E90: =IF(AND(E$88>=$B$79,MOD(E$88-$B$79,$B$80)=0),$B$70*$B$81^((E$88-$B$79)/$B$80),0) -> 9.2 | F90: =IF(AND(F$88>=$B$79,MOD(F$88-$B$79,$B$80)=0),$B$70*$B$81^((F$88-$B$79)/$B$80),0) -> 0 | G90: =IF(AND(G$88>=$B$79,MOD(G$88-$B$79,$B$80)=0),$B$70*$B$81^((G$88-$B$79)/$B$80),0) -> 0 | H90: =IF(AND(H$88>=$B$79,MOD(H$88-$B$79,$B$80)=0),$B$70*$B$81^((H$88-$B$79)/$B$80),0) -> 0 | I90: =IF(AND(I$88>=$B$79,MOD(I$88-$B$79,$B$80)=0),$B$70*$B$81^((I$88-$B$79)/$B$80),0) -> 3.68 | J90: =IF(AND(J$88>=$B$79,MOD(J$88-$B$79,$B$80)=0),$B$70*$B$81^((J$88-$B$79)/$B$80),0) -> 0 | ... Z90: =IF(AND(Z$88>=$B$79,MOD(Z$88-$B$79,$B$80)=0),$B$70*$B$81^((Z$88-$B$79)/$B$80),0) -> 0
A91: Contribution - one-time-only segment | B91: =SUM(C91:Z91) -> -3478.4703 | C91: =IF(C$88=1,$B$71*$B$83,0) -> -3478.4703 | D91: =IF(D$88=1,$B$71*$B$83,0) -> 0 | E91: =IF(E$88=1,$B$71*$B$83,0) -> 0 | F91: =IF(F$88=1,$B$71*$B$83,0) -> 0 | G91: =IF(G$88=1,$B$71*$B$83,0) -> 0 | H91: =IF(H$88=1,$B$71*$B$83,0) -> 0 | I91: =IF(I$88=1,$B$71*$B$83,0) -> 0 | J91: =IF(J$88=1,$B$71*$B$83,0) -> 0 | ... Z91: =IF(Z$88=1,$B$71*$B$83,0) -> 0
A92: Contribution - occasional repeat segment | B92: =SUM(C92:Z92) -> -335.17932 | C92: =IF(C$88=1,$B$70*$B$83,0)+C90*$B$75 -> -386.4967 | D92: =IF(D$88=1,$B$70*$B$83,0)+D90*$B$75 -> 0 | E92: =IF(E$88=1,$B$70*$B$83,0)+E90*$B$75 -> 30.91706 | F92: =IF(F$88=1,$B$70*$B$83,0)+F90*$B$75 -> 0 | G92: =IF(G$88=1,$B$70*$B$83,0)+G90*$B$75 -> 0 | H92: =IF(H$88=1,$B$70*$B$83,0)+H90*$B$75 -> 0 | I92: =IF(I$88=1,$B$70*$B$83,0)+I90*$B$75 -> 12.366824 | J92: =IF(J$88=1,$B$70*$B$83,0)+J90*$B$75 -> 0 | ... Z92: =IF(Z$88=1,$B$70*$B$83,0)+Z90*$B$75 -> 0
A93: Contribution - subscriber segment | B93: =SUM(C93:Z93) -> -347.41209 | C93: =IF(C$88=1,$B$69*$B$82,0)+C89*$B$74 -> -335.78482 | D93: =IF(D$88=1,$B$69*$B$82,0)+D89*$B$74 -> -1.3632597 | E93: =IF(E$88=1,$B$69*$B$82,0)+E89*$B$74 -> -1.2146644 | F93: =IF(F$88=1,$B$69*$B$82,0)+F89*$B$74 -> -1.082266 | G93: =IF(G$88=1,$B$69*$B$82,0)+G89*$B$74 -> -0.96429898 | H93: =IF(H$88=1,$B$69*$B$82,0)+H89*$B$74 -> -0.85919039 | I93: =IF(I$88=1,$B$69*$B$82,0)+I89*$B$74 -> -0.76553864 | J93: =IF(J$88=1,$B$69*$B$82,0)+J89*$B$74 -> -0.68209493 | ... Z93: =IF(Z$88=1,$B$69*$B$82,0)+Z89*$B$74 -> -0.10761879
A94: Total contribution before CAC | B94: =SUM(C94:Z94) -> -4161.0617 | C94: =SUM(C91:C93) -> -4200.7518 | D94: =SUM(D91:D93) -> -1.3632597 | E94: =SUM(E91:E93) -> 29.702396 | F94: =SUM(F91:F93) -> -1.082266 | G94: =SUM(G91:G93) -> -0.96429898 | H94: =SUM(H91:H93) -> -0.85919039 | I94: =SUM(I91:I93) -> 11.601285 | J94: =SUM(J91:J93) -> -0.68209493 | ... Z94: =SUM(Z91:Z93) -> -0.10761879
A95: CAC (paid, month 1) | B95: =SUM(C95:Z95) -> -6400 | C95: =IF(C$88=1,-$B$66*$B$73,0) -> -6400 | D95: =IF(D$88=1,-$B$66*$B$73,0) -> 0 | E95: =IF(E$88=1,-$B$66*$B$73,0) -> 0 | F95: =IF(F$88=1,-$B$66*$B$73,0) -> 0 | G95: =IF(G$88=1,-$B$66*$B$73,0) -> 0 | H95: =IF(H$88=1,-$B$66*$B$73,0) -> 0 | I95: =IF(I$88=1,-$B$66*$B$73,0) -> 0 | J95: =IF(J$88=1,-$B$66*$B$73,0) -> 0 | ... Z95: =IF(Z$88=1,-$B$66*$B$73,0) -> 0
A96: Net contribution after CAC | B96: =SUM(C96:Z96) -> -10561.062 | C96: =C94+C95 -> -10600.752 | D96: =D94+D95 -> -1.3632597 | E96: =E94+E95 -> 29.702396 | F96: =F94+F95 -> -1.082266 | G96: =G94+G95 -> -0.96429898 | H96: =H94+H95 -> -0.85919039 | I96: =I94+I95 -> 11.601285 | J96: =J94+J95 -> -0.68209493 | ... Z96: =Z94+Z95 -> -0.10761879
A97: CUMULATIVE contribution after CAC | C97: =C96 -> -10600.752 | D97: =C97+D96 -> -10602.115 | E97: =D97+E96 -> -10572.413 | F97: =E97+F96 -> -10573.495 | G97: =F97+G96 -> -10574.459 | H97: =G97+H96 -> -10575.318 | I97: =H97+I96 -> -10563.717 | J97: =I97+J96 -> -10564.399 | K97: =J97+K96 -> -10565.007 | ... Z97: =Y97+Z96 -> -10561.062
A98: Cumulative contribution before CAC, per customer | C98: =SUM($C94:C94)/$B$66 -> -42.007518 | D98: =SUM($C94:D94)/$B$66 -> -42.021151 | E98: =SUM($C94:E94)/$B$66 -> -41.724127 | F98: =SUM($C94:F94)/$B$66 -> -41.734949 | G98: =SUM($C94:G94)/$B$66 -> -41.744592 | H98: =SUM($C94:H94)/$B$66 -> -41.753184 | I98: =SUM($C94:I94)/$B$66 -> -41.637171 | J98: =SUM($C94:J94)/$B$66 -> -41.643992 | ... Z98: =SUM($C94:Z94)/$B$66 -> -41.610617
A99: Gross revenue (reference only - NOT used for LTV) | B99: =SUM(C99:Z99) -> 10084.851 | C99: =IF(C$88=1,$B$66*$B$84,0)+C89*$B$85+C90*$B$86 -> 7772.528 | D99: =IF(D$88=1,$B$66*$B$84,0)+D89*$B$85+D90*$B$86 -> 203.09454 | E99: =IF(E$88=1,$B$66*$B$84,0)+E89*$B$85+E90*$B$86 -> 530.46524 | F99: =IF(F$88=1,$B$66*$B$84,0)+F89*$B$85+F90*$B$86 -> 161.2329 | G99: =IF(G$88=1,$B$66*$B$84,0)+G89*$B$85+G90*$B$86 -> 143.65851 | H99: =IF(H$88=1,$B$66*$B$84,0)+H89*$B$85+H90*$B$86 -> 127.99973 | I99: =IF(I$88=1,$B$66*$B$84,0)+I89*$B$85+I90*$B$86 -> 253.85096 | J99: =IF(J$88=1,$B$66*$B$84,0)+J89*$B$85+J90*$B$86 -> 101.61656 | ... Z99: =IF(Z$88=1,$B$66*$B$84,0)+Z89*$B$85+Z90*$B$86 -> 16.03274
A100: Payback helper (month if cumulative >= 0, else 99) | C100: =IF(C97>=0,C$88,99) -> 99 | D100: =IF(D97>=0,D$88,99) -> 99 | E100: =IF(E97>=0,E$88,99) -> 99 | F100: =IF(F97>=0,F$88,99) -> 99 | G100: =IF(G97>=0,G$88,99) -> 99 | H100: =IF(H97>=0,H$88,99) -> 99 | I100: =IF(I97>=0,I$88,99) -> 99 | J100: =IF(J97>=0,J$88,99) -> 99 | ... Z100: =IF(Z97>=0,Z$88,99) -> 99
A102: FIRST-ORDER contribution before ads, per customer | B102: =$B$72 -> -42.007518
A103: FIRST-ORDER contribution after CAC, per customer | B103: =$B$72-$B$73 -> -106.00752
A104: Is the first order profitable after CAC? | B104: =IF(B103>=0,"YES - first order covers CAC","NO - first order loses money after CAC") -> NO - first order loses money after CAC
A105: Payback month (numeric; 99 = none within 24 months) | B105: =MIN(C100:Z100) -> 99
A106: Payback (display) | B106: =IF(B105>24,"No payback within 24 months","Month "&B105) -> No payback within 24 months
A107: 12-month contribution LTV per customer (before CAC) | B107: =SUM(C94:N94)/$B$66 -> -41.615141
A108: 24-month contribution LTV per customer (before CAC) | B108: =SUM(C94:Z94)/$B$66 -> -41.610617
A109: 12-month contribution LTV net of CAC | B109: =B107-$B$73 -> -105.61514
A110: 24-month contribution LTV net of CAC | B110: =B108-$B$73 -> -105.61062
...

Sheet Scenarios
A1: Scenarios: Pessimistic / Base / Optimistic computed side by side (independent of the selector)
A2: ="Every column is computed by its own engine group. First-order and cohort stage follow Inputs!D4: "&Inputs!$E$4 -> Every column is computed by its own engine group. First-order and cohort stage follow Inputs!D4: Private label (OEM + 3PL, CPA months 4-12)
A4: Metric | B4: Pessimistic | C4: Base | D4: Optimistic | E4: Unit
A5: CAT HOME - BASE CASE (corded stainless fountain + 90-day filter pack)
A6: Fountain price | B6: =Inputs!$D$11 -> 44.99 | C6: =Inputs!$E$11 -> 49.99 | D6: =Inputs!$F$11 -> 59.99 | E6: input
A7: Filter pack subscription price | B7: =Inputs!$D$14 -> 12.7415 | C7: =Inputs!$E$14 -> 15.291 | D7: =Inputs!$F$14 -> 15.741 | E7: input
A8: Paid CPA months 1-3 | B8: =Inputs!$D$111 -> 90 | C8: =Inputs!$E$111 -> 60 | D8: =Inputs!$F$111 -> 40 | E8: input
A9: Paid CPA months 4-12 | B9: =Inputs!$D$112 -> 65 | C9: =Inputs!$E$112 -> 45 | D9: =Inputs!$F$112 -> 32 | E9: input
A10: Subscription attach | B10: =Inputs!$D$133 -> 0.1 | C10: =Inputs!$E$133 -> 0.2 | D10: =Inputs!$F$133 -> 0.3 | E10: input
A11: Later-cycle churn, monthly equivalent | B11: =Inputs!$D$138 -> 0.096545278 | C11: =Inputs!$E$138 -> 0.05936264 | D11: =Inputs!$F$138 -> 0.0348241 | E11: input
A12: (a) Fountain - test stage: contribution before ads | B12: =Cat_UnitEcon!$H$50 -> -15.23547 | C12: =Cat_UnitEcon!$N$50 -> 3.70329 | D12: =Cat_UnitEcon!$T$50 -> 32.885555 | E12: $/order
A13: (a) Fountain - test stage: contribution after CPA | B13: =Cat_UnitEcon!$H$53 -> -105.23547 | C13: =Cat_UnitEcon!$N$53 -> -56.29671 | D13: =Cat_UnitEcon!$T$53 -> -7.114445 | E13: $/order
A14: (b) Fountain - private label: contribution before ads | B14: =Cat_UnitEcon!$I$50 -> -23.955647 | C14: =Cat_UnitEcon!$O$50 -> 2.0803188 | D14: =Cat_UnitEcon!$U$50 -> 26.347738 | E14: $/order
A15: (b) Fountain - private label: contribution after CPA | B15: =Cat_UnitEcon!$I$53 -> -88.955647 | C15: =Cat_UnitEcon!$O$53 -> -42.919681 | D15: =Cat_UnitEcon!$U$53 -> -5.6522623 | E15: $/order
A16: (c) Fountain + mat bundle - PL: contribution before ads | B16: =Cat_UnitEcon!$J$50 -> -17.964537 | C16: =Cat_UnitEcon!$P$50 -> 13.755829 | D16: =Cat_UnitEcon!$V$50 -> 43.351693 | E16: $/order
A17: (c) Fountain + mat bundle - PL: contribution after CPA | B17: =Cat_UnitEcon!$J$53 -> -82.964537 | C17: =Cat_UnitEcon!$P$53 -> -31.244171 | D17: =Cat_UnitEcon!$V$53 -> 11.351693 | E17: $/order
A18: (d) Filter subscription renewal: contribution before ads | B18: =Cat_UnitEcon!$K$50 -> -9.0517825 | C18: =Cat_UnitEcon!$Q$50 -> -3.419322 | D18: =Cat_UnitEcon!$W$50 -> 1.4220093 | E18: $/order
A19: (e) One-time filter repeat order: contribution before ads | B19: =Cat_UnitEcon!$L$50 -> -6.92695 | C19: =Cat_UnitEcon!$R$50 -> -1.79168 | D19: =Cat_UnitEcon!$X$50 -> 6.9772248 | E19: $/order
A20: Landed product cost, private label (per hero unit) | B20: =Cat_UnitEcon!$H$22 -> 41.200698 | C20: =Cat_UnitEcon!$N$22 -> 25.965622 | D20: =Cat_UnitEcon!$T$22 -> 15.60878 | E20: $/unit
A21: FIRST-ORDER contribution before ads (cohort mix) | B21: =Cat_Cohort!$B$102 -> -23.056981 | C21: =Cat_Cohort!$B$160 -> 4.9991963 | D21: =Cat_Cohort!$B$218 -> 32.299122 | E21: $/customer
A22: FIRST-ORDER contribution after CAC | B22: =Cat_Cohort!$B$103 -> -88.056981 | C22: =Cat_Cohort!$B$161 -> -40.000804 | D22: =Cat_Cohort!$B$219 -> 0.29912199 | E22: $/customer
A23: First-order contribution margin before ads | B23: =Cat_UnitEcon!$H$62 -> -0.52535562 | C23: =Cat_UnitEcon!$N$62 -> 0.095335328 | D23: =Cat_UnitEcon!$T$62 -> 0.48792744 | E23: % net rev
A24: 12-month contribution LTV (before CAC) | B24: =Cat_Cohort!$B$107 -> -25.481478 | C24: =Cat_Cohort!$B$165 -> 3.169286 | D24: =Cat_Cohort!$B$223 -> 37.008534 | E24: $/customer
A25: 24-month contribution LTV (before CAC) | B25: =Cat_Cohort!$B$108 -> -26.376075 | C25: =Cat_Cohort!$B$166 -> 2.1499872 | D25: =Cat_Cohort!$B$224 -> 39.086091 | E25: $/customer
A26: 12-month LTV net of CAC | B26: =Cat_Cohort!$B$109 -> -90.481478 | C26: =Cat_Cohort!$B$167 -> -41.830714 | D26: =Cat_Cohort!$B$225 -> 5.008534 | E26: $/customer
A27: 24-month LTV net of CAC | B27: =Cat_Cohort!$B$110 -> -91.376075 | C27: =Cat_Cohort!$B$168 -> -42.850013 | D27: =Cat_Cohort!$B$226 -> 7.0860906 | E27: $/customer
A28: 12-month LTV:CAC | B28: =Cat_Cohort!$B$111 -> -0.39202274 | C28: =Cat_Cohort!$B$169 -> 0.070428577 | D28: =Cat_Cohort!$B$227 -> 1.1565167 | E28: x
A29: 24-month LTV:CAC | B29: =Cat_Cohort!$B$112 -> -0.40578577 | C29: =Cat_Cohort!$B$170 -> 0.047777494 | D29: =Cat_Cohort!$B$228 -> 1.2214403 | E29: x
A30: Payback | B30: =Cat_Cohort!$B$106 -> No payback within 24 months | C30: =Cat_Cohort!$B$164 -> No payback within 24 months | D30: =Cat_Cohort!$B$222 -> Month 1
A31: Cumulative cohort contribution after CAC, month 24 (100 customers) | B31: =Cat_Cohort!$Z$97 -> -9137.6075 | C31: =Cat_Cohort!$Z$155 -> -4285.0013 | D31: =Cat_Cohort!$Z$213 -> 708.60906 | E31: $ per 100
A33: ESPRESSO - SHADOW CASE (De'Longhi Dedica 51mm upgrade kit + beans)
A34: Kit price | B34: =Inputs!$D$18 -> 74.99 | C34: =Inputs!$E$18 -> 84.99 | D34: =Inputs!$F$18 -> 99.99 | E34: input
A35: Bean shipment subscription price | B35: =Inputs!$D$22 -> 34.191 | C35: =Inputs!$E$22 -> 35.991 | D35: =Inputs!$F$22 -> 39.591 | E35: input
A36: Paid CPA months 1-3 | B36: =Inputs!$D$113 -> 85 | C36: =Inputs!$E$113 -> 60 | D36: =Inputs!$F$113 -> 40 | E36: input
A37: Paid CPA months 4-12 | B37: =Inputs!$D$114 -> 64 | C37: =Inputs!$E$114 -> 45 | D37: =Inputs!$F$114 -> 30 | E37: input
A38: Bean subscription attach | B38: =Inputs!$D$144 -> 0.08 | C38: =Inputs!$E$144 -> 0.15 | D38: =Inputs!$F$144 -> 0.25 | E38: input
A39: Monthly bean churn (voluntary) | B39: =Inputs!$D$146 -> 0.1 | C39: =Inputs!$E$146 -> 0.07 | D39: =Inputs!$F$146 -> 0.04 | E39: input
A40: (a) Kit - test stage: contribution before ads | B40: =Espresso_UnitEcon!$H$50 -> -40.326806 | C40: =Espresso_UnitEcon!$N$50 -> 14.62374 | D40: =Espresso_UnitEcon!$T$50 -> 59.053985 | E40: $/order
A41: (a) Kit - test stage: contribution after CPA | B41: =Espresso_UnitEcon!$H$53 -> -125.32681 | C41: =Espresso_UnitEcon!$N$53 -> -45.37626 | D41: =Espresso_UnitEcon!$T$53 -> 19.053985 | E41: $/order
A42: (b) Kit - private label: contribution before ads | B42: =Espresso_UnitEcon!$I$50 -> -42.010511 | C42: =Espresso_UnitEcon!$O$50 -> 20.431111 | D42: =Espresso_UnitEcon!$U$50 -> 54.638727 | E42: $/order
A43: (b) Kit - private label: contribution after CPA | B43: =Espresso_UnitEcon!$I$53 -> -106.01051 | C43: =Espresso_UnitEcon!$O$53 -> -24.568889 | D43: =Espresso_UnitEcon!$U$53 -> 24.638727 | E43: $/order
A44: (c) Kit + first beans - PL: contribution before ads | B44: =Espresso_UnitEcon!$J$50 -> -41.973103 | C44: =Espresso_UnitEcon!$P$50 -> 24.944542 | D44: =Espresso_UnitEcon!$V$50 -> 73.727518 | E44: $/order
A45: (c) Kit + first beans - PL: contribution after CPA | B45: =Espresso_UnitEcon!$J$53 -> -105.9731 | C45: =Espresso_UnitEcon!$P$53 -> -20.055458 | D45: =Espresso_UnitEcon!$V$53 -> 43.727518 | E45: $/order
A46: (d) Bean renewal: contribution before ads | B46: =Espresso_UnitEcon!$K$50 -> -0.229505 | C46: =Espresso_UnitEcon!$Q$50 -> 4.384378 | D46: =Espresso_UnitEcon!$W$50 -> 19.083019 | E46: $/order
A47: (e) One-time beans: contribution before ads | B47: =Espresso_UnitEcon!$L$50 -> 3.36055 | C47: =Espresso_UnitEcon!$R$50 -> 8.21542 | D47: =Espresso_UnitEcon!$X$50 -> 23.325855 | E47: $/order
A48: Landed product cost, private label (per hero unit) | B48: =Espresso_UnitEcon!$H$22 -> 77.19155 | C48: =Espresso_UnitEcon!$N$22 -> 34.657225 | D48: =Espresso_UnitEcon!$T$22 -> 20.929617 | E48: $/unit
A49: FIRST-ORDER contribution before ads (cohort mix) | B49: =Espresso_Cohort!$B$102 -> -42.007518 | C49: =Espresso_Cohort!$B$160 -> 21.108125 | D49: =Espresso_Cohort!$B$218 -> 59.410925 | E49: $/customer
A50: FIRST-ORDER contribution after CAC | B50: =Espresso_Cohort!$B$103 -> -106.00752 | C50: =Espresso_Cohort!$B$161 -> -23.891875 | D50: =Espresso_Cohort!$B$219 -> 29.410925 | E50: $/customer
A51: First-order contribution margin before ads | B51: =Espresso_UnitEcon!$H$62 -> -0.61171447 | C51: =Espresso_UnitEcon!$N$62 -> 0.25013965 | D51: =Espresso_UnitEcon!$T$62 -> 0.56133481 | E51: % net rev
A52: 12-month contribution LTV (before CAC) | B52: =Espresso_Cohort!$B$107 -> -41.615141 | C52: =Espresso_Cohort!$B$165 -> 27.155183 | D52: =Espresso_Cohort!$B$223 -> 104.88043 | E52: $/customer
A53: 24-month contribution LTV (before CAC) | B53: =Espresso_Cohort!$B$108 -> -41.610617 | C53: =Espresso_Cohort!$B$166 -> 29.072027 | D53: =Espresso_Cohort!$B$224 -> 129.50504 | E53: $/customer
A54: 12-month LTV net of CAC | B54: =Espresso_Cohort!$B$109 -> -105.61514 | C54: =Espresso_Cohort!$B$167 -> -17.844817 | D54: =Espresso_Cohort!$B$225 -> 74.88043 | E54: $/customer
A55: 24-month LTV net of CAC | B55: =Espresso_Cohort!$B$110 -> -105.61062 | C55: =Espresso_Cohort!$B$168 -> -15.927973 | D55: =Espresso_Cohort!$B$226 -> 99.505041 | E55: $/customer
A56: 12-month LTV:CAC | B56: =Espresso_Cohort!$B$111 -> -0.65023658 | C56: =Espresso_Cohort!$B$169 -> 0.60344851 | D56: =Espresso_Cohort!$B$227 -> 3.4960143 | E56: x
A57: 24-month LTV:CAC | B57: =Espresso_Cohort!$B$112 -> -0.65016589 | C57: =Espresso_Cohort!$B$170 -> 0.64604504 | D57: =Espresso_Cohort!$B$228 -> 4.3168347 | E57: x
A58: Payback | B58: =Espresso_Cohort!$B$106 -> No payback within 24 months | C58: =Espresso_Cohort!$B$164 -> No payback within 24 months | D58: =Espresso_Cohort!$B$222 -> Month 1
A59: Cumulative cohort contribution after CAC, month 24 (100 customers) | B59: =Espresso_Cohort!$Z$97 -> -10561.062 | C59: =Espresso_Cohort!$Z$155 -> -1592.7973 | D59: =Espresso_Cohort!$Z$213 -> 9950.5041 | E59: $ per 100
A61: Engine references: Cat_UnitEcon / Espresso_UnitEcon groups 2-4 and the matching engine blocks on Cat_Cohort / Espresso_Cohort.

Sheet Sensitivity
A1: Sensitivity: BASE case (Inputs column E) - one-at-a-time shocks and a CPA x attach two-way table
A2: Shock sizes are inputs (blue). Each shocked case is a full re-computation in its own engine group / cohort block.
A4: Shock settings
A5: Paid CPA change | C5: 0.3 | D5: ASSUMPTION | E5: Checkpoint 4 spec shock size
A6: Supplier unit cost (COGS) change | C6: 0.15 | D6: ASSUMPTION | E6: Checkpoint 4 spec shock size
A7: Postage change | C7: 0.2 | D7: ASSUMPTION | E7: Checkpoint 4 spec shock size
A8: Subscription attach change | C8: -0.5 | D8: ASSUMPTION | E8: Checkpoint 4 spec shock size
A9: Churn change (all churn rates) | C9: 0.5 | D9: ASSUMPTION | E9: Checkpoint 4 spec shock size
A10: Refund / replacement / returns multiplier | C10: 2 | D10: ASSUMPTION | E10: Checkpoint 4 spec shock size
A13: Case | B13: First-order contribution before ads | C13: Change vs base | D13: First-order contribution after CAC | E13: Change vs base | F13: 12-mo contribution LTV (before CAC) | G13: Change vs base | H13: 12-mo LTV net of CAC | I13: Change vs base | J13: 24-mo LTV net of CAC | K13: Payback month (99 = none) | L13: Payback (display)
A14: Base | B14: =Cat_Cohort!$B$160 -> 4.9991963 | C14: =B14-$B$14 -> 0 | D14: =Cat_Cohort!$B$161 -> -40.000804 | E14: =D14-$D$14 -> 0 | F14: =Cat_Cohort!$B$165 -> 3.169286 | G14: =F14-$F$14 -> 0 | H14: =Cat_Cohort!$B$167 -> -41.830714 | I14: =H14-$H$14 -> 0 | J14: =Cat_Cohort!$B$168 -> -42.850013 | K14: =Cat_Cohort!$B$163 -> 99 | L14: =Cat_Cohort!$B$164 -> No payback within 24 months
A15: CPA +30% | B15: =Cat_Cohort!$B$276 -> 4.9991963 | C15: =B15-$B$14 -> 0 | D15: =Cat_Cohort!$B$277 -> -53.500804 | E15: =D15-$D$14 -> -13.5 | F15: =Cat_Cohort!$B$281 -> 3.169286 | G15: =F15-$F$14 -> 0 | H15: =Cat_Cohort!$B$283 -> -55.330714 | I15: =H15-$H$14 -> -13.5 | J15: =Cat_Cohort!$B$284 -> -56.350013 | K15: =Cat_Cohort!$B$279 -> 99 | L15: =Cat_Cohort!$B$280 -> No payback within 24 months
A16: Supplier / COGS +15% | B16: =Cat_Cohort!$B$334 -> 2.3362214 | C16: =B16-$B$14 -> -2.662975 | D16: =Cat_Cohort!$B$335 -> -42.663779 | E16: =D16-$D$14 -> -2.662975 | F16: =Cat_Cohort!$B$339 -> 0.091280511 | G16: =F16-$F$14 -> -3.0780055 | H16: =Cat_Cohort!$B$341 -> -44.908719 | I16: =H16-$H$14 -> -3.0780055 | J16: =Cat_Cohort!$B$342 -> -46.12833 | K16: =Cat_Cohort!$B$337 -> 99 | L16: =Cat_Cohort!$B$338 -> No payback within 24 months
A17: Shipping +20% | B17: =Cat_Cohort!$B$392 -> 2.7551963 | C17: =B17-$B$14 -> -2.244 | D17: =Cat_Cohort!$B$393 -> -42.244804 | E17: =D17-$D$14 -> -2.244 | F17: =Cat_Cohort!$B$397 -> -0.20267987 | G17: =F17-$F$14 -> -3.3719659 | H17: =Cat_Cohort!$B$399 -> -45.20268 | I17: =H17-$H$14 -> -3.3719659 | J17: =Cat_Cohort!$B$400 -> -46.766385 | K17: =Cat_Cohort!$B$395 -> 99 | L17: =Cat_Cohort!$B$396 -> No payback within 24 months
A18: Subscription attach -50% | B18: =Cat_Cohort!$B$450 -> 4.9991963 | C18: =B18-$B$14 -> 0 | D18: =Cat_Cohort!$B$451 -> -40.000804 | E18: =D18-$D$14 -> 0 | F18: =Cat_Cohort!$B$455 -> 3.7330719 | G18: =F18-$F$14 -> 0.56378589 | H18: =Cat_Cohort!$B$457 -> -41.266928 | I18: =H18-$H$14 -> 0.56378589 | J18: =Cat_Cohort!$B$458 -> -41.85243 | K18: =Cat_Cohort!$B$453 -> 99 | L18: =Cat_Cohort!$B$454 -> No payback within 24 months
A19: Churn +50% | B19: =Cat_Cohort!$B$508 -> 4.9991963 | C19: =B19-$B$14 -> 0 | D19: =Cat_Cohort!$B$509 -> -40.000804 | E19: =D19-$D$14 -> 0 | F19: =Cat_Cohort!$B$513 -> 3.4788635 | G19: =F19-$F$14 -> 0.30957756 | H19: =Cat_Cohort!$B$515 -> -41.521136 | I19: =H19-$H$14 -> 0.30957756 | J19: =Cat_Cohort!$B$516 -> -42.122415 | K19: =Cat_Cohort!$B$511 -> 99 | L19: =Cat_Cohort!$B$512 -> No payback within 24 months
A20: Returns 2x | B20: =Cat_Cohort!$B$566 -> 0.99975265 | C20: =B20-$B$14 -> -3.9994437 | D20: =Cat_Cohort!$B$567 -> -44.000247 | E20: =D20-$D$14 -> -3.9994437 | F20: =Cat_Cohort!$B$571 -> -0.96793276 | G20: =F20-$F$14 -> -4.1372187 | H20: =Cat_Cohort!$B$573 -> -45.967933 | I20: =H20-$H$14 -> -4.1372187 | J20: =Cat_Cohort!$B$574 -> -47.052307 | K20: =Cat_Cohort!$B$569 -> 99 | L20: =Cat_Cohort!$B$570 -> No payback within 24 months
A23: Two-way tables (BASE case, cat). LTV(attach) = first-order contribution + attach x renewal contribution per subscriber + (1 - attach) x repeat rate x repeat contribution per occasional buyer; minus CPA. Closed form from the Base cohort block.
A24: Base first-order contribution before ads / customer | C24: =Cat_Cohort!$B$130 -> 4.9991963
A25: Renewal contribution per subscriber - 12 months / 24 months | C25: =Cat_Cohort!$B$173 -> -6.3401975 | D25: =Cat_Cohort!$B$176 -> -10.829871
A26: Repeat contribution per occasional buyer - 12 months / 24 months | C26: =Cat_Cohort!$B$174 -> -3.5116928 | D26: =Cat_Cohort!$B$177 -> -4.2702184
A27: Non-subscriber repeat rate / Base paid CAC | C27: =Cat_Cohort!$B$126 -> 0.2 | D27: =Cat_Cohort!$B$131 -> 45
A29: CPA factor (x base CAC) - inputs | C29: 0.6 | D29: 0.8 | E29: 1 | F29: 1.15 | G29: 1.3 | H29: 1.5 | I29: 2
A30: Attach rate axis - inputs | C30: 0 | D30: 0.05 | E30: 0.1 | F30: 0.2 | G30: 0.3 | H30: 0.4 | I30: 0.5
A32: Table 1: 12-month contribution LTV NET of CAC per customer ($): paid CPA (rows) x subscription attach (columns)
B33: CPA \ attach | C33: =C$30 -> 0 | D33: =D$30 -> 0.05 | E33: =E$30 -> 0.1 | F33: =F$30 -> 0.2 | G33: =G$30 -> 0.3 | H33: =H$30 -> 0.4 | I33: =I$30 -> 0.5
B34: =INDEX($C$29:$I$29,1,1)*$D$27 -> 27 | C34: =($C$24+C$33*$C$25+(1-C$33)*$C$27*$C$26)-$B34 -> -22.703142 | D34: =($C$24+D$33*$C$25+(1-D$33)*$C$27*$C$26)-$B34 -> -22.985035 | E34: =($C$24+E$33*$C$25+(1-E$33)*$C$27*$C$26)-$B34 -> -23.266928 | F34: =($C$24+F$33*$C$25+(1-F$33)*$C$27*$C$26)-$B34 -> -23.830714 | G34: =($C$24+G$33*$C$25+(1-G$33)*$C$27*$C$26)-$B34 -> -24.3945 | H34: =($C$24+H$33*$C$25+(1-H$33)*$C$27*$C$26)-$B34 -> -24.958286 | I34: =($C$24+I$33*$C$25+(1-I$33)*$C$27*$C$26)-$B34 -> -25.522072
B35: =INDEX($C$29:$I$29,1,2)*$D$27 -> 36 | C35: =($C$24+C$33*$C$25+(1-C$33)*$C$27*$C$26)-$B35 -> -31.703142 | D35: =($C$24+D$33*$C$25+(1-D$33)*$C$27*$C$26)-$B35 -> -31.985035 | E35: =($C$24+E$33*$C$25+(1-E$33)*$C$27*$C$26)-$B35 -> -32.266928 | F35: =($C$24+F$33*$C$25+(1-F$33)*$C$27*$C$26)-$B35 -> -32.830714 | G35: =($C$24+G$33*$C$25+(1-G$33)*$C$27*$C$26)-$B35 -> -33.3945 | H35: =($C$24+H$33*$C$25+(1-H$33)*$C$27*$C$26)-$B35 -> -33.958286 | I35: =($C$24+I$33*$C$25+(1-I$33)*$C$27*$C$26)-$B35 -> -34.522072
B36: =INDEX($C$29:$I$29,1,3)*$D$27 -> 45 | C36: =($C$24+C$33*$C$25+(1-C$33)*$C$27*$C$26)-$B36 -> -40.703142 | D36: =($C$24+D$33*$C$25+(1-D$33)*$C$27*$C$26)-$B36 -> -40.985035 | E36: =($C$24+E$33*$C$25+(1-E$33)*$C$27*$C$26)-$B36 -> -41.266928 | F36: =($C$24+F$33*$C$25+(1-F$33)*$C$27*$C$26)-$B36 -> -41.830714 | G36: =($C$24+G$33*$C$25+(1-G$33)*$C$27*$C$26)-$B36 -> -42.3945 | H36: =($C$24+H$33*$C$25+(1-H$33)*$C$27*$C$26)-$B36 -> -42.958286 | I36: =($C$24+I$33*$C$25+(1-I$33)*$C$27*$C$26)-$B36 -> -43.522072
B37: =INDEX($C$29:$I$29,1,4)*$D$27 -> 51.75 | C37: =($C$24+C$33*$C$25+(1-C$33)*$C$27*$C$26)-$B37 -> -47.453142 | D37: =($C$24+D$33*$C$25+(1-D$33)*$C$27*$C$26)-$B37 -> -47.735035 | E37: =($C$24+E$33*$C$25+(1-E$33)*$C$27*$C$26)-$B37 -> -48.016928 | F37: =($C$24+F$33*$C$25+(1-F$33)*$C$27*$C$26)-$B37 -> -48.580714 | G37: =($C$24+G$33*$C$25+(1-G$33)*$C$27*$C$26)-$B37 -> -49.1445 | H37: =($C$24+H$33*$C$25+(1-H$33)*$C$27*$C$26)-$B37 -> -49.708286 | I37: =($C$24+I$33*$C$25+(1-I$33)*$C$27*$C$26)-$B37 -> -50.272072
B38: =INDEX($C$29:$I$29,1,5)*$D$27 -> 58.5 | C38: =($C$24+C$33*$C$25+(1-C$33)*$C$27*$C$26)-$B38 -> -54.203142 | D38: =($C$24+D$33*$C$25+(1-D$33)*$C$27*$C$26)-$B38 -> -54.485035 | E38: =($C$24+E$33*$C$25+(1-E$33)*$C$27*$C$26)-$B38 -> -54.766928 | F38: =($C$24+F$33*$C$25+(1-F$33)*$C$27*$C$26)-$B38 -> -55.330714 | G38: =($C$24+G$33*$C$25+(1-G$33)*$C$27*$C$26)-$B38 -> -55.8945 | H38: =($C$24+H$33*$C$25+(1-H$33)*$C$27*$C$26)-$B38 -> -56.458286 | I38: =($C$24+I$33*$C$25+(1-I$33)*$C$27*$C$26)-$B38 -> -57.022072
B39: =INDEX($C$29:$I$29,1,6)*$D$27 -> 67.5 | C39: =($C$24+C$33*$C$25+(1-C$33)*$C$27*$C$26)-$B39 -> -63.203142 | D39: =($C$24+D$33*$C$25+(1-D$33)*$C$27*$C$26)-$B39 -> -63.485035 | E39: =($C$24+E$33*$C$25+(1-E$33)*$C$27*$C$26)-$B39 -> -63.766928 | F39: =($C$24+F$33*$C$25+(1-F$33)*$C$27*$C$26)-$B39 -> -64.330714 | G39: =($C$24+G$33*$C$25+(1-G$33)*$C$27*$C$26)-$B39 -> -64.8945 | H39: =($C$24+H$33*$C$25+(1-H$33)*$C$27*$C$26)-$B39 -> -65.458286 | I39: =($C$24+I$33*$C$25+(1-I$33)*$C$27*$C$26)-$B39 -> -66.022072
B40: =INDEX($C$29:$I$29,1,7)*$D$27 -> 90 | C40: =($C$24+C$33*$C$25+(1-C$33)*$C$27*$C$26)-$B40 -> -85.703142 | D40: =($C$24+D$33*$C$25+(1-D$33)*$C$27*$C$26)-$B40 -> -85.985035 | E40: =($C$24+E$33*$C$25+(1-E$33)*$C$27*$C$26)-$B40 -> -86.266928 | F40: =($C$24+F$33*$C$25+(1-F$33)*$C$27*$C$26)-$B40 -> -86.830714 | G40: =($C$24+G$33*$C$25+(1-G$33)*$C$27*$C$26)-$B40 -> -87.3945 | H40: =($C$24+H$33*$C$25+(1-H$33)*$C$27*$C$26)-$B40 -> -87.958286 | I40: =($C$24+I$33*$C$25+(1-I$33)*$C$27*$C$26)-$B40 -> -88.522072
A42: Table 2: 12-month contribution LTV : CAC (x)
B43: CPA \ attach | C43: =C$30 -> 0 | D43: =D$30 -> 0.05 | E43: =E$30 -> 0.1 | F43: =F$30 -> 0.2 | G43: =G$30 -> 0.3 | H43: =H$30 -> 0.4 | I43: =I$30 -> 0.5
B44: =INDEX($C$29:$I$29,1,1)*$D$27 -> 27 | C44: =IFERROR(($C$24+C$43*$C$25+(1-C$43)*$C$27*$C$26)/$B44,0) -> 0.15914288 | D44: =IFERROR(($C$24+D$43*$C$25+(1-D$43)*$C$27*$C$26)/$B44,0) -> 0.1487024 | E44: =IFERROR(($C$24+E$43*$C$25+(1-E$43)*$C$27*$C$26)/$B44,0) -> 0.13826192 | F44: =IFERROR(($C$24+F$43*$C$25+(1-F$43)*$C$27*$C$26)/$B44,0) -> 0.11738096 | G44: =IFERROR(($C$24+G$43*$C$25+(1-G$43)*$C$27*$C$26)/$B44,0) -> 0.096500004 | H44: =IFERROR(($C$24+H$43*$C$25+(1-H$43)*$C$27*$C$26)/$B44,0) -> 0.075619045 | I44: =IFERROR(($C$24+I$43*$C$25+(1-I$43)*$C$27*$C$26)/$B44,0) -> 0.054738086
B45: =INDEX($C$29:$I$29,1,2)*$D$27 -> 36 | C45: =IFERROR(($C$24+C$43*$C$25+(1-C$43)*$C$27*$C$26)/$B45,0) -> 0.11935716 | D45: =IFERROR(($C$24+D$43*$C$25+(1-D$43)*$C$27*$C$26)/$B45,0) -> 0.1115268 | E45: =IFERROR(($C$24+E$43*$C$25+(1-E$43)*$C$27*$C$26)/$B45,0) -> 0.10369644 | F45: =IFERROR(($C$24+F$43*$C$25+(1-F$43)*$C$27*$C$26)/$B45,0) -> 0.088035722 | G45: =IFERROR(($C$24+G$43*$C$25+(1-G$43)*$C$27*$C$26)/$B45,0) -> 0.072375003 | H45: =IFERROR(($C$24+H$43*$C$25+(1-H$43)*$C$27*$C$26)/$B45,0) -> 0.056714284 | I45: =IFERROR(($C$24+I$43*$C$25+(1-I$43)*$C$27*$C$26)/$B45,0) -> 0.041053564
B46: =INDEX($C$29:$I$29,1,3)*$D$27 -> 45 | C46: =IFERROR(($C$24+C$43*$C$25+(1-C$43)*$C$27*$C$26)/$B46,0) -> 0.095485728 | D46: =IFERROR(($C$24+D$43*$C$25+(1-D$43)*$C$27*$C$26)/$B46,0) -> 0.08922144 | E46: =IFERROR(($C$24+E$43*$C$25+(1-E$43)*$C$27*$C$26)/$B46,0) -> 0.082957153 | F46: =IFERROR(($C$24+F$43*$C$25+(1-F$43)*$C$27*$C$26)/$B46,0) -> 0.070428577 | G46: =IFERROR(($C$24+G$43*$C$25+(1-G$43)*$C$27*$C$26)/$B46,0) -> 0.057900002 | H46: =IFERROR(($C$24+H$43*$C$25+(1-H$43)*$C$27*$C$26)/$B46,0) -> 0.045371427 | I46: =IFERROR(($C$24+I$43*$C$25+(1-I$43)*$C$27*$C$26)/$B46,0) -> 0.032842851
B47: =INDEX($C$29:$I$29,1,4)*$D$27 -> 51.75 | C47: =IFERROR(($C$24+C$43*$C$25+(1-C$43)*$C$27*$C$26)/$B47,0) -> 0.083031068 | D47: =IFERROR(($C$24+D$43*$C$25+(1-D$43)*$C$27*$C$26)/$B47,0) -> 0.077583861 | E47: =IFERROR(($C$24+E$43*$C$25+(1-E$43)*$C$27*$C$26)/$B47,0) -> 0.072136655 | F47: =IFERROR(($C$24+F$43*$C$25+(1-F$43)*$C$27*$C$26)/$B47,0) -> 0.061242241 | G47: =IFERROR(($C$24+G$43*$C$25+(1-G$43)*$C$27*$C$26)/$B47,0) -> 0.050347828 | H47: =IFERROR(($C$24+H$43*$C$25+(1-H$43)*$C$27*$C$26)/$B47,0) -> 0.039453415 | I47: =IFERROR(($C$24+I$43*$C$25+(1-I$43)*$C$27*$C$26)/$B47,0) -> 0.028559001
B48: =INDEX($C$29:$I$29,1,5)*$D$27 -> 58.5 | C48: =IFERROR(($C$24+C$43*$C$25+(1-C$43)*$C$27*$C$26)/$B48,0) -> 0.07345056 | D48: =IFERROR(($C$24+D$43*$C$25+(1-D$43)*$C$27*$C$26)/$B48,0) -> 0.068631877 | E48: =IFERROR(($C$24+E$43*$C$25+(1-E$43)*$C$27*$C$26)/$B48,0) -> 0.063813194 | F48: =IFERROR(($C$24+F$43*$C$25+(1-F$43)*$C$27*$C$26)/$B48,0) -> 0.054175829 | G48: =IFERROR(($C$24+G$43*$C$25+(1-G$43)*$C$27*$C$26)/$B48,0) -> 0.044538463 | H48: =IFERROR(($C$24+H$43*$C$25+(1-H$43)*$C$27*$C$26)/$B48,0) -> 0.034901098 | I48: =IFERROR(($C$24+I$43*$C$25+(1-I$43)*$C$27*$C$26)/$B48,0) -> 0.025263732
B49: =INDEX($C$29:$I$29,1,6)*$D$27 -> 67.5 | C49: =IFERROR(($C$24+C$43*$C$25+(1-C$43)*$C$27*$C$26)/$B49,0) -> 0.063657152 | D49: =IFERROR(($C$24+D$43*$C$25+(1-D$43)*$C$27*$C$26)/$B49,0) -> 0.05948096 | E49: =IFERROR(($C$24+E$43*$C$25+(1-E$43)*$C$27*$C$26)/$B49,0) -> 0.055304769 | F49: =IFERROR(($C$24+F$43*$C$25+(1-F$43)*$C$27*$C$26)/$B49,0) -> 0.046952385 | G49: =IFERROR(($C$24+G$43*$C$25+(1-G$43)*$C$27*$C$26)/$B49,0) -> 0.038600001 | H49: =IFERROR(($C$24+H$43*$C$25+(1-H$43)*$C$27*$C$26)/$B49,0) -> 0.030247618 | I49: =IFERROR(($C$24+I$43*$C$25+(1-I$43)*$C$27*$C$26)/$B49,0) -> 0.021895234
B50: =INDEX($C$29:$I$29,1,7)*$D$27 -> 90 | C50: =IFERROR(($C$24+C$43*$C$25+(1-C$43)*$C$27*$C$26)/$B50,0) -> 0.047742864 | D50: =IFERROR(($C$24+D$43*$C$25+(1-D$43)*$C$27*$C$26)/$B50,0) -> 0.04461072 | E50: =IFERROR(($C$24+E$43*$C$25+(1-E$43)*$C$27*$C$26)/$B50,0) -> 0.041478576 | F50: =IFERROR(($C$24+F$43*$C$25+(1-F$43)*$C$27*$C$26)/$B50,0) -> 0.035214289 | G50: =IFERROR(($C$24+G$43*$C$25+(1-G$43)*$C$27*$C$26)/$B50,0) -> 0.028950001 | H50: =IFERROR(($C$24+H$43*$C$25+(1-H$43)*$C$27*$C$26)/$B50,0) -> 0.022685713 | I50: =IFERROR(($C$24+I$43*$C$25+(1-I$43)*$C$27*$C$26)/$B50,0) -> 0.016421426
A52: Table 3: 24-month contribution LTV NET of CAC per customer ($)
B53: CPA \ attach | C53: =C$30 -> 0 | D53: =D$30 -> 0.05 | E53: =E$30 -> 0.1 | F53: =F$30 -> 0.2 | G53: =G$30 -> 0.3 | H53: =H$30 -> 0.4 | I53: =I$30 -> 0.5
B54: =INDEX($C$29:$I$29,1,1)*$D$27 -> 27 | C54: =($C$24+C$53*$D$25+(1-C$53)*$C$27*$D$26)-$B54 -> -22.854847 | D54: =($C$24+D$53*$D$25+(1-D$53)*$C$27*$D$26)-$B54 -> -23.353639 | E54: =($C$24+E$53*$D$25+(1-E$53)*$C$27*$D$26)-$B54 -> -23.85243 | F54: =($C$24+F$53*$D$25+(1-F$53)*$C$27*$D$26)-$B54 -> -24.850013 | G54: =($C$24+G$53*$D$25+(1-G$53)*$C$27*$D$26)-$B54 -> -25.847595 | H54: =($C$24+H$53*$D$25+(1-H$53)*$C$27*$D$26)-$B54 -> -26.845178 | I54: =($C$24+I$53*$D$25+(1-I$53)*$C$27*$D$26)-$B54 -> -27.842761
B55: =INDEX($C$29:$I$29,1,2)*$D$27 -> 36 | C55: =($C$24+C$53*$D$25+(1-C$53)*$C$27*$D$26)-$B55 -> -31.854847 | D55: =($C$24+D$53*$D$25+(1-D$53)*$C$27*$D$26)-$B55 -> -32.353639 | E55: =($C$24+E$53*$D$25+(1-E$53)*$C$27*$D$26)-$B55 -> -32.85243 | F55: =($C$24+F$53*$D$25+(1-F$53)*$C$27*$D$26)-$B55 -> -33.850013 | G55: =($C$24+G$53*$D$25+(1-G$53)*$C$27*$D$26)-$B55 -> -34.847595 | H55: =($C$24+H$53*$D$25+(1-H$53)*$C$27*$D$26)-$B55 -> -35.845178 | I55: =($C$24+I$53*$D$25+(1-I$53)*$C$27*$D$26)-$B55 -> -36.842761
B56: =INDEX($C$29:$I$29,1,3)*$D$27 -> 45 | C56: =($C$24+C$53*$D$25+(1-C$53)*$C$27*$D$26)-$B56 -> -40.854847 | D56: =($C$24+D$53*$D$25+(1-D$53)*$C$27*$D$26)-$B56 -> -41.353639 | E56: =($C$24+E$53*$D$25+(1-E$53)*$C$27*$D$26)-$B56 -> -41.85243 | F56: =($C$24+F$53*$D$25+(1-F$53)*$C$27*$D$26)-$B56 -> -42.850013 | G56: =($C$24+G$53*$D$25+(1-G$53)*$C$27*$D$26)-$B56 -> -43.847595 | H56: =($C$24+H$53*$D$25+(1-H$53)*$C$27*$D$26)-$B56 -> -44.845178 | I56: =($C$24+I$53*$D$25+(1-I$53)*$C$27*$D$26)-$B56 -> -45.842761
B57: =INDEX($C$29:$I$29,1,4)*$D$27 -> 51.75 | C57: =($C$24+C$53*$D$25+(1-C$53)*$C$27*$D$26)-$B57 -> -47.604847 | D57: =($C$24+D$53*$D$25+(1-D$53)*$C$27*$D$26)-$B57 -> -48.103639 | E57: =($C$24+E$53*$D$25+(1-E$53)*$C$27*$D$26)-$B57 -> -48.60243 | F57: =($C$24+F$53*$D$25+(1-F$53)*$C$27*$D$26)-$B57 -> -49.600013 | G57: =($C$24+G$53*$D$25+(1-G$53)*$C$27*$D$26)-$B57 -> -50.597595 | H57: =($C$24+H$53*$D$25+(1-H$53)*$C$27*$D$26)-$B57 -> -51.595178 | I57: =($C$24+I$53*$D$25+(1-I$53)*$C$27*$D$26)-$B57 -> -52.592761
B58: =INDEX($C$29:$I$29,1,5)*$D$27 -> 58.5 | C58: =($C$24+C$53*$D$25+(1-C$53)*$C$27*$D$26)-$B58 -> -54.354847 | D58: =($C$24+D$53*$D$25+(1-D$53)*$C$27*$D$26)-$B58 -> -54.853639 | E58: =($C$24+E$53*$D$25+(1-E$53)*$C$27*$D$26)-$B58 -> -55.35243 | F58: =($C$24+F$53*$D$25+(1-F$53)*$C$27*$D$26)-$B58 -> -56.350013 | G58: =($C$24+G$53*$D$25+(1-G$53)*$C$27*$D$26)-$B58 -> -57.347595 | H58: =($C$24+H$53*$D$25+(1-H$53)*$C$27*$D$26)-$B58 -> -58.345178 | I58: =($C$24+I$53*$D$25+(1-I$53)*$C$27*$D$26)-$B58 -> -59.342761
B59: =INDEX($C$29:$I$29,1,6)*$D$27 -> 67.5 | C59: =($C$24+C$53*$D$25+(1-C$53)*$C$27*$D$26)-$B59 -> -63.354847 | D59: =($C$24+D$53*$D$25+(1-D$53)*$C$27*$D$26)-$B59 -> -63.853639 | E59: =($C$24+E$53*$D$25+(1-E$53)*$C$27*$D$26)-$B59 -> -64.35243 | F59: =($C$24+F$53*$D$25+(1-F$53)*$C$27*$D$26)-$B59 -> -65.350013 | G59: =($C$24+G$53*$D$25+(1-G$53)*$C$27*$D$26)-$B59 -> -66.347595 | H59: =($C$24+H$53*$D$25+(1-H$53)*$C$27*$D$26)-$B59 -> -67.345178 | I59: =($C$24+I$53*$D$25+(1-I$53)*$C$27*$D$26)-$B59 -> -68.342761
B60: =INDEX($C$29:$I$29,1,7)*$D$27 -> 90 | C60: =($C$24+C$53*$D$25+(1-C$53)*$C$27*$D$26)-$B60 -> -85.854847 | D60: =($C$24+D$53*$D$25+(1-D$53)*$C$27*$D$26)-$B60 -> -86.353639 | E60: =($C$24+E$53*$D$25+(1-E$53)*$C$27*$D$26)-$B60 -> -86.85243 | F60: =($C$24+F$53*$D$25+(1-F$53)*$C$27*$D$26)-$B60 -> -87.850013 | G60: =($C$24+G$53*$D$25+(1-G$53)*$C$27*$D$26)-$B60 -> -88.847595 | H60: =($C$24+H$53*$D$25+(1-H$53)*$C$27*$D$26)-$B60 -> -89.845178 | I60: =($C$24+I$53*$D$25+(1-I$53)*$C$27*$D$26)-$B60 -> -90.842761
A62: Check: Table 1 at base CPA (factor 1.0) and base attach should equal the Base row's 12-mo LTV net of CAC above.
A63: Closed-form value at base CPA and base attach | C63: =$C$24+Cat_Cohort!$B$125*$C$25+(1-Cat_Cohort!$B$125)*$C$27*$C$26-$D$27 -> -41.830714
A64: Difference vs cohort engine (should be 0) | C64: =ROUND(C63-H14,6) -> 0

Sheet Launch_Budget
A1: Launch_Budget: cash needed before the first private-label sale, runway and break-even (cat BASE CASE)
A2: ="Tier quantities from Inputs section O; unit costs from the SELECTED scenario ("&Inputs!$E$3&"). Tier chosen for GoNoGo: "&Inputs!$E$5 -> Tier quantities from Inputs section O; unit costs from the SELECTED scenario (Base). Tier chosen for GoNoGo: Lean
A4: Line item | C4: Lean | D4: Moderate | E4: Higher-capital | F4: Basis
A5: One-time costs before first private-label sale
A6: Samples (off-the-shelf x suppliers + express) + golden sample | C6: =Inputs!$D$171*(Inputs!$D$172+Inputs!$D$173)+Inputs!$D$174 -> 630 | D6: =Inputs!$E$171*(Inputs!$E$172+Inputs!$E$173)+Inputs!$E$174 -> 1440 | E6: =Inputs!$F$171*(Inputs!$F$172+Inputs!$F$173)+Inputs!$F$174 -> 2550 | F6: Incl. >=1 non-China OEM (client default)
A7: Certification tests: FCC Part 15B + Prop 65 + food-contact | C7: =Inputs!$G$49+Inputs!$G$50+Inputs!$G$51 -> 4650 | D7: =Inputs!$G$49+Inputs!$G$50+Inputs!$G$51 -> 4650 | E7: =Inputs!$G$49+Inputs!$G$50+Inputs!$G$51 -> 4650 | F7: Selected scenario lab prices
A8: Packaging design | C8: =Inputs!$D$175 -> 500 | D8: =Inputs!$E$175 -> 1500 | E8: =Inputs!$F$175 -> 3000
A9: Brand identity, site theme, launch creative setup | C9: =Inputs!$D$176 -> 500 | D9: =Inputs!$E$176 -> 2000 | E9: =Inputs!$F$176 -> 5000
A10: MOQ inventory - fountains (FOB incl. listed adapter) | C10: =Inputs!$D$177*(Inputs!$G$36+Inputs!$G$37) -> 5885 | D10: =Inputs!$E$177*(Inputs!$G$36+Inputs!$G$37) -> 8827.5 | E10: =Inputs!$F$177*(Inputs!$G$36+Inputs!$G$37) -> 11770
A11: Inventory - filters for US stock | C11: =Inputs!$D$178*Inputs!$G$56 -> 490 | D11: =Inputs!$E$178*Inputs!$G$56 -> 784 | E11: =Inputs!$F$178*Inputs!$G$56 -> 1470 | F11: The one US-stocked consumable line
A12: Inventory - litter mats | C12: =Inputs!$D$179*Inputs!$G$53 -> 0 | D12: =Inputs!$E$179*Inputs!$G$53 -> 600 | E12: =Inputs!$F$179*Inputs!$G$53 -> 1500
A13: Retail packaging (fountain boxes, filter pouches) | C13: =Inputs!$D$177*Inputs!$G$48+Inputs!$D$178/Inputs!$G$15*Inputs!$G$59 -> 533.33333 | D13: =Inputs!$E$177*Inputs!$G$48+Inputs!$E$178/Inputs!$G$15*Inputs!$G$59 -> 803.33333 | E13: =Inputs!$F$177*Inputs!$G$48+Inputs!$F$178/Inputs!$G$15*Inputs!$G$59 -> 1100
A14: International freight (LCL fountains/mats; filters) | C14: =Inputs!$D$177*Inputs!$G$38+Inputs!$D$178/Inputs!$G$15*Inputs!$G$58+Inputs!$D$179*Inputs!$G$55 -> 1916.6667 | D14: =Inputs!$E$177*Inputs!$G$38+Inputs!$E$178/Inputs!$G$15*Inputs!$G$58+Inputs!$E$179*Inputs!$G$55 -> 3051.6667 | E14: =Inputs!$F$177*Inputs!$G$38+Inputs!$F$178/Inputs!$G$15*Inputs!$G$58+Inputs!$F$179*Inputs!$G$55 -> 4400
A15: Duties (Section 301 stack) | C15: =C10*Inputs!$G$39+C11*Inputs!$G$57+C12*Inputs!$G$54 -> 2390.625 | D15: =D10*Inputs!$G$39+D11*Inputs!$G$57+D12*Inputs!$G$54 -> 3859.3125 | E15: =E10*Inputs!$G$39+E11*Inputs!$G$57+E12*Inputs!$G$54 -> 5602.5
A16: Customs entry: broker + ISF + bond + MPF + HMF (one consolidated entry) | C16: =Inputs!$G$41+Inputs!$G$42+Inputs!$G$43+MAX(Inputs!$G$45,MIN(Inputs!$G$46,Inputs!$G$44*(C10+C11+C12)))+Inputs!$G$47*(C10+C11+C12) -> 316.54875 | D16: =Inputs!$G$41+Inputs!$G$42+Inputs!$G$43+MAX(Inputs!$G$45,MIN(Inputs!$G$46,Inputs!$G$44*(D10+D11+D12)))+Inputs!$G$47*(D10+D11+D12) -> 323.13701 | E16: =Inputs!$G$41+Inputs!$G$42+Inputs!$G$43+MAX(Inputs!$G$45,MIN(Inputs!$G$46,Inputs!$G$44*(E10+E11+E12)))+Inputs!$G$47*(E10+E11+E12) -> 344.48436
A17: 3PL setup/integration + receiving | C17: =Inputs!$G$98+Inputs!$G$95*Inputs!$G$97 -> 639.56 | D17: =Inputs!$G$98+Inputs!$G$95*Inputs!$G$97 -> 639.56 | E17: =Inputs!$G$98+Inputs!$G$95*Inputs!$G$97 -> 639.56
A18: Custom filter-frame mold | C18: =Inputs!$D$180 -> 0 | D18: =Inputs!$E$180 -> 0 | E18: =Inputs!$F$180 -> 4000
A19: Subtotal one-time | C19: =SUM(C6:C18) -> 18451.734 | D19: =SUM(D6:D18) -> 28478.51 | E19: =SUM(E6:E18) -> 46026.544
A20: Contingency | C20: =Inputs!$D$187*C19 -> 1845.1734 | D20: =Inputs!$E$187*D19 -> 4271.7764 | E20: =Inputs!$F$187*E19 -> 6903.9817
A21: TOTAL ONE-TIME COSTS | C21: =C19+C20 -> 20296.907 | D21: =D19+D20 -> 32750.286 | E21: =E19+E20 -> 52930.526
A23: Monthly fixed costs - test stage (before first private-label sale)
A24: Shopify + AutoDS + Klaviyo + reviews + subscription app | C24: =Inputs!$G$152+Inputs!$G$153+Inputs!$G$154+Inputs!$G$155+Inputs!$G$156 -> 123.75 | D24: =Inputs!$G$152+Inputs!$G$153+Inputs!$G$154+Inputs!$G$155+Inputs!$G$156 -> 123.75 | E24: =Inputs!$G$152+Inputs!$G$153+Inputs!$G$154+Inputs!$G$155+Inputs!$G$156 -> 123.75
A25: Insurance (GL + product liability) | C25: =Inputs!$G$157 -> 100 | D25: =Inputs!$G$157 -> 100 | E25: =Inputs!$G$157 -> 100
A26: UGC creative (videos x unit cost x pet premium) | C26: =Inputs!$D$184*Inputs!$G$125*(1+Inputs!$G$126) -> 920 | D26: =Inputs!$E$184*Inputs!$G$125*(1+Inputs!$G$126) -> 1840 | E26: =Inputs!$F$184*Inputs!$G$125*(1+Inputs!$G$126) -> 2760
A27: Total monthly fixed - test stage | C27: =SUM(C24:C26) -> 1143.75 | D27: =SUM(D24:D26) -> 2063.75 | E27: =SUM(E24:E26) -> 2983.75
A29: Monthly fixed costs - after first private-label sale
A30: Shopify + Klaviyo + reviews + subscription app (AutoDS dropped) | C30: =Inputs!$G$152+Inputs!$G$154+Inputs!$G$155+Inputs!$G$156 -> 83.95 | D30: =Inputs!$G$152+Inputs!$G$154+Inputs!$G$155+Inputs!$G$156 -> 83.95 | E30: =Inputs!$G$152+Inputs!$G$154+Inputs!$G$155+Inputs!$G$156 -> 83.95
A31: Insurance | C31: =Inputs!$G$157 -> 100 | D31: =Inputs!$G$157 -> 100 | E31: =Inputs!$G$157 -> 100
A32: UGC creative | C32: =Inputs!$D$184*Inputs!$G$125*(1+Inputs!$G$126) -> 920 | D32: =Inputs!$E$184*Inputs!$G$125*(1+Inputs!$G$126) -> 1840 | E32: =Inputs!$F$184*Inputs!$G$125*(1+Inputs!$G$126) -> 2760
A33: 3PL storage (pallets x rate) | C33: =Inputs!$G$95*Inputs!$G$94 -> 75 | D33: =Inputs!$G$95*Inputs!$G$94 -> 75 | E33: =Inputs!$G$95*Inputs!$G$94 -> 75
A34: Planned new paid customers per month (post-PL ad budget / CPA m4-12) | C34: =Inputs!$D$185/Inputs!$G$112 -> 33.333333 | D34: =Inputs!$E$185/Inputs!$G$112 -> 66.666667 | E34: =Inputs!$F$185/Inputs!$G$112 -> 133.33333
A35: 3PL minimum shortfall (minimum less expected pick/pack fees) | C35: =MAX(0,Inputs!$G$96-C34*(Inputs!$G$88+Inputs!$G$90)*(1+Inputs!$G$92)) -> 330 | D35: =MAX(0,Inputs!$G$96-D34*(Inputs!$G$88+Inputs!$G$90)*(1+Inputs!$G$92)) -> 160 | E35: =MAX(0,Inputs!$G$96-E34*(Inputs!$G$88+Inputs!$G$90)*(1+Inputs!$G$92)) -> 0 | F35: Rough: first orders only
A36: Total monthly fixed - after PL launch | C36: =C30+C31+C32+C33+C35 -> 1508.95 | D36: =D30+D31+D32+D33+D35 -> 2258.95 | E36: =E30+E31+E32+E33+E35 -> 3018.95
A38: Advertising
A39: Test ad budget (AliExpress creative test) | C39: =Inputs!$D$181*Inputs!$D$182 -> 3000 | D39: =Inputs!$E$181*Inputs!$E$182 -> 6000 | E39: =Inputs!$F$181*Inputs!$F$182 -> 12000
A40: Post-PL monthly ad budget | C40: =Inputs!$D$185 -> 1500 | D40: =Inputs!$E$185 -> 3000 | E40: =Inputs!$F$185 -> 6000
A42: Cash needed and runway
A43: Fixed costs until first PL sale (monthly fixed x months to PL) | C43: =C27*Inputs!$D$183 -> 5718.75 | D43: =D27*Inputs!$E$183 -> 10318.75 | E43: =E27*Inputs!$F$183 -> 11935
A44: Test-stage first orders (test ad budget / CPA m1-3) | C44: =C39/Inputs!$G$111 -> 50 | D44: =D39/Inputs!$G$111 -> 100 | E44: =E39/Inputs!$G$111 -> 200
A45: Contribution before ads recovered from test orders | C45: =C44*Cat_UnitEcon!$B$50 -> 185.1645 | D45: =D44*Cat_UnitEcon!$B$50 -> 370.329 | E45: =E44*Cat_UnitEcon!$B$50 -> 740.658 | F45: Selected (a) contribution before ads
A46: TOTAL CASH NEEDED BEFORE FIRST PRIVATE-LABEL SALE | C46: =C21+C43+C39-C45 -> 28830.493 | D46: =D21+D43+D39-D45 -> 48698.707 | E46: =E21+E43+E39-E45 -> 76124.868
A47: Cash available (assumption) | C47: =Inputs!$D$186 -> 15000 | D47: =Inputs!$E$186 -> 30000 | E47: =Inputs!$F$186 -> 60000
A48: Cash remaining at first PL sale | C48: =C47-C46 -> -13830.493 | D48: =D47-D46 -> -18698.707 | E48: =E47-E46 -> -16124.868
A49: Months of runway at launch (cash less one-time costs, at test-stage burn) | C49: =MAX(0,IFERROR((C47-C21)/(C27+Inputs!$D$181),0)) -> 0 | D49: =MAX(0,IFERROR((D47-D21)/(D27+Inputs!$E$181),0)) -> 0 | E49: =MAX(0,IFERROR((E47-E21)/(E27+Inputs!$F$181),0)) -> 1.0122748 | F49: 0 = one-time costs alone exceed cash
A50: Certification amortization inside per-fountain contribution (added back: its cash is already in one-time costs) | C50: =Cat_UnitEcon!$B$21 -> 4.65 | D50: =Cat_UnitEcon!$B$21 -> 4.65 | E50: =Cat_UnitEcon!$B$21 -> 4.65 | F50: FIX: avoids double-counting certification
A51: Post-PL monthly net burn (fixed + ads - first-order cash contribution; repeats ignored) | C51: =C36+C40-C34*(Cat_UnitEcon!$B$57+C50) -> 2687.3101 | D51: =D36+D40-D34*(Cat_UnitEcon!$B$57+D50) -> 4615.6702 | E51: =E36+E40-E34*(Cat_UnitEcon!$B$57+E50) -> 7732.3905 | F51: Cash basis; conservative: excludes renewals
A52: Months of runway after first PL sale (999 = self-funding; 0 = cash already exhausted) | C52: =IF(C48<=0,0,IF(C51<=0,999,C48/C51)) -> 0 | D52: =IF(D48<=0,0,IF(D51<=0,999,D48/D51)) -> 0 | E52: =IF(E48<=0,0,IF(E51<=0,999,E48/E51)) -> 0
A54: Rough break-even monthly volume (selected scenario)
A55: First orders/month to cover post-PL fixed costs IF acquisition were free | C55: =IF(Cat_UnitEcon!$B$57+C50>0,C36/(Cat_UnitEcon!$B$57+C50),"n/a: first order loses cash before ads") -> 156.3809 | D55: =IF(Cat_UnitEcon!$B$57+D50>0,D36/(Cat_UnitEcon!$B$57+D50),"n/a: first order loses cash before ads") -> 234.10758 | E55: =IF(Cat_UnitEcon!$B$57+E50>0,E36/(Cat_UnitEcon!$B$57+E50),"n/a: first order loses cash before ads") -> 312.87062 | F55: Cash basis (certification already funded)
A56: New paid customers/month to cover fixed costs (steady state, 12-mo LTV net of CAC, cash basis) | C56: =IF(Cat_Cohort!$B$49+C50>0,C36/(Cat_Cohort!$B$49+C50),"Not reachable: 12-mo cash LTV < CAC") -> Not reachable: 12-mo cash LTV < CAC | D56: =IF(Cat_Cohort!$B$49+D50>0,D36/(Cat_Cohort!$B$49+D50),"Not reachable: 12-mo cash LTV < CAC") -> Not reachable: 12-mo cash LTV < CAC | E56: =IF(Cat_Cohort!$B$49+E50>0,E36/(Cat_Cohort!$B$49+E50),"Not reachable: 12-mo cash LTV < CAC") -> Not reachable: 12-mo cash LTV < CAC | F56: Cash basis (certification already funded)
A57: Equivalent total orders/month (new + repeat + renewals) | C57: =IF(ISNUMBER(C56),C56*Cat_Cohort!$B$57,"n/a") -> n/a | D57: =IF(ISNUMBER(D56),D56*Cat_Cohort!$B$57,"n/a") -> n/a | E57: =IF(ISNUMBER(E56),E56*Cat_Cohort!$B$57,"n/a") -> n/a
A58: Implied monthly ad spend at break-even volume | C58: =IF(ISNUMBER(C56),C56*Inputs!$G$112,"n/a") -> n/a | D58: =IF(ISNUMBER(D56),D56*Inputs!$G$112,"n/a") -> n/a | E58: =IF(ISNUMBER(E56),E56*Inputs!$G$112,"n/a") -> n/a
A60: Espresso SHADOW case comparison: core one-time cash for a first private-label kit run (selected scenario)
A61: Kit inventory (MOQ x OEM kit FOB) | C61: =Inputs!$G$68*Inputs!$G$65 -> 3860 | D61: =Inputs!$G$68*Inputs!$G$65 -> 3860 | E61: =Inputs!$G$68*Inputs!$G$65 -> 3860
A62: Freight + duty + customs entry | C62: =Inputs!$G$68*Inputs!$G$67+C61*Inputs!$G$66+Inputs!$G$41+Inputs!$G$42+Inputs!$G$43+MAX(Inputs!$G$45,MIN(Inputs!$G$46,Inputs!$G$44*C61))+Inputs!$G$47*C61 -> 2211.445 | D62: =Inputs!$G$68*Inputs!$G$67+D61*Inputs!$G$66+Inputs!$G$41+Inputs!$G$42+Inputs!$G$43+MAX(Inputs!$G$45,MIN(Inputs!$G$46,Inputs!$G$44*D61))+Inputs!$G$47*D61 -> 2211.445 | E62: =Inputs!$G$68*Inputs!$G$67+E61*Inputs!$G$66+Inputs!$G$41+Inputs!$G$42+Inputs!$G$43+MAX(Inputs!$G$45,MIN(Inputs!$G$46,Inputs!$G$44*E61))+Inputs!$G$47*E61 -> 2211.445
A63: Prop 65 (lead in brass) + food-contact tests | C63: =Inputs!$G$50+Inputs!$G$51 -> 1650 | D63: =Inputs!$G$50+Inputs!$G$51 -> 1650 | E63: =Inputs!$G$50+Inputs!$G$51 -> 1650
A64: Samples (same tier logic) | C64: =C6 -> 630 | D64: =D6 -> 1440 | E64: =E6 -> 2550
A65: Espresso core one-time total (excl. brand, packaging design, contingency) | C65: =SUM(C61:C64) -> 8351.445 | D65: =SUM(D61:D64) -> 9161.445 | E65: =SUM(E61:E64) -> 10271.445

Sheet GoNoGo
A1: GoNoGo: proposed financial go/no-go gates, computed from the model (SELECTED scenario)
A2: ="Scenario: "&Inputs!$E$3&" | stage: "&Inputs!$E$4&" | launch tier: "&Inputs!$E$5&". Thresholds are analyst proposals (Inputs section N)." -> Scenario: Base | stage: Private label (OEM + 3PL, CPA months 4-12) | launch tier: Lean. Thresholds are analyst proposals (Inputs section N).
A4: Gate | B4: Cat: GO threshold | C4: Cat: CONDITIONAL threshold | D4: Cat: model value | E4: Cat status | F4: Espresso: GO threshold | G4: Espresso: CONDITIONAL threshold | H4: Espresso: model value | I4: Espresso status | J4: How it is computed
A5: 1. Private-label CPA ceiling (paid CPA months 4-12) | B5: =INDEX(Cat_Cohort!$C$38:$Z$38,1,Inputs!$G$160) -> 3.620353 | C5: =MAX(B5,INDEX(Cat_Cohort!$C$38:$Z$38,1,Inputs!$G$161)) -> 3.620353 | D5: =Inputs!$G$112 -> 45 | E5: =IF(D5<=B5,"GO",IF(D5<=C5,"CONDITIONAL","NO-GO")) -> NO-GO | F5: =INDEX(Espresso_Cohort!$C$38:$Z$38,1,Inputs!$G$160) -> 26.237766 | G5: =MAX(F5,INDEX(Espresso_Cohort!$C$38:$Z$38,1,Inputs!$G$161)) -> 27.155183 | H5: =Inputs!$G$114 -> 45 | I5: =IF(H5<=F5,"GO",IF(H5<=G5,"CONDITIONAL","NO-GO")) -> NO-GO | J5: Ceiling = cumulative contribution before CAC per customer by the GO payback month (9) / max payback month (12, floored at the GO ceiling). Payback <= N months exactly when CAC <= this value. Cohort uses the stage in Inputs!D4.
A6: 2. Test-stage CPA ceiling (months 1-3 creative test) | B6: =B5*Inputs!$G$111/Inputs!$G$112 -> 4.8271374 | C6: =C5*Inputs!$G$111/Inputs!$G$112 -> 4.8271374 | D6: =Inputs!$G$111 -> 60 | E6: =IF(D6<=B6,"GO",IF(D6<=C6,"CONDITIONAL","NO-GO")) -> NO-GO | F6: =F5*Inputs!$G$113/Inputs!$G$114 -> 34.983687 | G6: =G5*Inputs!$G$113/Inputs!$G$114 -> 36.206911 | H6: =Inputs!$G$113 -> 60 | I6: =IF(H6<=F6,"GO",IF(H6<=G6,"CONDITIONAL","NO-GO")) -> NO-GO | J6: Gate 1 ceiling grossed up by the assumed learning improvement (CPA m1-3 / CPA m4-12): a test CPA above this cannot reach the private-label ceiling even after pixel learning. The test measures creative, not margin.
A7: 3. Test-stage cash break-even CPA (information) | B7: =Cat_UnitEcon!$B$50 -> 3.70329 | C7: =Cat_UnitEcon!$B$50 -> 3.70329 | D7: =Inputs!$G$111 -> 60 | E7: =IF(D7<=B7,"GO","INFO: test loses cash per order") -> INFO: test loses cash per order | F7: =Espresso_UnitEcon!$B$50 -> 14.62374 | G7: =Espresso_UnitEcon!$B$50 -> 14.62374 | H7: =Inputs!$G$113 -> 60 | I7: =IF(H7<=F7,"GO","INFO: test loses cash per order") -> INFO: test loses cash per order | J7: Contribution before ads on the AliExpress test order (a). Above it, every test order loses cash; expected and capped by the test budget.
A8: 4. Minimum first-order contribution margin before ads | B8: =Inputs!$G$164 -> 0.35 | C8: =Inputs!$G$165 -> 0.25 | D8: =Cat_UnitEcon!$B$62 -> 0.095335328 | E8: =IF(D8>=B8,"GO",IF(D8>=C8,"CONDITIONAL","NO-GO")) -> NO-GO | F8: =Inputs!$G$164 -> 0.35 | G8: =Inputs!$G$165 -> 0.25 | H8: =Espresso_UnitEcon!$B$62 -> 0.25013965 | I8: =IF(H8>=F8,"GO",IF(H8>=G8,"CONDITIONAL","NO-GO")) -> CONDITIONAL | J8: First-order (cohort mix) contribution before ads / net revenue.
